Workbook

Sheet LEIA-ME
A1: Base de dados — Painel de Gestão de Leitos · Hospital Regional Horrara
A2: Dados fictícios para demonstração. Nenhum paciente, profissional ou valor é real.
A4: Data de referência (censo) | B4: 46314.292
A6: Período de análise | B6: 20/09/2026 a 19/10/2026 (30 dias). O retrato dos leitos (fLeitosCenso) é o censo de 19/10/2026 às 7h.
A7: Modelo | B7: Modelo estrela: tabelas com prefixo d são dimensões (cadastros) e com prefixo f são fatos (medições).
A8: Chave principal | B8: id_unidade (sigla da unidade) liga quase todas as tabelas; id_leito, id_procedimento, id_motivo e id_componente completam o modelo.
A9: Percentuais | B9: Gravados em fração (0,85 = 85%), com formato de porcentagem.
A10: Cores | B10: Azul: valor digitado que pode ser alterado. Fundo amarelo: data de referência usada nas fórmulas. Colunas com fórmula estão indicadas no Dicionario.
A11: Recálculo | B11: As fórmulas são recalculadas ao abrir o arquivo. Altere B4 para simular outro momento do censo.
A12: Conferência | B12: A aba Conferencia recalcula os principais indicadores a partir das tabelas e compara com os valores exibidos no painel.
A14: Aba | B14: Granularidade | C14: Linhas
A15: dUnidade | B15: unidade de internação | C15: 10
A16: dLeito | B16: leito | C16: 230
A17: dCalendario | B17: dia (últimos 30 dias) | C17: 30
A18: dProcedimento | B18: procedimento × unidade | C18: 36
A19: dMotivoDesocupacao | B19: motivo de atraso na desocupação | C19: 8
A20: dComponenteCusto | B20: componente da diária | C20: 5
A21: fCensoDiario | B21: unidade × dia | C21: 300
A22: fLeitosCenso | B22: leito no censo de 19/10/2026 às 7h | C22: 230
A23: fSaidas | B23: saída de paciente | C23: 1006
A24: fSolicitacoes | B24: pedido de leito ao NIR | C24: 831
A25: fCustoDiaria | B25: unidade × componente da diária | C25: 50
A26: fAtrasosDesocupacao | B26: episódio de atraso na desocupação | C26: 181
A27: dMetas | B27: indicador estratégico | C27: 12

Sheet dUnidade
A1: id_unidade | B1: unidade | C1: tipo_leito | D1: leitos_instalados | E1: meta_taxa_ocupacao | F1: meta_media_permanencia | G1: custo_diaria | H1: receita_media_aih
A2: CM | B2: Clínica Médica | C2: Enfermaria clínica | D2: 60 | E2: 0.85 | F2: 6.5 | G2: 1180 | H2: 1850
A3: CC | B3: Clínica Cirúrgica | C3: Enfermaria cirúrgica | D3: 40 | E3: 0.85 | F3: 4.5 | G3: 1290 | H3: 2900
A4: ORT | B4: Ortopedia/Traumatologia | C4: Enfermaria cirúrgica | D4: 24 | E4: 0.85 | F4: 5 | G4: 1240 | H4: 4300
A5: UTI | B5: UTI Adulto | C5: Terapia intensiva adulto | D5: 20 | E5: 0.9 | F5: 7 | G5: 3950 | H5: 7800
A6: UCI | B6: Semi-intensiva (UCI) | C6: Cuidados intermediários | D6: 10 | E6: 0.85 | F6: 5 | G6: 2280 | H6: 3100
A7: PED | B7: Pediatria | C7: Pediatria | D7: 20 | E7: 0.8 | F7: 4.5 | G7: 1120 | H7: 1500
A8: MAT | B8: Maternidade | C8: Obstetrícia | D8: 26 | E8: 0.8 | F8: 2.5 | G8: 980 | H8: 1100
A9: UTIN | B9: UTI Neonatal | C9: Terapia intensiva neonatal | D9: 10 | E9: 0.9 | F9: 12 | G9: 4150 | H9: 9600
A10: ONC | B10: Oncologia | C10: Oncologia | D10: 12 | E10: 0.85 | F10: 8 | G10: 1650 | H10: 2400
A11: INF | B11: Infectologia/Isolamento | C11: Isolamento | D11: 8 | E11: 0.8 | F11: 9 | G11: 1720 | H11: 3000

Sheet dLeito
A1: id_leito | B1: id_unidade | C1: ala | D1: numero
A2: CM-A01 | B2: CM | C2: A | D2: 1
A3: CM-A02 | B3: CM | C3: A | D3: 2
A4: CM-A03 | B4: CM | C4: A | D4: 3
A5: CM-A04 | B5: CM | C5: A | D5: 4
A6: CM-A05 | B6: CM | C6: A | D6: 5
A7: CM-A06 | B7: CM | C7: A | D7: 6
A8: CM-A07 | B8: CM | C8: A | D8: 7
A9: CM-A08 | B9: CM | C9: A | D9: 8
A10: CM-A09 | B10: CM | C10: A | D10: 9
A11: CM-A10 | B11: CM | C11: A | D11: 10
A12: CM-A11 | B12: CM | C12: A | D12: 11
A13: CM-A12 | B13: CM | C13: A | D13: 12
... A231: INF-B08 | B231: INF | C231: B | D231: 8

Sheet dCalendario
A1: data | B1: dia | C1: mes | D1: nome_mes | E1: ano | F1: dia_semana | G1: nome_dia | H1: fim_de_semana
A2: 46285 | B2: 20 | C2: 9 | D2: setembro | E2: 2026 | F2: 7 | G2: domingo | H2: Sim
A3: 46286 | B3: 21 | C3: 9 | D3: setembro | E3: 2026 | F3: 1 | G3: segunda-feira | H3: Não
A4: 46287 | B4: 22 | C4: 9 | D4: setembro | E4: 2026 | F4: 2 | G4: terça-feira | H4: Não
A5: 46288 | B5: 23 | C5: 9 | D5: setembro | E5: 2026 | F5: 3 | G5: quarta-feira | H5: Não
A6: 46289 | B6: 24 | C6: 9 | D6: setembro | E6: 2026 | F6: 4 | G6: quinta-feira | H6: Não
A7: 46290 | B7: 25 | C7: 9 | D7: setembro | E7: 2026 | F7: 5 | G7: sexta-feira | H7: Não
A8: 46291 | B8: 26 | C8: 9 | D8: setembro | E8: 2026 | F8: 6 | G8: sábado | H8: Sim
A9: 46292 | B9: 27 | C9: 9 | D9: setembro | E9: 2026 | F9: 7 | G9: domingo | H9: Sim
A10: 46293 | B10: 28 | C10: 9 | D10: setembro | E10: 2026 | F10: 1 | G10: segunda-feira | H10: Não
A11: 46294 | B11: 29 | C11: 9 | D11: setembro | E11: 2026 | F11: 2 | G11: terça-feira | H11: Não
A12: 46295 | B12: 30 | C12: 9 | D12: setembro | E12: 2026 | F12: 3 | G12: quarta-feira | H12: Não
A13: 46296 | B13: 1 | C13: 10 | D13: outubro | E13: 2026 | F13: 4 | G13: quinta-feira | H13: Não
... A31: 46314 | B31: 19 | C31: 10 | D31: outubro | E31: 2026 | F31: 1 | G31: segunda-feira | H31: Não

Sheet dProcedimento
A1: id_procedimento | B1: procedimento | C1: id_unidade | D1: permanencia_ref_dias
A2: PR01 | B2: Tratamento de AVC isquêmico | C2: CM | D2: 7
A3: PR02 | B3: Tratamento de DPOC exacerbada | C3: CM | D3: 5
A4: PR03 | B4: Tratamento de diabetes descompensado | C4: CM | D4: 4
A5: PR04 | B5: Tratamento de infecção do trato urinário | C5: CM | D5: 4
A6: PR05 | B6: Tratamento de insuficiência cardíaca | C6: CM | D6: 6
A7: PR06 | B7: Tratamento de pneumonias | C7: CM | D7: 5
A8: PR07 | B8: Tratamento de sepse (enfermaria) | C8: CM | D8: 8
A9: PR08 | B9: Apendicectomia | C9: CC | D9: 3
A10: PR09 | B10: Colecistectomia | C10: CC | D10: 3
A11: PR10 | B11: Gastrectomia parcial | C11: CC | D11: 7
A12: PR11 | B12: Herniorrafia inguinal | C12: CC | D12: 2
A13: PR12 | B13: Laparotomia exploradora | C13: CC | D13: 6
... A37: PR36 | B37: Tratamento de tuberculose | C37: INF | D37: 14

Sheet dMotivoDesocupacao
A1: id_motivo | B1: motivo | C1: area_responsavel | D1: acao_recomendada
A2: MD01 | B2: Alta social | C2: Serviço Social | D2: Triagem de risco social na admissão; plano de alta iniciado em até 48 h; articulação com CRAS/CREAS e família; reunião semanal de casos longos.
A3: MD02 | B3: Falta de transporte | C3: Transporte sanitário / NIR | D3: Agendar o transporte na véspera da alta prevista; escala de ambulância para altas até 10 h; sala de alta para aguardar fora do leito.
A4: MD03 | B4: Falta de acompanhante ou responsável | C4: Serviço Social | D4: Identificar o responsável na admissão; contato ativo com a família na véspera; protocolo de alta com rede de apoio.
A5: MD04 | B5: Aguardando leito de retaguarda | C5: NIR / Regulação estadual | D5: Solicitar a vaga assim que a alta for previsível; pactuar cotas com hospitais de cuidados prolongados e ILPI; escalonar casos acima de 5 dias.
A6: MD05 | B6: Aguardando atenção domiciliar | C6: Atenção domiciliar (SAD) | D6: Encaminhar ao SAD/Melhor em Casa no início da internação; checklist de oxigênio e equipamentos domiciliares.
A7: MD06 | B7: Aguardando insumo ou equipamento para alta | C7: Farmácia e suprimentos | D7: Prever órteses, curativos e oxigênio na véspera; estoque mínimo para alta; dispensação antes das 10 h.
A8: MD07 | B8: Pendência judicial ou documental | C8: Jurídico / Serviço Social | D8: Acionar Jurídico e Serviço Social no primeiro dia; modelo padronizado de comunicação ao Ministério Público e à Defensoria.
A9: MD08 | B9: Aguardando transferência para outro serviço | C9: NIR / Regulação estadual | D9: Inserir o pedido na regulação junto com a previsão de alta; acompanhamento diário pelo NIR.

Sheet dComponenteCusto
A1: id_componente | B1: componente | C1: fator_dia_de_espera
A2: CC01 | B2: Equipe assistencial (enfermagem, médica e multiprofissional) | C2: 1
A3: CC02 | B3: Hotelaria (nutrição, higienização e lavanderia) | C3: 1
A4: CC03 | B4: Medicamentos e materiais | C4: 0.35
A5: CC04 | B5: Apoio diagnóstico (laboratório e imagem) | C5: 0.15
A6: CC05 | B6: Estrutura e administração (rateio) | C6: 1

Sheet fCensoDiario
A1: data | B1: id_unidade | C1: leitos_operacionais | D1: leitos_bloqueados | E1: pacientes_dia | F1: admissoes | G1: altas | H1: obitos | I1: obitos_ate_24h | J1: transferencias_externas | K1: saidas | L1: taxa_ocupacao
A2: 46285 | B2: CM | C2: 58 | D2: 2 | E2: 53 | F2: 7 | G2: 4 | H2: 1 | I2: 0 | J2: 1 | K2: =G2+H2+J2 | L2: =IF(C2=0,0,E2/C2)
A3: 46286 | B3: CM | C3: 58 | D3: 2 | E3: 55 | F3: 5 | G3: 6 | H3: 0 | I3: 0 | J3: 0 | K3: =G3+H3+J3 | L3: =IF(C3=0,0,E3/C3)
A4: 46287 | B4: CM | C4: 59 | D4: 1 | E4: 55 | F4: 9 | G4: 6 | H4: 1 | I4: 0 | J4: 1 | K4: =G4+H4+J4 | L4: =IF(C4=0,0,E4/C4)
A5: 46288 | B5: CM | C5: 56 | D5: 4 | E5: 56 | F5: 7 | G5: 6 | H5: 0 | I5: 0 | J5: 1 | K5: =G5+H5+J5 | L5: =IF(C5=0,0,E5/C5)
A6: 46289 | B6: CM | C6: 56 | D6: 4 | E6: 56 | F6: 8 | G6: 8 | H6: 0 | I6: 0 | J6: 0 | K6: =G6+H6+J6 | L6: =IF(C6=0,0,E6/C6)
A7: 46290 | B7: CM | C7: 58 | D7: 2 | E7: 58 | F7: 10 | G7: 9 | H7: 0 | I7: 0 | J7: 0 | K7: =G7+H7+J7 | L7: =IF(C7=0,0,E7/C7)
A8: 46291 | B8: CM | C8: 58 | D8: 2 | E8: 57 | F8: 4 | G8: 4 | H8: 0 | I8: 0 | J8: 0 | K8: =G8+H8+J8 | L8: =IF(C8=0,0,E8/C8)
A9: 46292 | B9: CM | C9: 57 | D9: 3 | E9: 54 | F9: 2 | G9: 3 | H9: 1 | I9: 0 | J9: 0 | K9: =G9+H9+J9 | L9: =IF(C9=0,0,E9/C9)
A10: 46293 | B10: CM | C10: 57 | D10: 3 | E10: 56 | F10: 9 | G10: 7 | H10: 1 | I10: 0 | J10: 0 | K10: =G10+H10+J10 | L10: =IF(C10=0,0,E10/C10)
A11: 46294 | B11: CM | C11: 59 | D11: 1 | E11: 53 | F11: 10 | G11: 6 | H11: 2 | I11: 0 | J11: 0 | K11: =G11+H11+J11 | L11: =IF(C11=0,0,E11/C11)
A12: 46295 | B12: CM | C12: 57 | D12: 3 | E12: 55 | F12: 5 | G12: 8 | H12: 0 | I12: 0 | J12: 0 | K12: =G12+H12+J12 | L12: =IF(C12=0,0,E12/C12)
A13: 46296 | B13: CM | C13: 57 | D13: 3 | E13: 52 | F13: 8 | G13: 8 | H13: 0 | I13: 0 | J13: 0 | K13: =G13+H13+J13 | L13: =IF(C13=0,0,E13/C13)
... A301: 46314 | B301: INF | C301: 7 | D301: 1 | E301: 5 | F301: 0 | G301: 2 | H301: 0 | I301: 0 | J301: 0 | K301: =G301+H301+J301 | L301: =IF(C301=0,0,E301/C301)

Sheet fLeitosCenso
A1: id_leito | B1: id_unidade | C1: status | D1: etapa_fluxo | E1: prontuario | F1: iniciais | G1: idade | H1: sexo | I1: id_procedimento | J1: data_internacao | K1: dias_internacao | L1: permanencia_ref_dias | M1: razao_permanencia | N1: classificacao_kanban | O1: previsao_alta | P1: origem | Q1: pendencia | R1: motivo_bloqueio | S1: bloqueado_desde | T1: tipo_higienizacao | U1: inicio_higienizacao | V1: reservado_para | W1: reservado_desde | X1: vago_desde
A2: CM-A01 | B2: CM | C2: Ocupado | D2: Aguardando desocupação | E2: P10001 | F2: DO.S. | G2: 30 | H2: M | I2: PR07 | J2: 46311.292 | K2: =IF(C2="Ocupado",INT('LEIA-ME'!$B$4-J2),"") | L2: =IF(I2="","",INDEX(dProcedimento!$D:$D,MATCH(I2,dProcedimento!$A:$A,0))) | M2: =IF(K2="","",K2/L2) | N2: =IF(K2="","",IF(K2<=L2/2,"Verde",IF(K2<=L2,"Amarelo","Vermelho"))) | O2: 46320 | P2: Pronto-Socorro | Q2: Aguardando transferência para outro serviço
A3: CM-A02 | B3: CM | C3: Ocupado | D3: Aguardando desocupação | E3: P10002 | F3: OV.R. | G3: 56 | H3: F | I3: PR01 | J3: 46307.625 | K3: =IF(C3="Ocupado",INT('LEIA-ME'!$B$4-J3),"") | L3: =IF(I3="","",INDEX(dProcedimento!$D:$D,MATCH(I3,dProcedimento!$A:$A,0))) | M3: =IF(K3="","",K3/L3) | N3: =IF(K3="","",IF(K3<=L3/2,"Verde",IF(K3<=L3,"Amarelo","Vermelho"))) | O3: 46316 | P3: Regulação (SISREG) | Q3: Falta de acompanhante ou responsável
A4: CM-A03 | B4: CM | C4: Ocupado | D4: Em internação | E4: P10003 | F4: HE.B. | G4: 69 | H4: F | I4: PR02 | J4: 46312.167 | K4: =IF(C4="Ocupado",INT('LEIA-ME'!$B$4-J4),"") | L4: =IF(I4="","",INDEX(dProcedimento!$D:$D,MATCH(I4,dProcedimento!$A:$A,0))) | M4: =IF(K4="","",K4/L4) | N4: =IF(K4="","",IF(K4<=L4/2,"Verde",IF(K4<=L4,"Amarelo","Vermelho"))) | O4: 46319 | P4: Centro Cirúrgico
A5: CM-A04 | B5: CM | C5: Ocupado | D5: Em internação | E5: P10004 | F5: OR.E. | G5: 51 | H5: M | I5: PR04 | J5: 46312.208 | K5: =IF(C5="Ocupado",INT('LEIA-ME'!$B$4-J5),"") | L5: =IF(I5="","",INDEX(dProcedimento!$D:$D,MATCH(I5,dProcedimento!$A:$A,0))) | M5: =IF(K5="","",K5/L5) | N5: =IF(K5="","",IF(K5<=L5/2,"Verde",IF(K5<=L5,"Amarelo","Vermelho"))) | O5: 46317 | P5: Pronto-Socorro
A6: CM-A05 | B6: CM | C6: Bloqueado | D6: Bloqueado | K6: =IF(C6="Ocupado",INT('LEIA-ME'!$B$4-J6),"") | L6: =IF(I6="","",INDEX(dProcedimento!$D:$D,MATCH(I6,dProcedimento!$A:$A,0))) | M6: =IF(K6="","",K6/L6) | N6: =IF(K6="","",IF(K6<=L6/2,"Verde",IF(K6<=L6,"Amarelo","Vermelho"))) | R6: Manutenção de equipamento | S6: 46309.583
A7: CM-A06 | B7: CM | C7: Ocupado | D7: Aguardando desocupação | E7: P10005 | F7: DP.R. | G7: 39 | H7: M | I7: PR07 | J7: 46310.042 | K7: =IF(C7="Ocupado",INT('LEIA-ME'!$B$4-J7),"") | L7: =IF(I7="","",INDEX(dProcedimento!$D:$D,MATCH(I7,dProcedimento!$A:$A,0))) | M7: =IF(K7="","",K7/L7) | N7: =IF(K7="","",IF(K7<=L7/2,"Verde",IF(K7<=L7,"Amarelo","Vermelho"))) | O7: 46320 | P7: Pronto-Socorro | Q7: Aguardando leito de retaguarda
A8: CM-A07 | B8: CM | C8: Ocupado | D8: Em internação | E8: P10006 | F8: NJ.T. | G8: 58 | H8: M | I8: PR02 | J8: 46311.875 | K8: =IF(C8="Ocupado",INT('LEIA-ME'!$B$4-J8),"") | L8: =IF(I8="","",INDEX(dProcedimento!$D:$D,MATCH(I8,dProcedimento!$A:$A,0))) | M8: =IF(K8="","",K8/L8) | N8: =IF(K8="","",IF(K8<=L8/2,"Verde",IF(K8<=L8,"Amarelo","Vermelho"))) | O8: 46317 | P8: Pronto-Socorro
A9: CM-A08 | B9: CM | C9: Ocupado | D9: Em internação | E9: P10007 | F9: NO.G. | G9: 82 | H9: M | I9: PR07 | J9: 46310.958 | K9: =IF(C9="Ocupado",INT('LEIA-ME'!$B$4-J9),"") | L9: =IF(I9="","",INDEX(dProcedimento!$D:$D,MATCH(I9,dProcedimento!$A:$A,0))) | M9: =IF(K9="","",K9/L9) | N9: =IF(K9="","",IF(K9<=L9/2,"Verde",IF(K9<=L9,"Amarelo","Vermelho"))) | O9: 46318 | P9: Pronto-Socorro
A10: CM-A09 | B10: CM | C10: Ocupado | D10: Em internação | E10: P10008 | F10: IA.B. | G10: 82 | H10: F | I10: PR07 | J10: 46311.958 | K10: =IF(C10="Ocupado",INT('LEIA-ME'!$B$4-J10),"") | L10: =IF(I10="","",INDEX(dProcedimento!$D:$D,MATCH(I10,dProcedimento!$A:$A,0))) | M10: =IF(K10="","",K10/L10) | N10: =IF(K10="","",IF(K10<=L10/2,"Verde",IF(K10<=L10,"Amarelo","Vermelho"))) | O10: 46319 | P10: Transferência interna
A11: CM-A10 | B11: CM | C11: Ocupado | D11: Em internação | E11: P10009 | F11: PS.R. | G11: 71 | H11: M | I11: PR04 | J11: 46313.042 | K11: =IF(C11="Ocupado",INT('LEIA-ME'!$B$4-J11),"") | L11: =IF(I11="","",INDEX(dProcedimento!$D:$D,MATCH(I11,dProcedimento!$A:$A,0))) | M11: =IF(K11="","",K11/L11) | N11: =IF(K11="","",IF(K11<=L11/2,"Verde",IF(K11<=L11,"Amarelo","Vermelho"))) | O11: 46318 | P11: Pronto-Socorro
A12: CM-A11 | B12: CM | C12: Ocupado | D12: Aguardando desocupação | E12: P10010 | F12: IR.P. | G12: 75 | H12: M | I12: PR05 | J12: 46309.542 | K12: =IF(C12="Ocupado",INT('LEIA-ME'!$B$4-J12),"") | L12: =IF(I12="","",INDEX(dProcedimento!$D:$D,MATCH(I12,dProcedimento!$A:$A,0))) | M12: =IF(K12="","",K12/L12) | N12: =IF(K12="","",IF(K12<=L12/2,"Verde",IF(K12<=L12,"Amarelo","Vermelho"))) | O12: 46315 | P12: Pronto-Socorro | Q12: Aguardando atenção domiciliar
A13: CM-A12 | B13: CM | C13: Ocupado | D13: Alta médica dada | E13: P10011 | F13: TB.J. | G13: 70 | H13: M | I13: PR07 | J13: 46304.083 | K13: =IF(C13="Ocupado",INT('LEIA-ME'!$B$4-J13),"") | L13: =IF(I13="","",INDEX(dProcedimento!$D:$D,MATCH(I13,dProcedimento!$A:$A,0))) | M13: =IF(K13="","",K13/L13) | N13: =IF(K13="","",IF(K13<=L13/2,"Verde",IF(K13<=L13,"Amarelo","Vermelho"))) | O13: 46314 | P13: Pronto-Socorro | Q13: Aguardando procedimento cirúrgico
A14: CM-A13 | B14: CM | C14: Ocupado | D14: Aguardando desocupação | E14: P10012 | F14: PS.I. | G14: 48 | H14: M | I14: PR01 | J14: 46296.292 | K14: =IF(C14="Ocupado",INT('LEIA-ME'!$B$4-J14),"") | L14: =IF(I14="","",INDEX(dProcedimento!$D:$D,MATCH(I14,dProcedimento!$A:$A,0))) | M14: =IF(K14="","",K14/L14) | N14: =IF(K14="","",IF(K14<=L14/2,"Verde",IF(K14<=L14,"Amarelo","Vermelho"))) | O14: 46316 | P14: Regulação (SISREG) | Q14: Falta de acompanhante ou responsável
A15: CM-A14 | B15: CM | C15: Ocupado | D15: Em internação | E15: P10013 | F15: OR.C. | G15: 53 | H15: M | I15: PR05 | J15: 46307.917 | K15: =IF(C15="Ocupado",INT('LEIA-ME'!$B$4-J15),"") | L15: =IF(I15="","",INDEX(dProcedimento!$D:$D,MATCH(I15,dProcedimento!$A:$A,0))) | M15: =IF(K15="","",K15/L15) | N15: =IF(K15="","",IF(K15<=L15/2,"Verde",IF(K15<=L15,"Amarelo","Vermelho"))) | O15: 46315 | P15: Pronto-Socorro
A16: CM-A15 | B16: CM | C16: Ocupado | D16: Alta médica dada | E16: P10014 | F16: DG.O. | G16: 52 | H16: F | I16: PR01 | J16: 46306.292 | K16: =IF(C16="Ocupado",INT('LEIA-ME'!$B$4-J16),"") | L16: =IF(I16="","",INDEX(dProcedimento!$D:$D,MATCH(I16,dProcedimento!$A:$A,0))) | M16: =IF(K16="","",K16/L16) | N16: =IF(K16="","",IF(K16<=L16/2,"Verde",IF(K16<=L16,"Amarelo","Vermelho"))) | O16: 46314 | P16: Pronto-Socorro | Q16: Aguardando resultado laboratorial
A17: CM-A16 | B17: CM | C17: Ocupado | D17: Em internação | E17: P10015 | F17: AC.A. | G17: 46 | H17: M | I17: PR01 | J17: 46311.5 | K17: =IF(C17="Ocupado",INT('LEIA-ME'!$B$4-J17),"") | L17: =IF(I17="","",INDEX(dProcedimento!$D:$D,MATCH(I17,dProcedimento!$A:$A,0))) | M17: =IF(K17="","",K17/L17) | N17: =IF(K17="","",IF(K17<=L17/2,"Verde",IF(K17<=L17,"Amarelo","Vermelho"))) | O17: 46319 | P17: Pronto-Socorro
A18: CM-A17 | B18: CM | C18: Ocupado | D18: Aguardando desocupação | E18: P10016 | F18: TC.G. | G18: 41 | H18: F | I18: PR02 | J18: 46310.833 | K18: =IF(C18="Ocupado",INT('LEIA-ME'!$B$4-J18),"") | L18: =IF(I18="","",INDEX(dProcedimento!$D:$D,MATCH(I18,dProcedimento!$A:$A,0))) | M18: =IF(K18="","",K18/L18) | N18: =IF(K18="","",IF(K18<=L18/2,"Verde",IF(K18<=L18,"Amarelo","Vermelho"))) | O18: 46317 | P18: Pronto-Socorro | Q18: Aguardando leito de retaguarda
A19: CM-A18 | B19: CM | C19: Ocupado | D19: Alta prevista hoje | E19: P10017 | F19: TI.M. | G19: 51 | H19: F | I19: PR06 | J19: 46302.583 | K19: =IF(C19="Ocupado",INT('LEIA-ME'!$B$4-J19),"") | L19: =IF(I19="","",INDEX(dProcedimento!$D:$D,MATCH(I19,dProcedimento!$A:$A,0))) | M19: =IF(K19="","",K19/L19) | N19: =IF(K19="","",IF(K19<=L19/2,"Verde",IF(K19<=L19,"Amarelo","Vermelho"))) | O19: 46314 | P19: Regulação (SISREG) | Q19: Aguardando exame de imagem
A20: CM-A19 | B20: CM | C20: Ocupado | D20: Em internação | E20: P10018 | F20: LV.V. | G20: 58 | H20: M | I20: PR06 | J20: 46312.25 | K20: =IF(C20="Ocupado",INT('LEIA-ME'!$B$4-J20),"") | L20: =IF(I20="","",INDEX(dProcedimento!$D:$D,MATCH(I20,dProcedimento!$A:$A,0))) | M20: =IF(K20="","",K20/L20) | N20: =IF(K20="","",IF(K20<=L20/2,"Verde",IF(K20<=L20,"Amarelo","Vermelho"))) | O20: 46317 | P20: Pronto-Socorro
A21: CM-A20 | B21: CM | C21: Ocupado | D21: Em internação | E21: P10019 | F21: ET.H. | G21: 50 | H21: M | I21: PR04 | J21: 46312.833 | K21: =IF(C21="Ocupado",INT('LEIA-ME'!$B$4-J21),"") | L21: =IF(I21="","",INDEX(dProcedimento!$D:$D,MATCH(I21,dProcedimento!$A:$A,0))) | M21: =IF(K21="","",K21/L21) | N21: =IF(K21="","",IF(K21<=L21/2,"Verde",IF(K21<=L21,"Amarelo","Vermelho"))) | O21: 46317 | P21: Ambulatório/Eletivo
A22: CM-A21 | B22: CM | C22: Ocupado | D22: Em internação | E22: P10020 | F22: ES.J. | G22: 41 | H22: F | I22: PR02 | J22: 46310.167 | K22: =IF(C22="Ocupado",INT('LEIA-ME'!$B$4-J22),"") | L22: =IF(I22="","",INDEX(dProcedimento!$D:$D,MATCH(I22,dProcedimento!$A:$A,0))) | M22: =IF(K22="","",K22/L22) | N22: =IF(K22="","",IF(K22<=L22/2,"Verde",IF(K22<=L22,"Amarelo","Vermelho"))) | O22: 46315 | P22: Centro Cirúrgico
A23: CM-A22 | B23: CM | C23: Ocupado | D23: Em internação | E23: P10021 | F23: FE.V. | G23: 70 | H23: M | I23: PR01 | J23: 46312.25 | K23: =IF(C23="Ocupado",INT('LEIA-ME'!$B$4-J23),"") | L23: =IF(I23="","",INDEX(dProcedimento!$D:$D,MATCH(I23,dProcedimento!$A:$A,0))) | M23: =IF(K23="","",K23/L23) | N23: =IF(K23="","",IF(K23<=L23/2,"Verde",IF(K23<=L23,"Amarelo","Vermelho"))) | O23: 46320 | P23: Pronto-Socorro
A24: CM-A23 | B24: CM | C24: Em higienização | D24: Em higienização | K24: =IF(C24="Ocupado",INT('LEIA-ME'!$B$4-J24),"") | L24: =IF(I24="","",INDEX(dProcedimento!$D:$D,MATCH(I24,dProcedimento!$A:$A,0))) | M24: =IF(K24="","",K24/L24) | N24: =IF(K24="","",IF(K24<=L24/2,"Verde",IF(K24<=L24,"Amarelo","Vermelho"))) | T24: Terminal | U24: 46314.216
A25: CM-A24 | B25: CM | C25: Ocupado | D25: Em internação | E25: P10022 | F25: NE.S. | G25: 62 | H25: F | I25: PR01 | J25: 46311.833 | K25: =IF(C25="Ocupado",INT('LEIA-ME'!$B$4-J25),"") | L25: =IF(I25="","",INDEX(dProcedimento!$D:$D,MATCH(I25,dProcedimento!$A:$A,0))) | M25: =IF(K25="","",K25/L25) | N25: =IF(K25="","",IF(K25<=L25/2,"Verde",IF(K25<=L25,"Amarelo","Vermelho"))) | O25: 46320 | P25: Pronto-Socorro
A26: CM-A25 | B26: CM | C26: Ocupado | D26: Em internação | E26: P10023 | F26: AD.N. | G26: 43 | H26: F | I26: PR01 | J26: 46309.792 | K26: =IF(C26="Ocupado",INT('LEIA-ME'!$B$4-J26),"") | L26: =IF(I26="","",INDEX(dProcedimento!$D:$D,MATCH(I26,dProcedimento!$A:$A,0))) | M26: =IF(K26="","",K26/L26) | N26: =IF(K26="","",IF(K26<=L26/2,"Verde",IF(K26<=L26,"Amarelo","Vermelho"))) | O26: 46316 | P26: Centro Cirúrgico
A27: CM-A26 | B27: CM | C27: Ocupado | D27: Alta médica dada | E27: P10024 | F27: MM.A. | G27: 55 | H27: F | I27: PR06 | J27: 46308.792 | K27: =IF(C27="Ocupado",INT('LEIA-ME'!$B$4-J27),"") | L27: =IF(I27="","",INDEX(dProcedimento!$D:$D,MATCH(I27,dProcedimento!$A:$A,0))) | M27: =IF(K27="","",K27/L27) | N27: =IF(K27="","",IF(K27<=L27/2,"Verde",IF(K27<=L27,"Amarelo","Vermelho"))) | O27: 46314 | P27: Pronto-Socorro
A28: CM-A27 | B28: CM | C28: Ocupado | D28: Aguardando desocupação | E28: P10025 | F28: RL.J. | G28: 68 | H28: M | I28: PR02 | J28: 46310.042 | K28: =IF(C28="Ocupado",INT('LEIA-ME'!$B$4-J28),"") | L28: =IF(I28="","",INDEX(dProcedimento!$D:$D,MATCH(I28,dProcedimento!$A:$A,0))) | M28: =IF(K28="","",K28/L28) | N28: =IF(K28="","",IF(K28<=L28/2,"Verde",IF(K28<=L28,"Amarelo","Vermelho"))) | O28: 46316 | P28: Pronto-Socorro | Q28: Aguardando insumo ou equipamento para alta
A29: CM-A28 | B29: CM | C29: Ocupado | D29: Em internação | E29: P10026 | F29: DR.P. | G29: 51 | H29: F | I29: PR03 | J29: 46312.25 | K29: =IF(C29="Ocupado",INT('LEIA-ME'!$B$4-J29),"") | L29: =IF(I29="","",INDEX(dProcedimento!$D:$D,MATCH(I29,dProcedimento!$A:$A,0))) | M29: =IF(K29="","",K29/L29) | N29: =IF(K29="","",IF(K29<=L29/2,"Verde",IF(K29<=L29,"Amarelo","Vermelho"))) | O29: 46318 | P29: Pronto-Socorro
A30: CM-A29 | B30: CM | C30: Ocupado | D30: Em internação | E30: P10027 | F30: VS.G. | G30: 73 | H30: M | I30: PR05 | J30: 46311.583 | K30: =IF(C30="Ocupado",INT('LEIA-ME'!$B$4-J30),"") | L30: =IF(I30="","",INDEX(dProcedimento!$D:$D,MATCH(I30,dProcedimento!$A:$A,0))) | M30: =IF(K30="","",K30/L30) | N30: =IF(K30="","",IF(K30<=L30/2,"Verde",IF(K30<=L30,"Amarelo","Vermelho"))) | O30: 46317 | P30: Regulação (SISREG)
A31: CM-A30 | B31: CM | C31: Ocupado | D31: Em internação | E31: P10028 | F31: LP.H. | G31: 53 | H31: F | I31: PR02 | J31: 46309.208 | K31: =IF(C31="Ocupado",INT('LEIA-ME'!$B$4-J31),"") | L31: =IF(I31="","",INDEX(dProcedimento!$D:$D,MATCH(I31,dProcedimento!$A:$A,0))) | M31: =IF(K31="","",K31/L31) | N31: =IF(K31="","",IF(K31<=L31/2,"Verde",IF(K31<=L31,"Amarelo","Vermelho"))) | O31: 46315 | P31: Regulação (SISREG)
A32: CM-B31 | B32: CM | C32: Ocupado | D32: Alta prevista hoje | E32: P10029 | F32: BG.F. | G32: 64 | H32: F | I32: PR02 | J32: 46307.833 | K32: =IF(C32="Ocupado",INT('LEIA-ME'!$B$4-J32),"") | L32: =IF(I32="","",INDEX(dProcedimento!$D:$D,MATCH(I32,dProcedimento!$A:$A,0))) | M32: =IF(K32="","",K32/L32) | N32: =IF(K32="","",IF(K32<=L32/2,"Verde",IF(K32<=L32,"Amarelo","Vermelho"))) | O32: 46314 | P32: Regulação (SISREG) | Q32: Aguardando procedimento cirúrgico
A33: CM-B32 | B33: CM | C33: Ocupado | D33: Em internação | E33: P10030 | F33: TB.P. | G33: 74 | H33: F | I33: PR04 | J33: 46312.542 | K33: =IF(C33="Ocupado",INT('LEIA-ME'!$B$4-J33),"") | L33: =IF(I33="","",INDEX(dProcedimento!$D:$D,MATCH(I33,dProcedimento!$A:$A,0))) | M33: =IF(K33="","",K33/L33) | N33: =IF(K33="","",IF(K33<=L33/2,"Verde",IF(K33<=L33,"Amarelo","Vermelho"))) | O33: 46317 | P33: Pronto-Socorro
A34: CM-B33 | B34: CM | C34: Reservado | D34: Reservado / aguardando paciente | K34: =IF(C34="Ocupado",INT('LEIA-ME'!$B$4-J34),"") | L34: =IF(I34="","",INDEX(dProcedimento!$D:$D,MATCH(I34,dProcedimento!$A:$A,0))) | M34: =IF(K34="","",K34/L34) | N34: =IF(K34="","",IF(K34<=L34/2,"Verde",IF(K34<=L34,"Amarelo","Vermelho"))) | V34: Centro Cirúrgico | W34: 46314.199
A35: CM-B34 | B35: CM | C35: Ocupado | D35: Alta prevista hoje | E35: P10031 | F35: ES.G. | G35: 89 | H35: F | I35: PR01 | J35: 46300.292 | K35: =IF(C35="Ocupado",INT('LEIA-ME'!$B$4-J35),"") | L35: =IF(I35="","",INDEX(dProcedimento!$D:$D,MATCH(I35,dProcedimento!$A:$A,0))) | M35: =IF(K35="","",K35/L35) | N35: =IF(K35="","",IF(K35<=L35/2,"Verde",IF(K35<=L35,"Amarelo","Vermelho"))) | O35: 46314 | P35: Pronto-Socorro | Q35: Aguardando exame de imagem
A36: CM-B35 | B36: CM | C36: Bloqueado | D36: Bloqueado | K36: =IF(C36="Ocupado",INT('LEIA-ME'!$B$4-J36),"") | L36: =IF(I36="","",INDEX(dProcedimento!$D:$D,MATCH(I36,dProcedimento!$A:$A,0))) | M36: =IF(K36="","",K36/L36) | N36: =IF(K36="","",IF(K36<=L36/2,"Verde",IF(K36<=L36,"Amarelo","Vermelho"))) | R36: Manutenção de equipamento | S36: 46311.958
A37: CM-B36 | B37: CM | C37: Ocupado | D37: Em internação | E37: P10032 | F37: FN.I. | G37: 64 | H37: M | I37: PR04 | J37: 46312.667 | K37: =IF(C37="Ocupado",INT('LEIA-ME'!$B$4-J37),"") | L37: =IF(I37="","",INDEX(dProcedimento!$D:$D,MATCH(I37,dProcedimento!$A:$A,0))) | M37: =IF(K37="","",K37/L37) | N37: =IF(K37="","",IF(K37<=L37/2,"Verde",IF(K37<=L37,"Amarelo","Vermelho"))) | O37: 46316 | P37: Pronto-Socorro
A38: CM-B37 | B38: CM | C38: Bloqueado | D38: Bloqueado | K38: =IF(C38="Ocupado",INT('LEIA-ME'!$B$4-J38),"") | L38: =IF(I38="","",INDEX(dProcedimento!$D:$D,MATCH(I38,dProcedimento!$A:$A,0))) | M38: =IF(K38="","",K38/L38) | N38: =IF(K38="","",IF(K38<=L38/2,"Verde",IF(K38<=L38,"Amarelo","Vermelho"))) | R38: Desinfecção terminal | S38: 46313.583
A39: CM-B38 | B39: CM | C39: Ocupado | D39: Alta médica dada | E39: P10033 | F39: NJ.F. | G39: 69 | H39: M | I39: PR01 | J39: 46303.833 | K39: =IF(C39="Ocupado",INT('LEIA-ME'!$B$4-J39),"") | L39: =IF(I39="","",INDEX(dProcedimento!$D:$D,MATCH(I39,dProcedimento!$A:$A,0))) | M39: =IF(K39="","",K39/L39) | N39: =IF(K39="","",IF(K39<=L39/2,"Verde",IF(K39<=L39,"Amarelo","Vermelho"))) | O39: 46314 | P39: Pronto-Socorro | Q39: Aguardando parecer de especialidade
A40: CM-B39 | B40: CM | C40: Reservado | D40: Reservado / aguardando paciente | K40: =IF(C40="Ocupado",INT('LEIA-ME'!$B$4-J40),"") | L40: =IF(I40="","",INDEX(dProcedimento!$D:$D,MATCH(I40,dProcedimento!$A:$A,0))) | M40: =IF(K40="","",K40/L40) | N40: =IF(K40="","",IF(K40<=L40/2,"Verde",IF(K40<=L40,"Amarelo","Vermelho"))) | V40: Pronto-Socorro | W40: 46314.242
A41: CM-B40 | B41: CM | C41: Ocupado | D41: Em internação | E41: P10034 | F41: IP.R. | G41: 74 | H41: M | I41: PR05 | J41: 46310.583 | K41: =IF(C41="Ocupado",INT('LEIA-ME'!$B$4-J41),"") | L41: =IF(I41="","",INDEX(dProcedimento!$D:$D,MATCH(I41,dProcedimento!$A:$A,0))) | M41: =IF(K41="","",K41/L41) | N41: =IF(K41="","",IF(K41<=L41/2,"Verde",IF(K41<=L41,"Amarelo","Vermelho"))) | O41: 46317 | P41: Pronto-Socorro
A42: CM-B41 | B42: CM | C42: Ocupado | D42: Em internação | E42: P10035 | F42: PF.L. | G42: 68 | H42: M | I42: PR03 | J42: 46312.083 | K42: =IF(C42="Ocupado",INT('LEIA-ME'!$B$4-J42),"") | L42: =IF(I42="","",INDEX(dProcedimento!$D:$D,MATCH(I42,dProcedimento!$A:$A,0))) | M42: =IF(K42="","",K42/L42) | N42: =IF(K42="","",IF(K42<=L42/2,"Verde",IF(K42<=L42,"Amarelo","Vermelho"))) | O42: 46317 | P42: Transferência interna
A43: CM-B42 | B43: CM | C43: Ocupado | D43: Alta médica dada | E43: P10036 | F43: SS.I. | G43: 76 | H43: F | I43: PR01 | J43: 46307.833 | K43: =IF(C43="Ocupado",INT('LEIA-ME'!$B$4-J43),"") | L43: =IF(I43="","",INDEX(dProcedimento!$D:$D,MATCH(I43,dProcedimento!$A:$A,0))) | M43: =IF(K43="","",K43/L43) | N43: =IF(K43="","",IF(K43<=L43/2,"Verde",IF(K43<=L43,"Amarelo","Vermelho"))) | O43: 46314 | P43: Pronto-Socorro | Q43: Aguardando parecer de especialidade
A44: CM-B43 | B44: CM | C44: Ocupado | D44: Em internação | E44: P10037 | F44: GH.A. | G44: 72 | H44: F | I44: PR07 | J44: 46310.75 | K44: =IF(C44="Ocupado",INT('LEIA-ME'!$B$4-J44),"") | L44: =IF(I44="","",INDEX(dProcedimento!$D:$D,MATCH(I44,dProcedimento!$A:$A,0))) | M44: =IF(K44="","",K44/L44) | N44: =IF(K44="","",IF(K44<=L44/2,"Verde",IF(K44<=L44,"Amarelo","Vermelho"))) | O44: 46320 | P44: Pronto-Socorro
A45: CM-B44 | B45: CM | C45: Ocupado | D45: Em internação | E45: P10038 | F45: OT.F. | G45: 70 | H45: F | I45: PR01 | J45: 46305.083 | K45: =IF(C45="Ocupado",INT('LEIA-ME'!$B$4-J45),"") | L45: =IF(I45="","",INDEX(dProcedimento!$D:$D,MATCH(I45,dProcedimento!$A:$A,0))) | M45: =IF(K45="","",K45/L45) | N45: =IF(K45="","",IF(K45<=L45/2,"Verde",IF(K45<=L45,"Amarelo","Vermelho"))) | O45: 46316 | P45: Regulação (SISREG) | Q45: Aguardando resultado laboratorial
A46: CM-B45 | B46: CM | C46: Ocupado | D46: Em internação | E46: P10039 | F46: FM.T. | G46: 83 | H46: F | I46: PR03 | J46: 46313.083 | K46: =IF(C46="Ocupado",INT('LEIA-ME'!$B$4-J46),"") | L46: =IF(I46="","",INDEX(dProcedimento!$D:$D,MATCH(I46,dProcedimento!$A:$A,0))) | M46: =IF(K46="","",K46/L46) | N46: =IF(K46="","",IF(K46<=L46/2,"Verde",IF(K46<=L46,"Amarelo","Vermelho"))) | O46: 46319 | P46: Centro Cirúrgico
A47: CM-B46 | B47: CM | C47: Ocupado | D47: Aguardando desocupação | E47: P10040 | F47: TV.G. | G47: 79 | H47: M | I47: PR06 | J47: 46305.083 | K47: =IF(C47="Ocupado",INT('LEIA-ME'!$B$4-J47),"") | L47: =IF(I47="","",INDEX(dProcedimento!$D:$D,MATCH(I47,dProcedimento!$A:$A,0))) | M47: =IF(K47="","",K47/L47) | N47: =IF(K47="","",IF(K47<=L47/2,"Verde",IF(K47<=L47,"Amarelo","Vermelho"))) | O47: 46315 | P47: Pronto-Socorro | Q47: Aguardando insumo ou equipamento para alta
A48: CM-B47 | B48: CM | C48: Ocupado | D48: Em internação | E48: P10041 | F48: IT.E. | G48: 73 | H48: F | I48: PR02 | J48: 46310.292 | K48: =IF(C48="Ocupado",INT('LEIA-ME'!$B$4-J48),"") | L48: =IF(I48="","",INDEX(dProcedimento!$D:$D,MATCH(I48,dProcedimento!$A:$A,0))) | M48: =IF(K48="","",K48/L48) | N48: =IF(K48="","",IF(K48<=L48/2,"Verde",IF(K48<=L48,"Amarelo","Vermelho"))) | O48: 46316 | P48: Pronto-Socorro
A49: CM-B48 | B49: CM | C49: Ocupado | D49: Aguardando desocupação | E49: P10042 | F49: ID.O. | G49: 55 | H49: F | I49: PR07 | J49: 46307.833 | K49: =IF(C49="Ocupado",INT('LEIA-ME'!$B$4-J49),"") | L49: =IF(I49="","",INDEX(dProcedimento!$D:$D,MATCH(I49,dProcedimento!$A:$A,0))) | M49: =IF(K49="","",K49/L49) | N49: =IF(K49="","",IF(K49<=L49/2,"Verde",IF(K49<=L49,"Amarelo","Vermelho"))) | O49: 46315 | P49: Regulação (SISREG) | Q49: Falta de transporte
A50: CM-B49 | B50: CM | C50: Ocupado | D50: Em internação | E50: P10043 | F50: BM.F. | G50: 73 | H50: F | I50: PR06 | J50: 46311.292 | K50: =IF(C50="Ocupado",INT('LEIA-ME'!$B$4-J50),"") | L50: =IF(I50="","",INDEX(dProcedimento!$D:$D,MATCH(I50,dProcedimento!$A:$A,0))) | M50: =IF(K50="","",K50/L50) | N50: =IF(K50="","",IF(K50<=L50/2,"Verde",IF(K50<=L50,"Amarelo","Vermelho"))) | O50: 46316 | P50: Regulação (SISREG)
A51: CM-B50 | B51: CM | C51: Ocupado | D51: Em internação | E51: P10044 | F51: LI.V. | G51: 66 | H51: F | I51: PR02 | J51: 46312.958 | K51: =IF(C51="Ocupado",INT('LEIA-ME'!$B$4-J51),"") | L51: =IF(I51="","",INDEX(dProcedimento!$D:$D,MATCH(I51,dProcedimento!$A:$A,0))) | M51: =IF(K51="","",K51/L51) | N51: =IF(K51="","",IF(K51<=L51/2,"Verde",IF(K51<=L51,"Amarelo","Vermelho"))) | O51: 46317 | P51: Ambulatório/Eletivo
A52: CM-B51 | B52: CM | C52: Ocupado | D52: Em internação | E52: P10045 | F52: LF.I. | G52: 67 | H52: M | I52: PR03 | J52: 46312.125 | K52: =IF(C52="Ocupado",INT('LEIA-ME'!$B$4-J52),"") | L52: =IF(I52="","",INDEX(dProcedimento!$D:$D,MATCH(I52,dProcedimento!$A:$A,0))) | M52: =IF(K52="","",K52/L52) | N52: =IF(K52="","",IF(K52<=L52/2,"Verde",IF(K52<=L52,"Amarelo","Vermelho"))) | O52: 46316 | P52: Pronto-Socorro
A53: CM-B52 | B53: CM | C53: Ocupado | D53: Em internação | E53: P10046 | F53: AO.I. | G53: 65 | H53: M | I53: PR06 | J53: 46311 | K53: =IF(C53="Ocupado",INT('LEIA-ME'!$B$4-J53),"") | L53: =IF(I53="","",INDEX(dProcedimento!$D:$D,MATCH(I53,dProcedimento!$A:$A,0))) | M53: =IF(K53="","",K53/L53) | N53: =IF(K53="","",IF(K53<=L53/2,"Verde",IF(K53<=L53,"Amarelo","Vermelho"))) | O53: 46316 | P53: Pronto-Socorro
A54: CM-B53 | B54: CM | C54: Ocupado | D54: Em internação | E54: P10047 | F54: BD.H. | G54: 62 | H54: F | I54: PR06 | J54: 46309.792 | K54: =IF(C54="Ocupado",INT('LEIA-ME'!$B$4-J54),"") | L54: =IF(I54="","",INDEX(dProcedimento!$D:$D,MATCH(I54,dProcedimento!$A:$A,0))) | M54: =IF(K54="","",K54/L54) | N54: =IF(K54="","",IF(K54<=L54/2,"Verde",IF(K54<=L54,"Amarelo","Vermelho"))) | O54: 46315 | P54: Pronto-Socorro
A55: CM-B54 | B55: CM | C55: Ocupado | D55: Alta médica dada | E55: P10048 | F55: DT.V. | G55: 61 | H55: M | I55: PR03 | J55: 46309.875 | K55: =IF(C55="Ocupado",INT('LEIA-ME'!$B$4-J55),"") | L55: =IF(I55="","",INDEX(dProcedimento!$D:$D,MATCH(I55,dProcedimento!$A:$A,0))) | M55: =IF(K55="","",K55/L55) | N55: =IF(K55="","",IF(K55<=L55/2,"Verde",IF(K55<=L55,"Amarelo","Vermelho"))) | O55: 46314 | P55: Pronto-Socorro | Q55: Aguardando parecer de especialidade
A56: CM-B55 | B56: CM | C56: Ocupado | D56: Em internação | E56: P10049 | F56: PB.N. | G56: 43 | H56: M | I56: PR03 | J56: 46311.833 | K56: =IF(C56="Ocupado",INT('LEIA-ME'!$B$4-J56),"") | L56: =IF(I56="","",INDEX(dProcedimento!$D:$D,MATCH(I56,dProcedimento!$A:$A,0))) | M56: =IF(K56="","",K56/L56) | N56: =IF(K56="","",IF(K56<=L56/2,"Verde",IF(K56<=L56,"Amarelo","Vermelho"))) | O56: 46316 | P56: Pronto-Socorro
A57: CM-B56 | B57: CM | C57: Ocupado | D57: Em internação | E57: P10050 | F57: GP.O. | G57: 52 | H57: F | I57: PR02 | J57: 46311.708 | K57: =IF(C57="Ocupado",INT('LEIA-ME'!$B$4-J57),"") | L57: =IF(I57="","",INDEX(dProcedimento!$D:$D,MATCH(I57,dProcedimento!$A:$A,0))) | M57: =IF(K57="","",K57/L57) | N57: =IF(K57="","",IF(K57<=L57/2,"Verde",IF(K57<=L57,"Amarelo","Vermelho"))) | O57: 46318 | P57: Pronto-Socorro
A58: CM-B57 | B58: CM | C58: Em higienização | D58: Em higienização | K58: =IF(C58="Ocupado",INT('LEIA-ME'!$B$4-J58),"") | L58: =IF(I58="","",INDEX(dProcedimento!$D:$D,MATCH(I58,dProcedimento!$A:$A,0))) | M58: =IF(K58="","",K58/L58) | N58: =IF(K58="","",IF(K58<=L58/2,"Verde",IF(K58<=L58,"Amarelo","Vermelho"))) | T58: Terminal | U58: 46314.231
A59: CM-B58 | B59: CM | C59: Ocupado | D59: Em internação | E59: P10051 | F59: SI.N. | G59: 49 | H59: M | I59: PR03 | J59: 46312.667 | K59: =IF(C59="Ocupado",INT('LEIA-ME'!$B$4-J59),"") | L59: =IF(I59="","",INDEX(dProcedimento!$D:$D,MATCH(I59,dProcedimento!$A:$A,0))) | M59: =IF(K59="","",K59/L59) | N59: =IF(K59="","",IF(K59<=L59/2,"Verde",IF(K59<=L59,"Amarelo","Vermelho"))) | O59: 46316 | P59: Pronto-Socorro
A60: CM-B59 | B60: CM | C60: Ocupado | D60: Em internação | E60: P10052 | F60: MB.O. | G60: 86 | H60: F | I60: PR07 | J60: 46309.917 | K60: =IF(C60="Ocupado",INT('LEIA-ME'!$B$4-J60),"") | L60: =IF(I60="","",INDEX(dProcedimento!$D:$D,MATCH(I60,dProcedimento!$A:$A,0))) | M60: =IF(K60="","",K60/L60) | N60: =IF(K60="","",IF(K60<=L60/2,"Verde",IF(K60<=L60,"Amarelo","Vermelho"))) | O60: 46317 | P60: Pronto-Socorro
A61: CM-B60 | B61: CM | C61: Ocupado | D61: Alta médica dada | E61: P10053 | F61: JD.J. | G61: 41 | H61: M | I61: PR03 | J61: 46306.25 | K61: =IF(C61="Ocupado",INT('LEIA-ME'!$B$4-J61),"") | L61: =IF(I61="","",INDEX(dProcedimento!$D:$D,MATCH(I61,dProcedimento!$A:$A,0))) | M61: =IF(K61="","",K61/L61) | N61: =IF(K61="","",IF(K61<=L61/2,"Verde",IF(K61<=L61,"Amarelo","Vermelho"))) | O61: 46314 | P61: Transferência interna | Q61: Aguardando resultado laboratorial
A62: CC-A01 | B62: CC | C62: Bloqueado | D62: Bloqueado | K62: =IF(C62="Ocupado",INT('LEIA-ME'!$B$4-J62),"") | L62: =IF(I62="","",INDEX(dProcedimento!$D:$D,MATCH(I62,dProcedimento!$A:$A,0))) | M62: =IF(K62="","",K62/L62) | N62: =IF(K62="","",IF(K62<=L62/2,"Verde",IF(K62<=L62,"Amarelo","Vermelho"))) | R62: Manutenção de equipamento | S62: 46311.875
A63: CC-A02 | B63: CC | C63: Ocupado | D63: Em internação | E63: P10054 | F63: AI.T. | G63: 63 | H63: M | I63: PR09 | J63: 46305.792 | K63: =IF(C63="Ocupado",INT('LEIA-ME'!$B$4-J63),"") | L63: =IF(I63="","",INDEX(dProcedimento!$D:$D,MATCH(I63,dProcedimento!$A:$A,0))) | M63: =IF(K63="","",K63/L63) | N63: =IF(K63="","",IF(K63<=L63/2,"Verde",IF(K63<=L63,"Amarelo","Vermelho"))) | O63: 46316 | P63: Ambulatório/Eletivo
A64: CC-A03 | B64: CC | C64: Ocupado | D64: Aguardando desocupação | E64: P10055 | F64: IL.E. | G64: 26 | H64: F | I64: PR12 | J64: 46308.583 | K64: =IF(C64="Ocupado",INT('LEIA-ME'!$B$4-J64),"") | L64: =IF(I64="","",INDEX(dProcedimento!$D:$D,MATCH(I64,dProcedimento!$A:$A,0))) | M64: =IF(K64="","",K64/L64) | N64: =IF(K64="","",IF(K64<=L64/2,"Verde",IF(K64<=L64,"Amarelo","Vermelho"))) | O64: 46315 | P64: Ambulatório/Eletivo | Q64: Falta de acompanhante ou responsável
A65: CC-A04 | B65: CC | C65: Reservado | D65: Reservado / aguardando paciente | K65: =IF(C65="Ocupado",INT('LEIA-ME'!$B$4-J65),"") | L65: =IF(I65="","",INDEX(dProcedimento!$D:$D,MATCH(I65,dProcedimento!$A:$A,0))) | M65: =IF(K65="","",K65/L65) | N65: =IF(K65="","",IF(K65<=L65/2,"Verde",IF(K65<=L65,"Amarelo","Vermelho"))) | V65: Regulação (SISREG) | W65: 46314.239
A66: CC-A05 | B66: CC | C66: Ocupado | D66: Em internação | E66: P10056 | F66: TB.S. | G66: 48 | H66: M | I66: PR11 | J66: 46313.125 | K66: =IF(C66="Ocupado",INT('LEIA-ME'!$B$4-J66),"") | L66: =IF(I66="","",INDEX(dProcedimento!$D:$D,MATCH(I66,dProcedimento!$A:$A,0))) | M66: =IF(K66="","",K66/L66) | N66: =IF(K66="","",IF(K66<=L66/2,"Verde",IF(K66<=L66,"Amarelo","Vermelho"))) | O66: 46315 | P66: Ambulatório/Eletivo
A67: CC-A06 | B67: CC | C67: Ocupado | D67: Em internação | E67: P10057 | F67: SL.B. | G67: 83 | H67: F | I67: PR08 | J67: 46313.25 | K67: =IF(C67="Ocupado",INT('LEIA-ME'!$B$4-J67),"") | L67: =IF(I67="","",INDEX(dProcedimento!$D:$D,MATCH(I67,dProcedimento!$A:$A,0))) | M67: =IF(K67="","",K67/L67) | N67: =IF(K67="","",IF(K67<=L67/2,"Verde",IF(K67<=L67,"Amarelo","Vermelho"))) | O67: 46318 | P67: Regulação (SISREG)
A68: CC-A07 | B68: CC | C68: Ocupado | D68: Em internação | E68: P10058 | F68: HR.B. | G68: 19 | H68: F | I68: PR13 | J68: 46314.208 | K68: =IF(C68="Ocupado",INT('LEIA-ME'!$B$4-J68),"") | L68: =IF(I68="","",INDEX(dProcedimento!$D:$D,MATCH(I68,dProcedimento!$A:$A,0))) | M68: =IF(K68="","",K68/L68) | N68: =IF(K68="","",IF(K68<=L68/2,"Verde",IF(K68<=L68,"Amarelo","Vermelho"))) | O68: 46316 | P68: Centro Cirúrgico
A69: CC-A08 | B69: CC | C69: Ocupado | D69: Em internação | E69: P10059 | F69: NM.H. | G69: 37 | H69: M | I69: PR13 | J69: 46311.958 | K69: =IF(C69="Ocupado",INT('LEIA-ME'!$B$4-J69),"") | L69: =IF(I69="","",INDEX(dProcedimento!$D:$D,MATCH(I69,dProcedimento!$A:$A,0))) | M69: =IF(K69="","",K69/L69) | N69: =IF(K69="","",IF(K69<=L69/2,"Verde",IF(K69<=L69,"Amarelo","Vermelho"))) | O69: 46315 | P69: Ambulatório/Eletivo | Q69: Aguardando vaga em UTI
A70: CC-A09 | B70: CC | C70: Ocupado | D70: Em internação | E70: P10060 | F70: GM.M. | G70: 59 | H70: M | I70: PR08 | J70: 46311.5 | K70: =IF(C70="Ocupado",INT('LEIA-ME'!$B$4-J70),"") | L70: =IF(I70="","",INDEX(dProcedimento!$D:$D,MATCH(I70,dProcedimento!$A:$A,0))) | M70: =IF(K70="","",K70/L70) | N70: =IF(K70="","",IF(K70<=L70/2,"Verde",IF(K70<=L70,"Amarelo","Vermelho"))) | O70: 46316 | P70: Ambulatório/Eletivo
A71: CC-A10 | B71: CC | C71: Vago | D71: Leito disponível | K71: =IF(C71="Ocupado",INT('LEIA-ME'!$B$4-J71),"") | L71: =IF(I71="","",INDEX(dProcedimento!$D:$D,MATCH(I71,dProcedimento!$A:$A,0))) | M71: =IF(K71="","",K71/L71) | N71: =IF(K71="","",IF(K71<=L71/2,"Verde",IF(K71<=L71,"Amarelo","Vermelho"))) | X71: 46313.996
A72: CC-A11 | B72: CC | C72: Bloqueado | D72: Bloqueado | K72: =IF(C72="Ocupado",INT('LEIA-ME'!$B$4-J72),"") | L72: =IF(I72="","",INDEX(dProcedimento!$D:$D,MATCH(I72,dProcedimento!$A:$A,0))) | M72: =IF(K72="","",K72/L72) | N72: =IF(K72="","",IF(K72<=L72/2,"Verde",IF(K72<=L72,"Amarelo","Vermelho"))) | R72: Isolamento de coorte | S72: 46306.5
A73: CC-A12 | B73: CC | C73: Ocupado | D73: Em internação | E73: P10061 | F73: RV.J. | G73: 44 | H73: F | I73: PR10 | J73: 46309.917 | K73: =IF(C73="Ocupado",INT('LEIA-ME'!$B$4-J73),"") | L73: =IF(I73="","",INDEX(dProcedimento!$D:$D,MATCH(I73,dProcedimento!$A:$A,0))) | M73: =IF(K73="","",K73/L73) | N73: =IF(K73="","",IF(K73<=L73/2,"Verde",IF(K73<=L73,"Amarelo","Vermelho"))) | O73: 46317 | P73: Ambulatório/Eletivo
A74: CC-A13 | B74: CC | C74: Ocupado | D74: Alta prevista hoje | E74: P10062 | F74: OE.R. | G74: 48 | H74: F | I74: PR11 | J74: 46312.25 | K74: =IF(C74="Ocupado",INT('LEIA-ME'!$B$4-J74),"") | L74: =IF(I74="","",INDEX(dProcedimento!$D:$D,MATCH(I74,dProcedimento!$A:$A,0))) | M74: =IF(K74="","",K74/L74) | N74: =IF(K74="","",IF(K74<=L74/2,"Verde",IF(K74<=L74,"Amarelo","Vermelho"))) | O74: 46314 | P74: Ambulatório/Eletivo
A75: CC-A14 | B75: CC | C75: Ocupado | D75: Aguardando desocupação | E75: P10063 | F75: BF.C. | G75: 50 | H75: M | I75: PR08 | J75: 46306.917 | K75: =IF(C75="Ocupado",INT('LEIA-ME'!$B$4-J75),"") | L75: =IF(I75="","",INDEX(dProcedimento!$D:$D,MATCH(I75,dProcedimento!$A:$A,0))) | M75: =IF(K75="","",K75/L75) | N75: =IF(K75="","",IF(K75<=L75/2,"Verde",IF(K75<=L75,"Amarelo","Vermelho"))) | O75: 46316 | P75: Centro Cirúrgico | Q75: Aguardando leito de retaguarda
A76: CC-A15 | B76: CC | C76: Ocupado | D76: Em internação | E76: P10064 | F76: TI.E. | G76: 52 | H76: F | I76: PR08 | J76: 46312.875 | K76: =IF(C76="Ocupado",INT('LEIA-ME'!$B$4-J76),"") | L76: =IF(I76="","",INDEX(dProcedimento!$D:$D,MATCH(I76,dProcedimento!$A:$A,0))) | M76: =IF(K76="","",K76/L76) | N76: =IF(K76="","",IF(K76<=L76/2,"Verde",IF(K76<=L76,"Amarelo","Vermelho"))) | O76: 46317 | P76: Pronto-Socorro
A77: CC-A16 | B77: CC | C77: Ocupado | D77: Em internação | E77: P10065 | F77: TG.V. | G77: 62 | H77: M | I77: PR09 | J77: 46312.917 | K77: =IF(C77="Ocupado",INT('LEIA-ME'!$B$4-J77),"") | L77: =IF(I77="","",INDEX(dProcedimento!$D:$D,MATCH(I77,dProcedimento!$A:$A,0))) | M77: =IF(K77="","",K77/L77) | N77: =IF(K77="","",IF(K77<=L77/2,"Verde",IF(K77<=L77,"Amarelo","Vermelho"))) | O77: 46317 | P77: Ambulatório/Eletivo
A78: CC-A17 | B78: CC | C78: Ocupado | D78: Em internação | E78: P10066 | F78: NN.T. | G78: 60 | H78: F | I78: PR10 | J78: 46290.875 | K78: =IF(C78="Ocupado",INT('LEIA-ME'!$B$4-J78),"") | L78: =IF(I78="","",INDEX(dProcedimento!$D:$D,MATCH(I78,dProcedimento!$A:$A,0))) | M78: =IF(K78="","",K78/L78) | N78: =IF(K78="","",IF(K78<=L78/2,"Verde",IF(K78<=L78,"Amarelo","Vermelho"))) | O78: 46315 | P78: Pronto-Socorro | Q78: Aguardando exame de imagem
A79: CC-A18 | B79: CC | C79: Ocupado | D79: Em internação | E79: P10067 | F79: DC.E. | G79: 73 | H79: M | I79: PR10 | J79: 46312 | K79: =IF(C79="Ocupado",INT('LEIA-ME'!$B$4-J79),"") | L79: =IF(I79="","",INDEX(dProcedimento!$D:$D,MATCH(I79,dProcedimento!$A:$A,0))) | M79: =IF(K79="","",K79/L79) | N79: =IF(K79="","",IF(K79<=L79/2,"Verde",IF(K79<=L79,"Amarelo","Vermelho"))) | O79: 46321 | P79: Regulação (SISREG)
A80: CC-A19 | B80: CC | C80: Ocupado | D80: Em internação | E80: P10068 | F80: JB.V. | G80: 19 | H80: F | I80: PR08 | J80: 46308.75 | K80: =IF(C80="Ocupado",INT('LEIA-ME'!$B$4-J80),"") | L80: =IF(I80="","",INDEX(dProcedimento!$D:$D,MATCH(I80,dProcedimento!$A:$A,0))) | M80: =IF(K80="","",K80/L80) | N80: =IF(K80="","",IF(K80<=L80/2,"Verde",IF(K80<=L80,"Amarelo","Vermelho"))) | O80: 46315 | P80: Ambulatório/Eletivo | Q80: Aguardando exame de imagem
A81: CC-A20 | B81: CC | C81: Ocupado | D81: Em internação | E81: P10069 | F81: JJ.T. | G81: 33 | H81: M | I81: PR11 | J81: 46312.042 | K81: =IF(C81="Ocupado",INT('LEIA-ME'!$B$4-J81),"") | L81: =IF(I81="","",INDEX(dProcedimento!$D:$D,MATCH(I81,dProcedimento!$A:$A,0))) | M81: =IF(K81="","",K81/L81) | N81: =IF(K81="","",IF(K81<=L81/2,"Verde",IF(K81<=L81,"Amarelo","Vermelho"))) | O81: 46316 | P81: Ambulatório/Eletivo
A82: CC-B21 | B82: CC | C82: Ocupado | D82: Em internação | E82: P10070 | F82: EN.G. | G82: 49 | H82: F | I82: PR08 | J82: 46312.583 | K82: =IF(C82="Ocupado",INT('LEIA-ME'!$B$4-J82),"") | L82: =IF(I82="","",INDEX(dProcedimento!$D:$D,MATCH(I82,dProcedimento!$A:$A,0))) | M82: =IF(K82="","",K82/L82) | N82: =IF(K82="","",IF(K82<=L82/2,"Verde",IF(K82<=L82,"Amarelo","Vermelho"))) | O82: 46317 | P82: Regulação (SISREG)
A83: CC-B22 | B83: CC | C83: Ocupado | D83: Em internação | E83: P10071 | F83: RO.M. | G83: 45 | H83: F | I83: PR10 | J83: 46311.625 | K83: =IF(C83="Ocupado",INT('LEIA-ME'!$B$4-J83),"") | L83: =IF(I83="","",INDEX(dProcedimento!$D:$D,MATCH(I83,dProcedimento!$A:$A,0))) | M83: =IF(K83="","",K83/L83) | N83: =IF(K83="","",IF(K83<=L83/2,"Verde",IF(K83<=L83,"Amarelo","Vermelho"))) | O83: 46319 | P83: Ambulatório/Eletivo
A84: CC-B23 | B84: CC | C84: Vago | D84: Leito disponível | K84: =IF(C84="Ocupado",INT('LEIA-ME'!$B$4-J84),"") | L84: =IF(I84="","",INDEX(dProcedimento!$D:$D,MATCH(I84,dProcedimento!$A:$A,0))) | M84: =IF(K84="","",K84/L84) | N84: =IF(K84="","",IF(K84<=L84/2,"Verde",IF(K84<=L84,"Amarelo","Vermelho"))) | X84: 46313.916
A85: CC-B24 | B85: CC | C85: Ocupado | D85: Em internação | E85: P10072 | F85: SA.F. | G85: 30 | H85: M | I85: PR13 | J85: 46313.208 | K85: =IF(C85="Ocupado",INT('LEIA-ME'!$B$4-J85),"") | L85: =IF(I85="","",INDEX(dProcedimento!$D:$D,MATCH(I85,dProcedimento!$A:$A,0))) | M85: =IF(K85="","",K85/L85) | N85: =IF(K85="","",IF(K85<=L85/2,"Verde",IF(K85<=L85,"Amarelo","Vermelho"))) | O85: 46316 | P85: Ambulatório/Eletivo
A86: CC-B25 | B86: CC | C86: Ocupado | D86: Em internação | E86: P10073 | F86: EF.A. | G86: 39 | H86: F | I86: PR10 | J86: 46310.833 | K86: =IF(C86="Ocupado",INT('LEIA-ME'!$B$4-J86),"") | L86: =IF(I86="","",INDEX(dProcedimento!$D:$D,MATCH(I86,dProcedimento!$A:$A,0))) | M86: =IF(K86="","",K86/L86) | N86: =IF(K86="","",IF(K86<=L86/2,"Verde",IF(K86<=L86,"Amarelo","Vermelho"))) | O86: 46317 | P86: Ambulatório/Eletivo
A87: CC-B26 | B87: CC | C87: Ocupado | D87: Em internação | E87: P10074 | F87: AM.C. | G87: 28 | H87: M | I87: PR10 | J87: 46308.667 | K87: =IF(C87="Ocupado",INT('LEIA-ME'!$B$4-J87),"") | L87: =IF(I87="","",INDEX(dProcedimento!$D:$D,MATCH(I87,dProcedimento!$A:$A,0))) | M87: =IF(K87="","",K87/L87) | N87: =IF(K87="","",IF(K87<=L87/2,"Verde",IF(K87<=L87,"Amarelo","Vermelho"))) | O87: 46317 | P87: Pronto-Socorro
A88: CC-B27 | B88: CC | C88: Ocupado | D88: Em internação | E88: P10075 | F88: GT.E. | G88: 18 | H88: F | I88: PR08 | J88: 46312.792 | K88: =IF(C88="Ocupado",INT('LEIA-ME'!$B$4-J88),"") | L88: =IF(I88="","",INDEX(dProcedimento!$D:$D,MATCH(I88,dProcedimento!$A:$A,0))) | M88: =IF(K88="","",K88/L88) | N88: =IF(K88="","",IF(K88<=L88/2,"Verde",IF(K88<=L88,"Amarelo","Vermelho"))) | O88: 46315 | P88: Centro Cirúrgico
A89: CC-B28 | B89: CC | C89: Vago | D89: Leito disponível | K89: =IF(C89="Ocupado",INT('LEIA-ME'!$B$4-J89),"") | L89: =IF(I89="","",INDEX(dProcedimento!$D:$D,MATCH(I89,dProcedimento!$A:$A,0))) | M89: =IF(K89="","",K89/L89) | N89: =IF(K89="","",IF(K89<=L89/2,"Verde",IF(K89<=L89,"Amarelo","Vermelho"))) | X89: 46314.154
A90: CC-B29 | B90: CC | C90: Ocupado | D90: Alta médica dada | E90: P10076 | F90: DL.R. | G90: 54 | H90: F | I90: PR11 | J90: 46312.875 | K90: =IF(C90="Ocupado",INT('LEIA-ME'!$B$4-J90),"") | L90: =IF(I90="","",INDEX(dProcedimento!$D:$D,MATCH(I90,dProcedimento!$A:$A,0))) | M90: =IF(K90="","",K90/L90) | N90: =IF(K90="","",IF(K90<=L90/2,"Verde",IF(K90<=L90,"Amarelo","Vermelho"))) | O90: 46314 | P90: Ambulatório/Eletivo
A91: CC-B30 | B91: CC | C91: Em higienização | D91: Em higienização | K91: =IF(C91="Ocupado",INT('LEIA-ME'!$B$4-J91),"") | L91: =IF(I91="","",INDEX(dProcedimento!$D:$D,MATCH(I91,dProcedimento!$A:$A,0))) | M91: =IF(K91="","",K91/L91) | N91: =IF(K91="","",IF(K91<=L91/2,"Verde",IF(K91<=L91,"Amarelo","Vermelho"))) | T91: Terminal | U91: 46314.215
A92: CC-B31 | B92: CC | C92: Ocupado | D92: Alta prevista hoje | E92: P10077 | F92: IJ.D. | G92: 18 | H92: M | I92: PR09 | J92: 46310.833 | K92: =IF(C92="Ocupado",INT('LEIA-ME'!$B$4-J92),"") | L92: =IF(I92="","",INDEX(dProcedimento!$D:$D,MATCH(I92,dProcedimento!$A:$A,0))) | M92: =IF(K92="","",K92/L92) | N92: =IF(K92="","",IF(K92<=L92/2,"Verde",IF(K92<=L92,"Amarelo","Vermelho"))) | O92: 46314 | P92: Transferência interna | Q92: Aguardando procedimento cirúrgico
A93: CC-B32 | B93: CC | C93: Ocupado | D93: Aguardando desocupação | E93: P10078 | F93: DT.S. | G93: 60 | H93: F | I93: PR12 | J93: 46305.583 | K93: =IF(C93="Ocupado",INT('LEIA-ME'!$B$4-J93),"") | L93: =IF(I93="","",INDEX(dProcedimento!$D:$D,MATCH(I93,dProcedimento!$A:$A,0))) | M93: =IF(K93="","",K93/L93) | N93: =IF(K93="","",IF(K93<=L93/2,"Verde",IF(K93<=L93,"Amarelo","Vermelho"))) | O93: 46316 | P93: Transferência interna | Q93: Aguardando atenção domiciliar
A94: CC-B33 | B94: CC | C94: Ocupado | D94: Alta prevista hoje | E94: P10079 | F94: VM.C. | G94: 51 | H94: F | I94: PR08 | J94: 46311.625 | K94: =IF(C94="Ocupado",INT('LEIA-ME'!$B$4-J94),"") | L94: =IF(I94="","",INDEX(dProcedimento!$D:$D,MATCH(I94,dProcedimento!$A:$A,0))) | M94: =IF(K94="","",K94/L94) | N94: =IF(K94="","",IF(K94<=L94/2,"Verde",IF(K94<=L94,"Amarelo","Vermelho"))) | O94: 46314 | P94: Ambulatório/Eletivo | Q94: Aguardando procedimento cirúrgico
A95: CC-B34 | B95: CC | C95: Ocupado | D95: Em internação | E95: P10080 | F95: RJ.I. | G95: 52 | H95: F | I95: PR09 | J95: 46313 | K95: =IF(C95="Ocupado",INT('LEIA-ME'!$B$4-J95),"") | L95: =IF(I95="","",INDEX(dProcedimento!$D:$D,MATCH(I95,dProcedimento!$A:$A,0))) | M95: =IF(K95="","",K95/L95) | N95: =IF(K95="","",IF(K95<=L95/2,"Verde",IF(K95<=L95,"Amarelo","Vermelho"))) | O95: 46318 | P95: Pronto-Socorro
A96: CC-B35 | B96: CC | C96: Ocupado | D96: Em internação | E96: P10081 | F96: LO.S. | G96: 56 | H96: M | I96: PR11 | J96: 46312.917 | K96: =IF(C96="Ocupado",INT('LEIA-ME'!$B$4-J96),"") | L96: =IF(I96="","",INDEX(dProcedimento!$D:$D,MATCH(I96,dProcedimento!$A:$A,0))) | M96: =IF(K96="","",K96/L96) | N96: =IF(K96="","",IF(K96<=L96/2,"Verde",IF(K96<=L96,"Amarelo","Vermelho"))) | O96: 46315 | P96: Ambulatório/Eletivo
A97: CC-B36 | B97: CC | C97: Ocupado | D97: Em internação | E97: P10082 | F97: RN.L. | G97: 41 | H97: F | I97: PR08 | J97: 46313.125 | K97: =IF(C97="Ocupado",INT('LEIA-ME'!$B$4-J97),"") | L97: =IF(I97="","",INDEX(dProcedimento!$D:$D,MATCH(I97,dProcedimento!$A:$A,0))) | M97: =IF(K97="","",K97/L97) | N97: =IF(K97="","",IF(K97<=L97/2,"Verde",IF(K97<=L97,"Amarelo","Vermelho"))) | O97: 46317 | P97: Regulação (SISREG)
A98: CC-B37 | B98: CC | C98: Em higienização | D98: Em higienização | K98: =IF(C98="Ocupado",INT('LEIA-ME'!$B$4-J98),"") | L98: =IF(I98="","",INDEX(dProcedimento!$D:$D,MATCH(I98,dProcedimento!$A:$A,0))) | M98: =IF(K98="","",K98/L98) | N98: =IF(K98="","",IF(K98<=L98/2,"Verde",IF(K98<=L98,"Amarelo","Vermelho"))) | T98: Concorrente | U98: 46314.217
A99: CC-B38 | B99: CC | C99: Ocupado | D99: Alta médica dada | E99: P10083 | F99: HM.M. | G99: 44 | H99: M | I99: PR12 | J99: 46307.542 | K99: =IF(C99="Ocupado",INT('LEIA-ME'!$B$4-J99),"") | L99: =IF(I99="","",INDEX(dProcedimento!$D:$D,MATCH(I99,dProcedimento!$A:$A,0))) | M99: =IF(K99="","",K99/L99) | N99: =IF(K99="","",IF(K99<=L99/2,"Verde",IF(K99<=L99,"Amarelo","Vermelho"))) | O99: 46314 | P99: Centro Cirúrgico
A100: CC-B39 | B100: CC | C100: Vago | D100: Leito disponível | K100: =IF(C100="Ocupado",INT('LEIA-ME'!$B$4-J100),"") | L100: =IF(I100="","",INDEX(dProcedimento!$D:$D,MATCH(I100,dProcedimento!$A:$A,0))) | M100: =IF(K100="","",K100/L100) | N100: =IF(K100="","",IF(K100<=L100/2,"Verde",IF(K100<=L100,"Amarelo","Vermelho"))) | X100: 46314.124
...

Sheet fSaidas
A1: id_saida | B1: data | C1: id_unidade | D1: tipo_saida | E1: alta_medica | F1: saida_paciente | G1: inicio_higienizacao | H1: fim_higienizacao | I1: tipo_higienizacao | J1: nova_ocupacao | K1: min_alta_ate_saida | L1: min_saida_ate_inicio_hig | M1: min_higienizacao | N1: min_liberacao_ate_ocupacao | O1: min_giro_total | P1: saida_ate_10h
A2: SA0001 | B2: 46285 | C2: CM | D2: Alta | E2: 46285.371 | F2: 46285.447 | G2: 46285.454 | H2: 46285.492 | I2: Concorrente | J2: 46285.623 | K2: 111 | L2: 10 | M2: 54 | N2: 189 | O2: 253 | P2: =IF(D2="Óbito","",IF(HOUR(F2)<10,"Sim","Não"))
A3: SA0002 | B3: 46285 | C3: CM | D3: Alta | E3: 46285.394 | F3: 46285.52 | G3: 46285.531 | H3: 46285.549 | I3: Concorrente | J3: 46285.65 | K3: 182 | L3: 16 | M3: 25 | N3: 146 | O3: 187 | P3: =IF(D3="Óbito","",IF(HOUR(F3)<10,"Sim","Não"))
A4: SA0003 | B4: 46285 | C4: CM | D4: Alta | E4: 46285.512 | F4: 46285.674 | G4: 46285.724 | H4: 46285.789 | I4: Terminal | J4: 46285.878 | K4: 233 | L4: 73 | M4: 93 | N4: 129 | O4: 295 | P4: =IF(D4="Óbito","",IF(HOUR(F4)<10,"Sim","Não"))
A5: SA0004 | B5: 46285 | C5: CM | D5: Alta | E5: 46285.545 | F5: 46285.635 | G5: 46285.659 | H5: 46285.697 | I5: Concorrente | J5: 46285.859 | K5: 130 | L5: 35 | M5: 54 | N5: 234 | O5: 322 | P5: =IF(D5="Óbito","",IF(HOUR(F5)<10,"Sim","Não"))
A6: SA0005 | B6: 46285 | C6: CM | D6: Óbito | E6: 46285.207 | F6: 46285.265 | G6: 46285.293 | H6: 46285.331 | I6: Concorrente | J6: 46285.376 | K6: 84 | L6: 41 | M6: 55 | N6: 64 | O6: 160 | P6: =IF(D6="Óbito","",IF(HOUR(F6)<10,"Sim","Não"))
A7: SA0006 | B7: 46285 | C7: CM | D7: Transferência externa | E7: 46285.424 | F7: 46285.517 | G7: 46285.551 | H7: 46285.592 | I7: Concorrente | J7: 46285.66 | K7: 133 | L7: 50 | M7: 59 | N7: 98 | O7: 206 | P7: =IF(D7="Óbito","",IF(HOUR(F7)<10,"Sim","Não"))
A8: SA0007 | B8: 46286 | C8: CM | D8: Alta | E8: 46286.424 | F8: 46286.615 | G8: 46286.622 | H8: 46286.66 | I8: Concorrente | J8: 46286.803 | K8: 275 | L8: 11 | M8: 54 | N8: 206 | O8: 272 | P8: =IF(D8="Óbito","",IF(HOUR(F8)<10,"Sim","Não"))
A9: SA0008 | B9: 46286 | C9: CM | D9: Alta | E9: 46286.515 | F9: 46286.579 | G9: 46286.588 | H9: 46286.612 | I9: Concorrente | J9: 46286.667 | K9: 92 | L9: 13 | M9: 34 | N9: 80 | O9: 128 | P9: =IF(D9="Óbito","",IF(HOUR(F9)<10,"Sim","Não"))
A10: SA0009 | B10: 46286 | C10: CM | D10: Alta | E10: 46286.393 | F10: 46286.572 | G10: 46286.59 | H10: 46286.656 | I10: Terminal | J10: 46286.794 | K10: 258 | L10: 25 | M10: 95 | N10: 199 | O10: 319 | P10: =IF(D10="Óbito","",IF(HOUR(F10)<10,"Sim","Não"))
A11: SA0010 | B11: 46286 | C11: CM | D11: Alta | E11: 46286.435 | F11: 46286.568 | G11: 46286.575 | H11: 46286.603 | I11: Concorrente | J11: 46286.619 | K11: 192 | L11: 10 | M11: 40 | N11: 24 | O11: 73 | P11: =IF(D11="Óbito","",IF(HOUR(F11)<10,"Sim","Não"))
A12: SA0011 | B12: 46286 | C12: CM | D12: Alta | E12: 46286.556 | F12: 46286.644 | G12: 46286.686 | H12: 46286.717 | I12: Concorrente | J12: 46286.789 | K12: 126 | L12: 61 | M12: 44 | N12: 103 | O12: 209 | P12: =IF(D12="Óbito","",IF(HOUR(F12)<10,"Sim","Não"))
A13: SA0012 | B13: 46286 | C13: CM | D13: Alta | E13: 46286.425 | F13: 46286.493 | G13: 46286.508 | H13: 46286.537 | I13: Concorrente | J13: 46286.581 | K13: 98 | L13: 21 | M13: 41 | N13: 63 | O13: 126 | P13: =IF(D13="Óbito","",IF(HOUR(F13)<10,"Sim","Não"))
... A1007: SA1006 | B1007: 46314 | C1007: INF | D1007: Alta | E1007: 46314.418 | F1007: 46314.552 | G1007: 46314.568 | H1007: 46314.61 | I1007: Terminal | J1007: 46314.697 | K1007: 193 | L1007: 23 | M1007: 60 | N1007: 126 | O1007: 209 | P1007: =IF(D1007="Óbito","",IF(HOUR(F1007)<10,"Sim","Não"))

Sheet fSolicitacoes
A1: id_solicitacao | B1: data_solicitacao | C1: origem | D1: id_unidade_destino | E1: prioridade | F1: data_alocacao | G1: status | H1: tempo_espera_h | I1: atendida_ate_6h
A2: SOL-00001 | B2: 46285.517 | C2: Regulação (SISREG) | D2: CM | E2: Urgência | F2: 46285.926 | G2: Atendida | H2: 9.8 | I2: =IF(AND(G2="Atendida",H2<=6),"Sim","Não")
A3: SOL-00002 | B3: 46285.57 | C3: Pronto-Socorro | D3: PED | E3: Emergência | F3: 46285.617 | G3: Atendida | H3: 1.1 | I3: =IF(AND(G3="Atendida",H3<=6),"Sim","Não")
A4: SOL-00003 | B4: 46285.103 | C4: Centro Cirúrgico | D4: UTI | E4: Eletiva | F4: 46285.597 | G4: Atendida | H4: 11.9 | I4: =IF(AND(G4="Atendida",H4<=6),"Sim","Não")
A5: SOL-00004 | B5: 46285.18 | C5: Pronto-Socorro | D5: PED | E5: Urgência | F5: 46285.306 | G5: Atendida | H5: 3 | I5: =IF(AND(G5="Atendida",H5<=6),"Sim","Não")
A6: SOL-00005 | B6: 46285.019 | C6: Ambulatório/Eletivo | D6: CM | E6: Eletiva | F6: 46285.52 | G6: Atendida | H6: 12 | I6: =IF(AND(G6="Atendida",H6<=6),"Sim","Não")
A7: SOL-00006 | B7: 46285.903 | C7: Pronto-Socorro | D7: CM | E7: Emergência | F7: 46285.995 | G7: Atendida | H7: 2.2 | I7: =IF(AND(G7="Atendida",H7<=6),"Sim","Não")
A8: SOL-00007 | B8: 46285.917 | C8: Pronto-Socorro | D8: CM | E8: Urgência | F8: 46287.601 | G8: Atendida | H8: 40.4 | I8: =IF(AND(G8="Atendida",H8<=6),"Sim","Não")
A9: SOL-00008 | B9: 46285.533 | C9: Pronto-Socorro | D9: MAT | E9: Urgência | F9: 46285.837 | G9: Atendida | H9: 7.3 | I9: =IF(AND(G9="Atendida",H9<=6),"Sim","Não")
A10: SOL-00009 | B10: 46285.7 | C10: Pronto-Socorro | D10: CM | E10: Emergência | F10: 46285.906 | G10: Atendida | H10: 4.9 | I10: =IF(AND(G10="Atendida",H10<=6),"Sim","Não")
A11: SOL-00010 | B11: 46285.903 | C11: Pronto-Socorro | D11: CM | E11: Urgência | F11: 46286.64 | G11: Atendida | H11: 17.7 | I11: =IF(AND(G11="Atendida",H11<=6),"Sim","Não")
A12: SOL-00011 | B12: 46285.298 | C12: Pronto-Socorro | D12: MAT | E12: Urgência | F12: 46285.422 | G12: Atendida | H12: 3 | I12: =IF(AND(G12="Atendida",H12<=6),"Sim","Não")
A13: SOL-00012 | B13: 46285.206 | C13: Pronto-Socorro | D13: CM | E13: Eletiva | G13: Cancelada | H13: 14.8 | I13: =IF(AND(G13="Atendida",H13<=6),"Sim","Não")
A14: SOL-00013 | B14: 46285.371 | C14: Centro Cirúrgico | D14: ORT | E14: Urgência | F14: 46286.511 | G14: Atendida | H14: 27.4 | I14: =IF(AND(G14="Atendida",H14<=6),"Sim","Não")
A15: SOL-00014 | B15: 46285.492 | C15: Pronto-Socorro | D15: UCI | E15: Urgência | F15: 46285.838 | G15: Atendida | H15: 8.3 | I15: =IF(AND(G15="Atendida",H15<=6),"Sim","Não")
A16: SOL-00015 | B16: 46285.062 | C16: Pronto-Socorro | D16: CM | E16: Emergência | F16: 46285.174 | G16: Atendida | H16: 2.7 | I16: =IF(AND(G16="Atendida",H16<=6),"Sim","Não")
A17: SOL-00016 | B17: 46285.406 | C17: Pronto-Socorro | D17: CM | E17: Eletiva | F17: 46286.607 | G17: Atendida | H17: 28.8 | I17: =IF(AND(G17="Atendida",H17<=6),"Sim","Não")
A18: SOL-00017 | B18: 46285.378 | C18: Pronto-Socorro | D18: CC | E18: Eletiva | F18: 46286.019 | G18: Atendida | H18: 15.4 | I18: =IF(AND(G18="Atendida",H18<=6),"Sim","Não")
A19: SOL-00018 | B19: 46285.998 | C19: Ambulatório/Eletivo | D19: CM | E19: Eletiva | F19: 46287.138 | G19: Atendida | H19: 27.4 | I19: =IF(AND(G19="Atendida",H19<=6),"Sim","Não")
A20: SOL-00019 | B20: 46285.826 | C20: Ambulatório/Eletivo | D20: UTI | E20: Eletiva | F20: 46289.826 | G20: Atendida | H20: 96 | I20: =IF(AND(G20="Atendida",H20<=6),"Sim","Não")
A21: SOL-00020 | B21: 46285.577 | C21: Pronto-Socorro | D21: ONC | E21: Eletiva | F21: 46286.615 | G21: Atendida | H21: 24.9 | I21: =IF(AND(G21="Atendida",H21<=6),"Sim","Não")
A22: SOL-00021 | B22: 46285 | C22: Regulação (SISREG) | D22: CM | E22: Urgência | F22: 46285.877 | G22: Atendida | H22: 21 | I22: =IF(AND(G22="Atendida",H22<=6),"Sim","Não")
A23: SOL-00022 | B23: 46285.652 | C23: Pronto-Socorro | D23: CM | E23: Emergência | F23: 46285.853 | G23: Atendida | H23: 4.8 | I23: =IF(AND(G23="Atendida",H23<=6),"Sim","Não")
A24: SOL-00023 | B24: 46285.44 | C24: Pronto-Socorro | D24: CM | E24: Eletiva | F24: 46286.088 | G24: Atendida | H24: 15.6 | I24: =IF(AND(G24="Atendida",H24<=6),"Sim","Não")
A25: SOL-00024 | B25: 46285.793 | C25: Pronto-Socorro | D25: ONC | E25: Emergência | F25: 46285.899 | G25: Atendida | H25: 2.5 | I25: =IF(AND(G25="Atendida",H25<=6),"Sim","Não")
A26: SOL-00025 | B26: 46285.663 | C26: Pronto-Socorro | D26: CC | E26: Urgência | G26: Cancelada | H26: 5.5 | I26: =IF(AND(G26="Atendida",H26<=6),"Sim","Não")
A27: SOL-00026 | B27: 46286.973 | C27: Ambulatório/Eletivo | D27: CM | E27: Eletiva | F27: 46287.251 | G27: Atendida | H27: 6.7 | I27: =IF(AND(G27="Atendida",H27<=6),"Sim","Não")
A28: SOL-00027 | B28: 46286.258 | C28: Regulação (SISREG) | D28: PED | E28: Urgência | F28: 46286.387 | G28: Atendida | H28: 3.1 | I28: =IF(AND(G28="Atendida",H28<=6),"Sim","Não")
A29: SOL-00028 | B29: 46286.469 | C29: Pronto-Socorro | D29: CM | E29: Urgência | F29: 46287.023 | G29: Atendida | H29: 13.3 | I29: =IF(AND(G29="Atendida",H29<=6),"Sim","Não")
A30: SOL-00029 | B30: 46286.513 | C30: Regulação (SISREG) | D30: MAT | E30: Urgência | F30: 46286.685 | G30: Atendida | H30: 4.1 | I30: =IF(AND(G30="Atendida",H30<=6),"Sim","Não")
A31: SOL-00030 | B31: 46286.195 | C31: Pronto-Socorro | D31: CM | E31: Eletiva | F31: 46289.614 | G31: Atendida | H31: 82.1 | I31: =IF(AND(G31="Atendida",H31<=6),"Sim","Não")
A32: SOL-00031 | B32: 46286.556 | C32: Pronto-Socorro | D32: UCI | E32: Urgência | G32: Cancelada | H32: 3.9 | I32: =IF(AND(G32="Atendida",H32<=6),"Sim","Não")
A33: SOL-00032 | B33: 46286.012 | C33: Pronto-Socorro | D33: ORT | E33: Urgência | F33: 46286.773 | G33: Atendida | H33: 18.3 | I33: =IF(AND(G33="Atendida",H33<=6),"Sim","Não")
A34: SOL-00033 | B34: 46286.912 | C34: Pronto-Socorro | D34: PED | E34: Emergência | F34: 46286.95 | G34: Atendida | H34: 0.9 | I34: =IF(AND(G34="Atendida",H34<=6),"Sim","Não")
A35: SOL-00034 | B35: 46286.723 | C35: Pronto-Socorro | D35: ORT | E35: Urgência | F35: 46287.125 | G35: Atendida | H35: 9.6 | I35: =IF(AND(G35="Atendida",H35<=6),"Sim","Não")
A36: SOL-00035 | B36: 46286.354 | C36: Pronto-Socorro | D36: UTI | E36: Urgência | F36: 46286.867 | G36: Atendida | H36: 12.3 | I36: =IF(AND(G36="Atendida",H36<=6),"Sim","Não")
A37: SOL-00036 | B37: 46286.808 | C37: Pronto-Socorro | D37: UTIN | E37: Urgência | F37: 46287.081 | G37: Atendida | H37: 6.5 | I37: =IF(AND(G37="Atendida",H37<=6),"Sim","Não")
A38: SOL-00037 | B38: 46286.606 | C38: Centro Cirúrgico | D38: CM | E38: Eletiva | F38: 46287.188 | G38: Atendida | H38: 14 | I38: =IF(AND(G38="Atendida",H38<=6),"Sim","Não")
A39: SOL-00038 | B39: 46286.53 | C39: Centro Cirúrgico | D39: CM | E39: Urgência | F39: 46286.807 | G39: Atendida | H39: 6.7 | I39: =IF(AND(G39="Atendida",H39<=6),"Sim","Não")
A40: SOL-00039 | B40: 46286.192 | C40: Pronto-Socorro | D40: UTI | E40: Eletiva | F40: 46287.017 | G40: Atendida | H40: 19.8 | I40: =IF(AND(G40="Atendida",H40<=6),"Sim","Não")
A41: SOL-00040 | B41: 46286.697 | C41: Regulação (SISREG) | D41: MAT | E41: Urgência | F41: 46286.778 | G41: Atendida | H41: 2 | I41: =IF(AND(G41="Atendida",H41<=6),"Sim","Não")
A42: SOL-00041 | B42: 46286.372 | C42: Regulação (SISREG) | D42: CC | E42: Emergência | F42: 46286.438 | G42: Atendida | H42: 1.6 | I42: =IF(AND(G42="Atendida",H42<=6),"Sim","Não")
A43: SOL-00042 | B43: 46286.801 | C43: Pronto-Socorro | D43: PED | E43: Eletiva | F43: 46287.087 | G43: Atendida | H43: 6.9 | I43: =IF(AND(G43="Atendida",H43<=6),"Sim","Não")
A44: SOL-00043 | B44: 46286.885 | C44: Centro Cirúrgico | D44: CM | E44: Emergência | F44: 46287.108 | G44: Atendida | H44: 5.4 | I44: =IF(AND(G44="Atendida",H44<=6),"Sim","Não")
... A53: SOL-00052 | B53: 46286.986 | C53: Regulação (SISREG) | D53: UTI | E53: Urgência | F53: 46287.397 | G53: Atendida | H53: 9.9 | I53: =IF(AND(G53="Atendida",H53<=6),"Sim","Não")
A54: SOL-00053 | B54: 46286.162 | C54: Pronto-Socorro | D54: CC | E54: Urgência | G54: Cancelada | H54: 5.1 | I54: =IF(AND(G54="Atendida",H54<=6),"Sim","Não")
A55: SOL-00054 | B55: 46286.121 | C55: Pronto-Socorro | D55: CC | E55: Emergência | F55: 46286.226 | G55: Atendida | H55: 2.5 | I55: =IF(AND(G55="Atendida",H55<=6),"Sim","Não")
A56: SOL-00055 | B56: 46286.42 | C56: Regulação (SISREG) | D56: MAT | E56: Urgência | F56: 46286.606 | G56: Atendida | H56: 4.5 | I56: =IF(AND(G56="Atendida",H56<=6),"Sim","Não")
A57: SOL-00056 | B57: 46286.929 | C57: Regulação (SISREG) | D57: ORT | E57: Urgência | F57: 46287.034 | G57: Atendida | H57: 2.5 | I57: =IF(AND(G57="Atendida",H57<=6),"Sim","Não")
A58: SOL-00057 | B58: 46286.039 | C58: Ambulatório/Eletivo | D58: PED | E58: Eletiva | F58: 46286.189 | G58: Atendida | H58: 3.6 | I58: =IF(AND(G58="Atendida",H58<=6),"Sim","Não")
A59: SOL-00058 | B59: 46286.883 | C59: Regulação (SISREG) | D59: MAT | E59: Urgência | F59: 46287.068 | G59: Atendida | H59: 4.4 | I59: =IF(AND(G59="Atendida",H59<=6),"Sim","Não")
A60: SOL-00059 | B60: 46286.673 | C60: Pronto-Socorro | D60: MAT | E60: Urgência | F60: 46287.211 | G60: Atendida | H60: 12.9 | I60: =IF(AND(G60="Atendida",H60<=6),"Sim","Não")
A61: SOL-00060 | B61: 46287.272 | C61: Pronto-Socorro | D61: INF | E61: Urgência | F61: 46287.452 | G61: Atendida | H61: 4.3 | I61: =IF(AND(G61="Atendida",H61<=6),"Sim","Não")
A62: SOL-00061 | B62: 46287.451 | C62: Pronto-Socorro | D62: PED | E62: Eletiva | F62: 46287.581 | G62: Atendida | H62: 3.1 | I62: =IF(AND(G62="Atendida",H62<=6),"Sim","Não")
A63: SOL-00062 | B63: 46287.206 | C63: Pronto-Socorro | D63: UCI | E63: Urgência | F63: 46287.338 | G63: Atendida | H63: 3.2 | I63: =IF(AND(G63="Atendida",H63<=6),"Sim","Não")
A64: SOL-00063 | B64: 46287.697 | C64: Ambulatório/Eletivo | D64: PED | E64: Eletiva | F64: 46287.893 | G64: Atendida | H64: 4.7 | I64: =IF(AND(G64="Atendida",H64<=6),"Sim","Não")
A65: SOL-00064 | B65: 46287.322 | C65: Ambulatório/Eletivo | D65: ORT | E65: Eletiva | F65: 46287.561 | G65: Atendida | H65: 5.7 | I65: =IF(AND(G65="Atendida",H65<=6),"Sim","Não")
A66: SOL-00065 | B66: 46287.878 | C66: Pronto-Socorro | D66: UTIN | E66: Urgência | F66: 46287.908 | G66: Atendida | H66: 0.7 | I66: =IF(AND(G66="Atendida",H66<=6),"Sim","Não")
... A68: SOL-00067 | B68: 46287.717 | C68: Pronto-Socorro | D68: CM | E68: Urgência | F68: 46287.84 | G68: Atendida | H68: 2.9 | I68: =IF(AND(G68="Atendida",H68<=6),"Sim","Não")
A69: SOL-00068 | B69: 46287.673 | C69: Pronto-Socorro | D69: UTI | E69: Emergência | G69: Cancelada | H69: 3.7 | I69: =IF(AND(G69="Atendida",H69<=6),"Sim","Não")
A70: SOL-00069 | B70: 46287.101 | C70: Pronto-Socorro | D70: CM | E70: Eletiva | F70: 46287.871 | G70: Atendida | H70: 18.5 | I70: =IF(AND(G70="Atendida",H70<=6),"Sim","Não")
A71: SOL-00070 | B71: 46287.783 | C71: Pronto-Socorro | D71: PED | E71: Eletiva | F71: 46287.886 | G71: Atendida | H71: 2.5 | I71: =IF(AND(G71="Atendida",H71<=6),"Sim","Não")
A72: SOL-00071 | B72: 46287.145 | C72: Regulação (SISREG) | D72: UTIN | E72: Urgência | F72: 46287.292 | G72: Atendida | H72: 3.5 | I72: =IF(AND(G72="Atendida",H72<=6),"Sim","Não")
A73: SOL-00072 | B73: 46287.331 | C73: Centro Cirúrgico | D73: CM | E73: Eletiva | F73: 46288.039 | G73: Atendida | H73: 17 | I73: =IF(AND(G73="Atendida",H73<=6),"Sim","Não")
A74: SOL-00073 | B74: 46287.173 | C74: Pronto-Socorro | D74: CM | E74: Urgência | F74: 46287.449 | G74: Atendida | H74: 6.6 | I74: =IF(AND(G74="Atendida",H74<=6),"Sim","Não")
A75: SOL-00074 | B75: 46287.107 | C75: Regulação (SISREG) | D75: UTI | E75: Urgência | F75: 46287.33 | G75: Atendida | H75: 5.4 | I75: =IF(AND(G75="Atendida",H75<=6),"Sim","Não")
A76: SOL-00075 | B76: 46287.624 | C76: Pronto-Socorro | D76: ORT | E76: Emergência | F76: 46287.95 | G76: Atendida | H76: 7.8 | I76: =IF(AND(G76="Atendida",H76<=6),"Sim","Não")
A77: SOL-00076 | B77: 46287.426 | C77: Pronto-Socorro | D77: UTIN | E77: Urgência | F77: 46288.109 | G77: Atendida | H77: 16.4 | I77: =IF(AND(G77="Atendida",H77<=6),"Sim","Não")
A78: SOL-00077 | B78: 46287.218 | C78: Pronto-Socorro | D78: ONC | E78: Urgência | F78: 46287.547 | G78: Atendida | H78: 7.9 | I78: =IF(AND(G78="Atendida",H78<=6),"Sim","Não")
A79: SOL-00078 | B79: 46287.286 | C79: Pronto-Socorro | D79: UTI | E79: Urgência | F79: 46287.802 | G79: Atendida | H79: 12.4 | I79: =IF(AND(G79="Atendida",H79<=6),"Sim","Não")
A80: SOL-00079 | B80: 46287.472 | C80: Pronto-Socorro | D80: UTI | E80: Urgência | F80: 46287.71 | G80: Atendida | H80: 5.7 | I80: =IF(AND(G80="Atendida",H80<=6),"Sim","Não")
A81: SOL-00080 | B81: 46287.38 | C81: Centro Cirúrgico | D81: PED | E81: Urgência | F81: 46287.431 | G81: Atendida | H81: 1.2 | I81: =IF(AND(G81="Atendida",H81<=6),"Sim","Não")
... A124: SOL-00123 | B124: 46289.69 | C124: Centro Cirúrgico | D124: PED | E124: Urgência | F124: 46289.799 | G124: Atendida | H124: 2.6 | I124: =IF(AND(G124="Atendida",H124<=6),"Sim","Não")
A125: SOL-00124 | B125: 46289.853 | C125: Pronto-Socorro | D125: UTIN | E125: Urgência | G125: Cancelada | H125: 5.1 | I125: =IF(AND(G125="Atendida",H125<=6),"Sim","Não")
A126: SOL-00125 | B126: 46289.167 | C126: Regulação (SISREG) | D126: MAT | E126: Urgência | F126: 46289.194 | G126: Atendida | H126: 0.7 | I126: =IF(AND(G126="Atendida",H126<=6),"Sim","Não")
A127: SOL-00126 | B127: 46289.901 | C127: Pronto-Socorro | D127: CM | E127: Eletiva | F127: 46290.508 | G127: Atendida | H127: 14.6 | I127: =IF(AND(G127="Atendida",H127<=6),"Sim","Não")
A128: SOL-00127 | B128: 46289.409 | C128: Pronto-Socorro | D128: UTI | E128: Urgência | F128: 46289.606 | G128: Atendida | H128: 4.7 | I128: =IF(AND(G128="Atendida",H128<=6),"Sim","Não")
A129: SOL-00128 | B129: 46289.367 | C129: Regulação (SISREG) | D129: CM | E129: Eletiva | F129: 46291.119 | G129: Atendida | H129: 42 | I129: =IF(AND(G129="Atendida",H129<=6),"Sim","Não")
A130: SOL-00129 | B130: 46289.856 | C130: Pronto-Socorro | D130: CM | E130: Urgência | F130: 46290.518 | G130: Atendida | H130: 15.9 | I130: =IF(AND(G130="Atendida",H130<=6),"Sim","Não")
A131: SOL-00130 | B131: 46289.238 | C131: Centro Cirúrgico | D131: UCI | E131: Urgência | F131: 46289.51 | G131: Atendida | H131: 6.5 | I131: =IF(AND(G131="Atendida",H131<=6),"Sim","Não")
A132: SOL-00131 | B132: 46289.642 | C132: Centro Cirúrgico | D132: INF | E132: Emergência | F132: 46289.783 | G132: Atendida | H132: 3.4 | I132: =IF(AND(G132="Atendida",H132<=6),"Sim","Não")
A133: SOL-00132 | B133: 46289.135 | C133: Pronto-Socorro | D133: CC | E133: Eletiva | F133: 46289.364 | G133: Atendida | H133: 5.5 | I133: =IF(AND(G133="Atendida",H133<=6),"Sim","Não")
A134: SOL-00133 | B134: 46289.616 | C134: Pronto-Socorro | D134: UCI | E134: Emergência | F134: 46289.881 | G134: Atendida | H134: 6.4 | I134: =IF(AND(G134="Atendida",H134<=6),"Sim","Não")
A135: SOL-00134 | B135: 46289.408 | C135: Pronto-Socorro | D135: CM | E135: Emergência | F135: 46289.572 | G135: Atendida | H135: 3.9 | I135: =IF(AND(G135="Atendida",H135<=6),"Sim","Não")
A136: SOL-00135 | B136: 46289.617 | C136: Pronto-Socorro | D136: CM | E136: Eletiva | F136: 46290.485 | G136: Atendida | H136: 20.8 | I136: =IF(AND(G136="Atendida",H136<=6),"Sim","Não")
A137: SOL-00136 | B137: 46289.3 | C137: Pronto-Socorro | D137: UTI | E137: Emergência | F137: 46289.549 | G137: Atendida | H137: 6 | I137: =IF(AND(G137="Atendida",H137<=6),"Sim","Não")
... A144: SOL-00143 | B144: 46289.596 | C144: Centro Cirúrgico | D144: CC | E144: Urgência | F144: 46289.626 | G144: Atendida | H144: 0.7 | I144: =IF(AND(G144="Atendida",H144<=6),"Sim","Não")
A145: SOL-00144 | B145: 46289.918 | C145: Pronto-Socorro | D145: UTI | E145: Urgência | G145: Cancelada | H145: 9.5 | I145: =IF(AND(G145="Atendida",H145<=6),"Sim","Não")
A146: SOL-00145 | B146: 46289.536 | C146: Pronto-Socorro | D146: CM | E146: Urgência | F146: 46289.966 | G146: Atendida | H146: 10.3 | I146: =IF(AND(G146="Atendida",H146<=6),"Sim","Não")
A147: SOL-00146 | B147: 46289.724 | C147: Pronto-Socorro | D147: CM | E147: Emergência | F147: 46289.874 | G147: Atendida | H147: 3.6 | I147: =IF(AND(G147="Atendida",H147<=6),"Sim","Não")
A148: SOL-00147 | B148: 46289.976 | C148: Ambulatório/Eletivo | D148: CM | E148: Eletiva | F148: 46290.708 | G148: Atendida | H148: 17.6 | I148: =IF(AND(G148="Atendida",H148<=6),"Sim","Não")
A149: SOL-00148 | B149: 46289.422 | C149: Pronto-Socorro | D149: UCI | E149: Urgência | F149: 46289.682 | G149: Atendida | H149: 6.2 | I149: =IF(AND(G149="Atendida",H149<=6),"Sim","Não")
A150: SOL-00149 | B150: 46289.901 | C150: Pronto-Socorro | D150: CM | E150: Urgência | F150: 46290.076 | G150: Atendida | H150: 4.2 | I150: =IF(AND(G150="Atendida",H150<=6),"Sim","Não")
A151: SOL-00150 | B151: 46289.665 | C151: Pronto-Socorro | D151: UCI | E151: Urgência | F151: 46290.454 | G151: Atendida | H151: 18.9 | I151: =IF(AND(G151="Atendida",H151<=6),"Sim","Não")
A152: SOL-00151 | B152: 46289.431 | C152: Pronto-Socorro | D152: ORT | E152: Urgência | F152: 46290.244 | G152: Atendida | H152: 19.5 | I152: =IF(AND(G152="Atendida",H152<=6),"Sim","Não")
A153: SOL-00152 | B153: 46289.61 | C153: Centro Cirúrgico | D153: CC | E153: Emergência | F153: 46289.737 | G153: Atendida | H153: 3 | I153: =IF(AND(G153="Atendida",H153<=6),"Sim","Não")
A154: SOL-00153 | B154: 46289.625 | C154: Ambulatório/Eletivo | D154: UTI | E154: Eletiva | F154: 46289.994 | G154: Atendida | H154: 8.8 | I154: =IF(AND(G154="Atendida",H154<=6),"Sim","Não")
A155: SOL-00154 | B155: 46289.895 | C155: Regulação (SISREG) | D155: CM | E155: Urgência | F155: 46290.284 | G155: Atendida | H155: 9.3 | I155: =IF(AND(G155="Atendida",H155<=6),"Sim","Não")
A156: SOL-00155 | B156: 46289.085 | C156: Pronto-Socorro | D156: CM | E156: Eletiva | G156: Cancelada | H156: 38.2 | I156: =IF(AND(G156="Atendida",H156<=6),"Sim","Não")
A157: SOL-00156 | B157: 46289.395 | C157: Regulação (SISREG) | D157: ORT | E157: Eletiva | F157: 46289.558 | G157: Atendida | H157: 3.9 | I157: =IF(AND(G157="Atendida",H157<=6),"Sim","Não")
...

Sheet fCustoDiaria
A1: id_unidade | B1: id_componente | C1: valor_diaria | D1: fator_dia_de_espera | E1: valor_dia_espera
A2: CM | B2: CC01 | C2: 519.2 | D2: =INDEX(dComponenteCusto!$C:$C,MATCH(B2,dComponenteCusto!$A:$A,0)) | E2: =C2*D2
A3: CM | B3: CC02 | C3: 200.6 | D3: =INDEX(dComponenteCusto!$C:$C,MATCH(B3,dComponenteCusto!$A:$A,0)) | E3: =C3*D3
A4: CM | B4: CC03 | C4: 224.2 | D4: =INDEX(dComponenteCusto!$C:$C,MATCH(B4,dComponenteCusto!$A:$A,0)) | E4: =C4*D4
A5: CM | B5: CC04 | C5: 94.4 | D5: =INDEX(dComponenteCusto!$C:$C,MATCH(B5,dComponenteCusto!$A:$A,0)) | E5: =C5*D5
A6: CM | B6: CC05 | C6: 141.6 | D6: =INDEX(dComponenteCusto!$C:$C,MATCH(B6,dComponenteCusto!$A:$A,0)) | E6: =C6*D6
A7: CC | B7: CC01 | C7: 567.6 | D7: =INDEX(dComponenteCusto!$C:$C,MATCH(B7,dComponenteCusto!$A:$A,0)) | E7: =C7*D7
A8: CC | B8: CC02 | C8: 219.3 | D8: =INDEX(dComponenteCusto!$C:$C,MATCH(B8,dComponenteCusto!$A:$A,0)) | E8: =C8*D8
A9: CC | B9: CC03 | C9: 245.1 | D9: =INDEX(dComponenteCusto!$C:$C,MATCH(B9,dComponenteCusto!$A:$A,0)) | E9: =C9*D9
A10: CC | B10: CC04 | C10: 103.2 | D10: =INDEX(dComponenteCusto!$C:$C,MATCH(B10,dComponenteCusto!$A:$A,0)) | E10: =C10*D10
A11: CC | B11: CC05 | C11: 154.8 | D11: =INDEX(dComponenteCusto!$C:$C,MATCH(B11,dComponenteCusto!$A:$A,0)) | E11: =C11*D11
A12: ORT | B12: CC01 | C12: 545.6 | D12: =INDEX(dComponenteCusto!$C:$C,MATCH(B12,dComponenteCusto!$A:$A,0)) | E12: =C12*D12
A13: ORT | B13: CC02 | C13: 210.8 | D13: =INDEX(dComponenteCusto!$C:$C,MATCH(B13,dComponenteCusto!$A:$A,0)) | E13: =C13*D13
... A51: INF | B51: CC05 | C51: 206.4 | D51: =INDEX(dComponenteCusto!$C:$C,MATCH(B51,dComponenteCusto!$A:$A,0)) | E51: =C51*D51

Sheet fAtrasosDesocupacao
A1: id_atraso | B1: id_leito | C1: id_unidade | D1: prontuario | E1: id_motivo | F1: data_alta_medica | G1: data_desocupacao | H1: situacao | I1: dias_atraso | J1: custo_dia_espera | K1: custo_total | L1: internacoes_perdidas | M1: receita_nao_realizada
A2: DES-0100 | B2: CC-B26 | C2: CC | D2: P29265 | E2: MD02 | F2: 46285.033 | G2: 46285.363 | H2: Resolvido | I2: 0.3 | J2: =ROUND(SUMIF(fCustoDiaria!$A$2:$A$51,C2,fCustoDiaria!$E$2:$E$51),2) | K2: =ROUND(I2*J2,0) | L2: =ROUND(I2/ROUND(SUMIF(fCensoDiario!$B$2:$B$301,C2,fCensoDiario!$E$2:$E$301)/SUMIF(fCensoDiario!$B$2:$B$301,C2,fCensoDiario!$K$2:$K$301),1),2) | M2: =ROUND(I2/ROUND(SUMIF(fCensoDiario!$B$2:$B$301,C2,fCensoDiario!$E$2:$E$301)/SUMIF(fCensoDiario!$B$2:$B$301,C2,fCensoDiario!$K$2:$K$301),1)*INDEX(dUnidade!$H:$H,MATCH(C2,dUnidade!$A:$A,0)),0)
A3: DES-0082 | B3: CM-B41 | C3: CM | D3: P23647 | E3: MD02 | F3: 46285.126 | G3: 46285.578 | H3: Resolvido | I3: 0.5 | J3: =ROUND(SUMIF(fCustoDiaria!$A$2:$A$51,C3,fCustoDiaria!$E$2:$E$51),2) | K3: =ROUND(I3*J3,0) | L3: =ROUND(I3/ROUND(SUMIF(fCensoDiario!$B$2:$B$301,C3,fCensoDiario!$E$2:$E$301)/SUMIF(fCensoDiario!$B$2:$B$301,C3,fCensoDiario!$K$2:$K$301),1),2) | M3: =ROUND(I3/ROUND(SUMIF(fCensoDiario!$B$2:$B$301,C3,fCensoDiario!$E$2:$E$301)/SUMIF(fCensoDiario!$B$2:$B$301,C3,fCensoDiario!$K$2:$K$301),1)*INDEX(dUnidade!$H:$H,MATCH(C3,dUnidade!$A:$A,0)),0)
A4: DES-0181 | B4: UTI-A03 | C4: UTI | D4: P28263 | E4: MD08 | F4: 46285.272 | G4: 46286.474 | H4: Resolvido | I4: 1.2 | J4: =ROUND(SUMIF(fCustoDiaria!$A$2:$A$51,C4,fCustoDiaria!$E$2:$E$51),2) | K4: =ROUND(I4*J4,0) | L4: =ROUND(I4/ROUND(SUMIF(fCensoDiario!$B$2:$B$301,C4,fCensoDiario!$E$2:$E$301)/SUMIF(fCensoDiario!$B$2:$B$301,C4,fCensoDiario!$K$2:$K$301),1),2) | M4: =ROUND(I4/ROUND(SUMIF(fCensoDiario!$B$2:$B$301,C4,fCensoDiario!$E$2:$E$301)/SUMIF(fCensoDiario!$B$2:$B$301,C4,fCensoDiario!$K$2:$K$301),1)*INDEX(dUnidade!$H:$H,MATCH(C4,dUnidade!$A:$A,0)),0)
A5: DES-0087 | B5: CM-B59 | C5: CM | D5: P29047 | E5: MD02 | F5: 46285.568 | G5: 46287.661 | H5: Resolvido | I5: 2.1 | J5: =ROUND(SUMIF(fCustoDiaria!$A$2:$A$51,C5,fCustoDiaria!$E$2:$E$51),2) | K5: =ROUND(I5*J5,0) | L5: =ROUND(I5/ROUND(SUMIF(fCensoDiario!$B$2:$B$301,C5,fCensoDiario!$E$2:$E$301)/SUMIF(fCensoDiario!$B$2:$B$301,C5,fCensoDiario!$K$2:$K$301),1),2) | M5: =ROUND(I5/ROUND(SUMIF(fCensoDiario!$B$2:$B$301,C5,fCensoDiario!$E$2:$E$301)/SUMIF(fCensoDiario!$B$2:$B$301,C5,fCensoDiario!$K$2:$K$301),1)*INDEX(dUnidade!$H:$H,MATCH(C5,dUnidade!$A:$A,0)),0)
A6: DES-0162 | B6: UCI-B07 | C6: UCI | D6: P20930 | E6: MD03 | F6: 46285.745 | G6: 46287.057 | H6: Resolvido | I6: 1.3 | J6: =ROUND(SUMIF(fCustoDiaria!$A$2:$A$51,C6,fCustoDiaria!$E$2:$E$51),2) | K6: =ROUND(I6*J6,0) | L6: =ROUND(I6/ROUND(SUMIF(fCensoDiario!$B$2:$B$301,C6,fCensoDiario!$E$2:$E$301)/SUMIF(fCensoDiario!$B$2:$B$301,C6,fCensoDiario!$K$2:$K$301),1),2) | M6: =ROUND(I6/ROUND(SUMIF(fCensoDiario!$B$2:$B$301,C6,fCensoDiario!$E$2:$E$301)/SUMIF(fCensoDiario!$B$2:$B$301,C6,fCensoDiario!$K$2:$K$301),1)*INDEX(dUnidade!$H:$H,MATCH(C6,dUnidade!$A:$A,0)),0)
A7: DES-0138 | B7: ONC-A05 | C7: ONC | D7: P27651 | E7: MD02 | F7: 46285.792 | G7: 46286.742 | H7: Resolvido | I7: 0.9 | J7: =ROUND(SUMIF(fCustoDiaria!$A$2:$A$51,C7,fCustoDiaria!$E$2:$E$51),2) | K7: =ROUND(I7*J7,0) | L7: =ROUND(I7/ROUND(SUMIF(fCensoDiario!$B$2:$B$301,C7,fCensoDiario!$E$2:$E$301)/SUMIF(fCensoDiario!$B$2:$B$301,C7,fCensoDiario!$K$2:$K$301),1),2) | M7: =ROUND(I7/ROUND(SUMIF(fCensoDiario!$B$2:$B$301,C7,fCensoDiario!$E$2:$E$301)/SUMIF(fCensoDiario!$B$2:$B$301,C7,fCensoDiario!$K$2:$K$301),1)*INDEX(dUnidade!$H:$H,MATCH(C7,dUnidade!$A:$A,0)),0)
A8: DES-0109 | B8: CC-B23 | C8: CC | D8: P24515 | E8: MD06 | F8: 46285.867 | G8: 46287.089 | H8: Resolvido | I8: 1.2 | J8: =ROUND(SUMIF(fCustoDiaria!$A$2:$A$51,C8,fCustoDiaria!$E$2:$E$51),2) | K8: =ROUND(I8*J8,0) | L8: =ROUND(I8/ROUND(SUMIF(fCensoDiario!$B$2:$B$301,C8,fCensoDiario!$E$2:$E$301)/SUMIF(fCensoDiario!$B$2:$B$301,C8,fCensoDiario!$K$2:$K$301),1),2) | M8: =ROUND(I8/ROUND(SUMIF(fCensoDiario!$B$2:$B$301,C8,fCensoDiario!$E$2:$E$301)/SUMIF(fCensoDiario!$B$2:$B$301,C8,fCensoDiario!$K$2:$K$301),1)*INDEX(dUnidade!$H:$H,MATCH(C8,dUnidade!$A:$A,0)),0)
A9: DES-0025 | B9: CM-B53 | C9: CM | D9: P21804 | E9: MD01 | F9: 46286.074 | G9: 46287.269 | H9: Resolvido | I9: 1.2 | J9: =ROUND(SUMIF(fCustoDiaria!$A$2:$A$51,C9,fCustoDiaria!$E$2:$E$51),2) | K9: =ROUND(I9*J9,0) | L9: =ROUND(I9/ROUND(SUMIF(fCensoDiario!$B$2:$B$301,C9,fCensoDiario!$E$2:$E$301)/SUMIF(fCensoDiario!$B$2:$B$301,C9,fCensoDiario!$K$2:$K$301),1),2) | M9: =ROUND(I9/ROUND(SUMIF(fCensoDiario!$B$2:$B$301,C9,fCensoDiario!$E$2:$E$301)/SUMIF(fCensoDiario!$B$2:$B$301,C9,fCensoDiario!$K$2:$K$301),1)*INDEX(dUnidade!$H:$H,MATCH(C9,dUnidade!$A:$A,0)),0)
A10: DES-0078 | B10: CM-B57 | C10: CM | D10: P29288 | E10: MD02 | F10: 46286.226 | G10: 46286.761 | H10: Resolvido | I10: 0.5 | J10: =ROUND(SUMIF(fCustoDiaria!$A$2:$A$51,C10,fCustoDiaria!$E$2:$E$51),2) | K10: =ROUND(I10*J10,0) | L10: =ROUND(I10/ROUND(SUMIF(fCensoDiario!$B$2:$B$301,C10,fCensoDiario!$E$2:$E$301)/SUMIF(fCensoDiario!$B$2:$B$301,C10,fCensoDiario!$K$2:$K$301),1),2) | M10: =ROUND(I10/ROUND(SUMIF(fCensoDiario!$B$2:$B$301,C10,fCensoDiario!$E$2:$E$301)/SUMIF(fCensoDiario!$B$2:$B$301,C10,fCensoDiario!$K$2:$K$301),1)*INDEX(dUnidade!$H:$H,MATCH(C10,dUnidade!$A:$A,0)),0)
A11: DES-0105 | B11: CC-A16 | C11: CC | D11: P26281 | E11: MD02 | F11: 46286.245 | G11: 46288.184 | H11: Resolvido | I11: 1.9 | J11: =ROUND(SUMIF(fCustoDiaria!$A$2:$A$51,C11,fCustoDiaria!$E$2:$E$51),2) | K11: =ROUND(I11*J11,0) | L11: =ROUND(I11/ROUND(SUMIF(fCensoDiario!$B$2:$B$301,C11,fCensoDiario!$E$2:$E$301)/SUMIF(fCensoDiario!$B$2:$B$301,C11,fCensoDiario!$K$2:$K$301),1),2) | M11: =ROUND(I11/ROUND(SUMIF(fCensoDiario!$B$2:$B$301,C11,fCensoDiario!$E$2:$E$301)/SUMIF(fCensoDiario!$B$2:$B$301,C11,fCensoDiario!$K$2:$K$301),1)*INDEX(dUnidade!$H:$H,MATCH(C11,dUnidade!$A:$A,0)),0)
A12: DES-0069 | B12: CM-B38 | C12: CM | D12: P20124 | E12: MD05 | F12: 46286.524 | G12: 46289.821 | H12: Resolvido | I12: 3.3 | J12: =ROUND(SUMIF(fCustoDiaria!$A$2:$A$51,C12,fCustoDiaria!$E$2:$E$51),2) | K12: =ROUND(I12*J12,0) | L12: =ROUND(I12/ROUND(SUMIF(fCensoDiario!$B$2:$B$301,C12,fCensoDiario!$E$2:$E$301)/SUMIF(fCensoDiario!$B$2:$B$301,C12,fCensoDiario!$K$2:$K$301),1),2) | M12: =ROUND(I12/ROUND(SUMIF(fCensoDiario!$B$2:$B$301,C12,fCensoDiario!$E$2:$E$301)/SUMIF(fCensoDiario!$B$2:$B$301,C12,fCensoDiario!$K$2:$K$301),1)*INDEX(dUnidade!$H:$H,MATCH(C12,dUnidade!$A:$A,0)),0)
A13: DES-0156 | B13: INF-A01 | C13: INF | D13: P22137 | E13: MD01 | F13: 46286.644 | G13: 46287.31 | H13: Resolvido | I13: 0.7 | J13: =ROUND(SUMIF(fCustoDiaria!$A$2:$A$51,C13,fCustoDiaria!$E$2:$E$51),2) | K13: =ROUND(I13*J13,0) | L13: =ROUND(I13/ROUND(SUMIF(fCensoDiario!$B$2:$B$301,C13,fCensoDiario!$E$2:$E$301)/SUMIF(fCensoDiario!$B$2:$B$301,C13,fCensoDiario!$K$2:$K$301),1),2) | M13: =ROUND(I13/ROUND(SUMIF(fCensoDiario!$B$2:$B$301,C13,fCensoDiario!$E$2:$E$301)/SUMIF(fCensoDiario!$B$2:$B$301,C13,fCensoDiario!$K$2:$K$301),1)*INDEX(dUnidade!$H:$H,MATCH(C13,dUnidade!$A:$A,0)),0)
... A112: DES-0093 | B112: CC-B21 | C112: CC | D112: P23013 | E112: MD01 | F112: 46306.233 | G112: 46313.88 | H112: Resolvido | I112: 7.6 | J112: =ROUND(SUMIF(fCustoDiaria!$A$2:$A$51,C112,fCustoDiaria!$E$2:$E$51),2) | K112: =ROUND(I112*J112,0) | L112: =ROUND(I112/ROUND(SUMIF(fCensoDiario!$B$2:$B$301,C112,fCensoDiario!$E$2:$E$301)/SUMIF(fCensoDiario!$B$2:$B$301,C112,fCensoDiario!$K$2:$K$301),1),2) | M112: =ROUND(I112/ROUND(SUMIF(fCensoDiario!$B$2:$B$301,C112,fCensoDiario!$E$2:$E$301)/SUMIF(fCensoDiario!$B$2:$B$301,C112,fCensoDiario!$K$2:$K$301),1)*INDEX(dUnidade!$H:$H,MATCH(C112,dUnidade!$A:$A,0)),0)
A113: DES-0010 | B113: ORT-A12 | C113: ORT | D113: P10095 | E113: MD04 | F113: 46307.044 | H113: Em aberto | I113: 7.2 | J113: =ROUND(SUMIF(fCustoDiaria!$A$2:$A$51,C113,fCustoDiaria!$E$2:$E$51),2) | K113: =ROUND(I113*J113,0) | L113: =ROUND(I113/ROUND(SUMIF(fCensoDiario!$B$2:$B$301,C113,fCensoDiario!$E$2:$E$301)/SUMIF(fCensoDiario!$B$2:$B$301,C113,fCensoDiario!$K$2:$K$301),1),2) | M113: =ROUND(I113/ROUND(SUMIF(fCensoDiario!$B$2:$B$301,C113,fCensoDiario!$E$2:$E$301)/SUMIF(fCensoDiario!$B$2:$B$301,C113,fCensoDiario!$K$2:$K$301),1)*INDEX(dUnidade!$H:$H,MATCH(C113,dUnidade!$A:$A,0)),0)
A114: DES-0048 | B114: CM-A07 | C114: CM | D114: P27010 | E114: MD04 | F114: 46307.244 | G114: 46309.264 | H114: Resolvido | I114: 2 | J114: =ROUND(SUMIF(fCustoDiaria!$A$2:$A$51,C114,fCustoDiaria!$E$2:$E$51),2) | K114: =ROUND(I114*J114,0) | L114: =ROUND(I114/ROUND(SUMIF(fCensoDiario!$B$2:$B$301,C114,fCensoDiario!$E$2:$E$301)/SUMIF(fCensoDiario!$B$2:$B$301,C114,fCensoDiario!$K$2:$K$301),1),2) | M114: =ROUND(I114/ROUND(SUMIF(fCensoDiario!$B$2:$B$301,C114,fCensoDiario!$E$2:$E$301)/SUMIF(fCensoDiario!$B$2:$B$301,C114,fCensoDiario!$K$2:$K$301),1)*INDEX(dUnidade!$H:$H,MATCH(C114,dUnidade!$A:$A,0)),0)
A115: DES-0175 | B115: PED-A08 | C115: PED | D115: P27799 | E115: MD02 | F115: 46307.334 | G115: 46308.579 | H115: Resolvido | I115: 1.2 | J115: =ROUND(SUMIF(fCustoDiaria!$A$2:$A$51,C115,fCustoDiaria!$E$2:$E$51),2) | K115: =ROUND(I115*J115,0) | L115: =ROUND(I115/ROUND(SUMIF(fCensoDiario!$B$2:$B$301,C115,fCensoDiario!$E$2:$E$301)/SUMIF(fCensoDiario!$B$2:$B$301,C115,fCensoDiario!$K$2:$K$301),1),2) | M115: =ROUND(I115/ROUND(SUMIF(fCensoDiario!$B$2:$B$301,C115,fCensoDiario!$E$2:$E$301)/SUMIF(fCensoDiario!$B$2:$B$301,C115,fCensoDiario!$K$2:$K$301),1)*INDEX(dUnidade!$H:$H,MATCH(C115,dUnidade!$A:$A,0)),0)
A116: DES-0115 | B116: ORT-A07 | C116: ORT | D116: P25864 | E116: MD03 | F116: 46307.344 | G116: 46309.374 | H116: Resolvido | I116: 2 | J116: =ROUND(SUMIF(fCustoDiaria!$A$2:$A$51,C116,fCustoDiaria!$E$2:$E$51),2) | K116: =ROUND(I116*J116,0) | L116: =ROUND(I116/ROUND(SUMIF(fCensoDiario!$B$2:$B$301,C116,fCensoDiario!$E$2:$E$301)/SUMIF(fCensoDiario!$B$2:$B$301,C116,fCensoDiario!$K$2:$K$301),1),2) | M116: =ROUND(I116/ROUND(SUMIF(fCensoDiario!$B$2:$B$301,C116,fCensoDiario!$E$2:$E$301)/SUMIF(fCensoDiario!$B$2:$B$301,C116,fCensoDiario!$K$2:$K$301),1)*INDEX(dUnidade!$H:$H,MATCH(C116,dUnidade!$A:$A,0)),0)
A117: DES-0113 | B117: ORT-B19 | C117: ORT | D117: P28094 | E117: MD04 | F117: 46307.424 | G117: 46309.939 | H117: Resolvido | I117: 2.5 | J117: =ROUND(SUMIF(fCustoDiaria!$A$2:$A$51,C117,fCustoDiaria!$E$2:$E$51),2) | K117: =ROUND(I117*J117,0) | L117: =ROUND(I117/ROUND(SUMIF(fCensoDiario!$B$2:$B$301,C117,fCensoDiario!$E$2:$E$301)/SUMIF(fCensoDiario!$B$2:$B$301,C117,fCensoDiario!$K$2:$K$301),1),2) | M117: =ROUND(I117/ROUND(SUMIF(fCensoDiario!$B$2:$B$301,C117,fCensoDiario!$E$2:$E$301)/SUMIF(fCensoDiario!$B$2:$B$301,C117,fCensoDiario!$K$2:$K$301),1)*INDEX(dUnidade!$H:$H,MATCH(C117,dUnidade!$A:$A,0)),0)
A118: DES-0174 | B118: PED-A04 | C118: PED | D118: P22526 | E118: MD07 | F118: 46307.675 | G118: 46314.106 | H118: Resolvido | I118: 6.4 | J118: =ROUND(SUMIF(fCustoDiaria!$A$2:$A$51,C118,fCustoDiaria!$E$2:$E$51),2) | K118: =ROUND(I118*J118,0) | L118: =ROUND(I118/ROUND(SUMIF(fCensoDiario!$B$2:$B$301,C118,fCensoDiario!$E$2:$E$301)/SUMIF(fCensoDiario!$B$2:$B$301,C118,fCensoDiario!$K$2:$K$301),1),2) | M118: =ROUND(I118/ROUND(SUMIF(fCensoDiario!$B$2:$B$301,C118,fCensoDiario!$E$2:$E$301)/SUMIF(fCensoDiario!$B$2:$B$301,C118,fCensoDiario!$K$2:$K$301),1)*INDEX(dUnidade!$H:$H,MATCH(C118,dUnidade!$A:$A,0)),0)
A119: DES-0015 | B119: CC-B32 | C119: CC | D119: P10078 | E119: MD05 | F119: 46307.762 | H119: Em aberto | I119: 6.5 | J119: =ROUND(SUMIF(fCustoDiaria!$A$2:$A$51,C119,fCustoDiaria!$E$2:$E$51),2) | K119: =ROUND(I119*J119,0) | L119: =ROUND(I119/ROUND(SUMIF(fCensoDiario!$B$2:$B$301,C119,fCensoDiario!$E$2:$E$301)/SUMIF(fCensoDiario!$B$2:$B$301,C119,fCensoDiario!$K$2:$K$301),1),2) | M119: =ROUND(I119/ROUND(SUMIF(fCensoDiario!$B$2:$B$301,C119,fCensoDiario!$E$2:$E$301)/SUMIF(fCensoDiario!$B$2:$B$301,C119,fCensoDiario!$K$2:$K$301),1)*INDEX(dUnidade!$H:$H,MATCH(C119,dUnidade!$A:$A,0)),0)
A120: DES-0036 | B120: CM-B60 | C120: CM | D120: P25999 | E120: MD02 | F120: 46307.779 | G120: 46308.262 | H120: Resolvido | I120: 0.5 | J120: =ROUND(SUMIF(fCustoDiaria!$A$2:$A$51,C120,fCustoDiaria!$E$2:$E$51),2) | K120: =ROUND(I120*J120,0) | L120: =ROUND(I120/ROUND(SUMIF(fCensoDiario!$B$2:$B$301,C120,fCensoDiario!$E$2:$E$301)/SUMIF(fCensoDiario!$B$2:$B$301,C120,fCensoDiario!$K$2:$K$301),1),2) | M120: =ROUND(I120/ROUND(SUMIF(fCensoDiario!$B$2:$B$301,C120,fCensoDiario!$E$2:$E$301)/SUMIF(fCensoDiario!$B$2:$B$301,C120,fCensoDiario!$K$2:$K$301),1)*INDEX(dUnidade!$H:$H,MATCH(C120,dUnidade!$A:$A,0)),0)
A121: DES-0144 | B121: ONC-A05 | C121: ONC | D121: P22174 | E121: MD03 | F121: 46307.867 | G121: 46309.097 | H121: Resolvido | I121: 1.2 | J121: =ROUND(SUMIF(fCustoDiaria!$A$2:$A$51,C121,fCustoDiaria!$E$2:$E$51),2) | K121: =ROUND(I121*J121,0) | L121: =ROUND(I121/ROUND(SUMIF(fCensoDiario!$B$2:$B$301,C121,fCensoDiario!$E$2:$E$301)/SUMIF(fCensoDiario!$B$2:$B$301,C121,fCensoDiario!$K$2:$K$301),1),2) | M121: =ROUND(I121/ROUND(SUMIF(fCensoDiario!$B$2:$B$301,C121,fCensoDiario!$E$2:$E$301)/SUMIF(fCensoDiario!$B$2:$B$301,C121,fCensoDiario!$K$2:$K$301),1)*INDEX(dUnidade!$H:$H,MATCH(C121,dUnidade!$A:$A,0)),0)
A122: DES-0148 | B122: INF-A02 | C122: INF | D122: P20686 | E122: MD05 | F122: 46307.994 | G122: 46309.124 | H122: Resolvido | I122: 1.1 | J122: =ROUND(SUMIF(fCustoDiaria!$A$2:$A$51,C122,fCustoDiaria!$E$2:$E$51),2) | K122: =ROUND(I122*J122,0) | L122: =ROUND(I122/ROUND(SUMIF(fCensoDiario!$B$2:$B$301,C122,fCensoDiario!$E$2:$E$301)/SUMIF(fCensoDiario!$B$2:$B$301,C122,fCensoDiario!$K$2:$K$301),1),2) | M122: =ROUND(I122/ROUND(SUMIF(fCensoDiario!$B$2:$B$301,C122,fCensoDiario!$E$2:$E$301)/SUMIF(fCensoDiario!$B$2:$B$301,C122,fCensoDiario!$K$2:$K$301),1)*INDEX(dUnidade!$H:$H,MATCH(C122,dUnidade!$A:$A,0)),0)
A123: DES-0001 | B123: CM-A13 | C123: CM | D123: P10012 | E123: MD03 | F123: 46308.246 | H123: Em aberto | I123: 6 | J123: =ROUND(SUMIF(fCustoDiaria!$A$2:$A$51,C123,fCustoDiaria!$E$2:$E$51),2) | K123: =ROUND(I123*J123,0) | L123: =ROUND(I123/ROUND(SUMIF(fCensoDiario!$B$2:$B$301,C123,fCensoDiario!$E$2:$E$301)/SUMIF(fCensoDiario!$B$2:$B$301,C123,fCensoDiario!$K$2:$K$301),1),2) | M123: =ROUND(I123/ROUND(SUMIF(fCensoDiario!$B$2:$B$301,C123,fCensoDiario!$E$2:$E$301)/SUMIF(fCensoDiario!$B$2:$B$301,C123,fCensoDiario!$K$2:$K$301),1)*INDEX(dUnidade!$H:$H,MATCH(C123,dUnidade!$A:$A,0)),0)
A124: DES-0140 | B124: ONC-B09 | C124: ONC | D124: P26397 | E124: MD01 | F124: 46308.289 | G124: 46314.169 | H124: Resolvido | I124: 5.9 | J124: =ROUND(SUMIF(fCustoDiaria!$A$2:$A$51,C124,fCustoDiaria!$E$2:$E$51),2) | K124: =ROUND(I124*J124,0) | L124: =ROUND(I124/ROUND(SUMIF(fCensoDiario!$B$2:$B$301,C124,fCensoDiario!$E$2:$E$301)/SUMIF(fCensoDiario!$B$2:$B$301,C124,fCensoDiario!$K$2:$K$301),1),2) | M124: =ROUND(I124/ROUND(SUMIF(fCensoDiario!$B$2:$B$301,C124,fCensoDiario!$E$2:$E$301)/SUMIF(fCensoDiario!$B$2:$B$301,C124,fCensoDiario!$K$2:$K$301),1)*INDEX(dUnidade!$H:$H,MATCH(C124,dUnidade!$A:$A,0)),0)
A125: DES-0072 | B125: CM-A08 | C125: CM | D125: P28931 | E125: MD02 | F125: 46308.705 | G125: 46309.637 | H125: Resolvido | I125: 0.9 | J125: =ROUND(SUMIF(fCustoDiaria!$A$2:$A$51,C125,fCustoDiaria!$E$2:$E$51),2) | K125: =ROUND(I125*J125,0) | L125: =ROUND(I125/ROUND(SUMIF(fCensoDiario!$B$2:$B$301,C125,fCensoDiario!$E$2:$E$301)/SUMIF(fCensoDiario!$B$2:$B$301,C125,fCensoDiario!$K$2:$K$301),1),2) | M125: =ROUND(I125/ROUND(SUMIF(fCensoDiario!$B$2:$B$301,C125,fCensoDiario!$E$2:$E$301)/SUMIF(fCensoDiario!$B$2:$B$301,C125,fCensoDiario!$K$2:$K$301),1)*INDEX(dUnidade!$H:$H,MATCH(C125,dUnidade!$A:$A,0)),0)
A126: DES-0040 | B126: CM-B58 | C126: CM | D126: P27010 | E126: MD08 | F126: 46308.792 | G126: 46311.854 | H126: Resolvido | I126: 3.1 | J126: =ROUND(SUMIF(fCustoDiaria!$A$2:$A$51,C126,fCustoDiaria!$E$2:$E$51),2) | K126: =ROUND(I126*J126,0) | L126: =ROUND(I126/ROUND(SUMIF(fCensoDiario!$B$2:$B$301,C126,fCensoDiario!$E$2:$E$301)/SUMIF(fCensoDiario!$B$2:$B$301,C126,fCensoDiario!$K$2:$K$301),1),2) | M126: =ROUND(I126/ROUND(SUMIF(fCensoDiario!$B$2:$B$301,C126,fCensoDiario!$E$2:$E$301)/SUMIF(fCensoDiario!$B$2:$B$301,C126,fCensoDiario!$K$2:$K$301),1)*INDEX(dUnidade!$H:$H,MATCH(C126,dUnidade!$A:$A,0)),0)
A127: DES-0060 | B127: CM-A26 | C127: CM | D127: P21234 | E127: MD01 | F127: 46308.796 | G127: 46314.085 | H127: Resolvido | I127: 5.3 | J127: =ROUND(SUMIF(fCustoDiaria!$A$2:$A$51,C127,fCustoDiaria!$E$2:$E$51),2) | K127: =ROUND(I127*J127,0) | L127: =ROUND(I127/ROUND(SUMIF(fCensoDiario!$B$2:$B$301,C127,fCensoDiario!$E$2:$E$301)/SUMIF(fCensoDiario!$B$2:$B$301,C127,fCensoDiario!$K$2:$K$301),1),2) | M127: =ROUND(I127/ROUND(SUMIF(fCensoDiario!$B$2:$B$301,C127,fCensoDiario!$E$2:$E$301)/SUMIF(fCensoDiario!$B$2:$B$301,C127,fCensoDiario!$K$2:$K$301),1)*INDEX(dUnidade!$H:$H,MATCH(C127,dUnidade!$A:$A,0)),0)
A128: DES-0012 | B128: ORT-B14 | C128: ORT | D128: P10097 | E128: MD03 | F128: 46309.011 | H128: Em aberto | I128: 5.3 | J128: =ROUND(SUMIF(fCustoDiaria!$A$2:$A$51,C128,fCustoDiaria!$E$2:$E$51),2) | K128: =ROUND(I128*J128,0) | L128: =ROUND(I128/ROUND(SUMIF(fCensoDiario!$B$2:$B$301,C128,fCensoDiario!$E$2:$E$301)/SUMIF(fCensoDiario!$B$2:$B$301,C128,fCensoDiario!$K$2:$K$301),1),2) | M128: =ROUND(I128/ROUND(SUMIF(fCensoDiario!$B$2:$B$301,C128,fCensoDiario!$E$2:$E$301)/SUMIF(fCensoDiario!$B$2:$B$301,C128,fCensoDiario!$K$2:$K$301),1)*INDEX(dUnidade!$H:$H,MATCH(C128,dUnidade!$A:$A,0)),0)
A129: DES-0090 | B129: CC-B35 | C129: CC | D129: P20367 | E129: MD01 | F129: 46309.089 | G129: 46313.963 | H129: Resolvido | I129: 4.9 | J129: =ROUND(SUMIF(fCustoDiaria!$A$2:$A$51,C129,fCustoDiaria!$E$2:$E$51),2) | K129: =ROUND(I129*J129,0) | L129: =ROUND(I129/ROUND(SUMIF(fCensoDiario!$B$2:$B$301,C129,fCensoDiario!$E$2:$E$301)/SUMIF(fCensoDiario!$B$2:$B$301,C129,fCensoDiario!$K$2:$K$301),1),2) | M129: =ROUND(I129/ROUND(SUMIF(fCensoDiario!$B$2:$B$301,C129,fCensoDiario!$E$2:$E$301)/SUMIF(fCensoDiario!$B$2:$B$301,C129,fCensoDiario!$K$2:$K$301),1)*INDEX(dUnidade!$H:$H,MATCH(C129,dUnidade!$A:$A,0)),0)
A130: DES-0051 | B130: CM-A04 | C130: CM | D130: P23846 | E130: MD03 | F130: 46309.123 | G130: 46310.237 | H130: Resolvido | I130: 1.1 | J130: =ROUND(SUMIF(fCustoDiaria!$A$2:$A$51,C130,fCustoDiaria!$E$2:$E$51),2) | K130: =ROUND(I130*J130,0) | L130: =ROUND(I130/ROUND(SUMIF(fCensoDiario!$B$2:$B$301,C130,fCensoDiario!$E$2:$E$301)/SUMIF(fCensoDiario!$B$2:$B$301,C130,fCensoDiario!$K$2:$K$301),1),2) | M130: =ROUND(I130/ROUND(SUMIF(fCensoDiario!$B$2:$B$301,C130,fCensoDiario!$E$2:$E$301)/SUMIF(fCensoDiario!$B$2:$B$301,C130,fCensoDiario!$K$2:$K$301),1)*INDEX(dUnidade!$H:$H,MATCH(C130,dUnidade!$A:$A,0)),0)
A131: DES-0097 | B131: CC-B22 | C131: CC | D131: P22013 | E131: MD02 | F131: 46309.29 | G131: 46310.344 | H131: Resolvido | I131: 1.1 | J131: =ROUND(SUMIF(fCustoDiaria!$A$2:$A$51,C131,fCustoDiaria!$E$2:$E$51),2) | K131: =ROUND(I131*J131,0) | L131: =ROUND(I131/ROUND(SUMIF(fCensoDiario!$B$2:$B$301,C131,fCensoDiario!$E$2:$E$301)/SUMIF(fCensoDiario!$B$2:$B$301,C131,fCensoDiario!$K$2:$K$301),1),2) | M131: =ROUND(I131/ROUND(SUMIF(fCensoDiario!$B$2:$B$301,C131,fCensoDiario!$E$2:$E$301)/SUMIF(fCensoDiario!$B$2:$B$301,C131,fCensoDiario!$K$2:$K$301),1)*INDEX(dUnidade!$H:$H,MATCH(C131,dUnidade!$A:$A,0)),0)
A132: DES-0134 | B132: ONC-A01 | C132: ONC | D132: P22561 | E132: MD06 | F132: 46309.29 | G132: 46310.452 | H132: Resolvido | I132: 1.2 | J132: =ROUND(SUMIF(fCustoDiaria!$A$2:$A$51,C132,fCustoDiaria!$E$2:$E$51),2) | K132: =ROUND(I132*J132,0) | L132: =ROUND(I132/ROUND(SUMIF(fCensoDiario!$B$2:$B$301,C132,fCensoDiario!$E$2:$E$301)/SUMIF(fCensoDiario!$B$2:$B$301,C132,fCensoDiario!$K$2:$K$301),1),2) | M132: =ROUND(I132/ROUND(SUMIF(fCensoDiario!$B$2:$B$301,C132,fCensoDiario!$E$2:$E$301)/SUMIF(fCensoDiario!$B$2:$B$301,C132,fCensoDiario!$K$2:$K$301),1)*INDEX(dUnidade!$H:$H,MATCH(C132,dUnidade!$A:$A,0)),0)
A133: DES-0163 | B133: UCI-A01 | C133: UCI | D133: P28945 | E133: MD02 | F133: 46309.42 | G133: 46310.545 | H133: Resolvido | I133: 1.1 | J133: =ROUND(SUMIF(fCustoDiaria!$A$2:$A$51,C133,fCustoDiaria!$E$2:$E$51),2) | K133: =ROUND(I133*J133,0) | L133: =ROUND(I133/ROUND(SUMIF(fCensoDiario!$B$2:$B$301,C133,fCensoDiario!$E$2:$E$301)/SUMIF(fCensoDiario!$B$2:$B$301,C133,fCensoDiario!$K$2:$K$301),1),2) | M133: =ROUND(I133/ROUND(SUMIF(fCensoDiario!$B$2:$B$301,C133,fCensoDiario!$E$2:$E$301)/SUMIF(fCensoDiario!$B$2:$B$301,C133,fCensoDiario!$K$2:$K$301),1)*INDEX(dUnidade!$H:$H,MATCH(C133,dUnidade!$A:$A,0)),0)
A134: DES-0085 | B134: CM-A18 | C134: CM | D134: P28749 | E134: MD01 | F134: 46309.489 | G134: 46313.938 | H134: Resolvido | I134: 4.4 | J134: =ROUND(SUMIF(fCustoDiaria!$A$2:$A$51,C134,fCustoDiaria!$E$2:$E$51),2) | K134: =ROUND(I134*J134,0) | L134: =ROUND(I134/ROUND(SUMIF(fCensoDiario!$B$2:$B$301,C134,fCensoDiario!$E$2:$E$301)/SUMIF(fCensoDiario!$B$2:$B$301,C134,fCensoDiario!$K$2:$K$301),1),2) | M134: =ROUND(I134/ROUND(SUMIF(fCensoDiario!$B$2:$B$301,C134,fCensoDiario!$E$2:$E$301)/SUMIF(fCensoDiario!$B$2:$B$301,C134,fCensoDiario!$K$2:$K$301),1)*INDEX(dUnidade!$H:$H,MATCH(C134,dUnidade!$A:$A,0)),0)
A135: DES-0151 | B135: INF-B07 | C135: INF | D135: P24743 | E135: MD02 | F135: 46309.501 | G135: 46309.833 | H135: Resolvido | I135: 0.3 | J135: =ROUND(SUMIF(fCustoDiaria!$A$2:$A$51,C135,fCustoDiaria!$E$2:$E$51),2) | K135: =ROUND(I135*J135,0) | L135: =ROUND(I135/ROUND(SUMIF(fCensoDiario!$B$2:$B$301,C135,fCensoDiario!$E$2:$E$301)/SUMIF(fCensoDiario!$B$2:$B$301,C135,fCensoDiario!$K$2:$K$301),1),2) | M135: =ROUND(I135/ROUND(SUMIF(fCensoDiario!$B$2:$B$301,C135,fCensoDiario!$E$2:$E$301)/SUMIF(fCensoDiario!$B$2:$B$301,C135,fCensoDiario!$K$2:$K$301),1)*INDEX(dUnidade!$H:$H,MATCH(C135,dUnidade!$A:$A,0)),0)
A136: DES-0137 | B136: ONC-A04 | C136: ONC | D136: P20993 | E136: MD02 | F136: 46309.531 | G136: 46311.588 | H136: Resolvido | I136: 2.1 | J136: =ROUND(SUMIF(fCustoDiaria!$A$2:$A$51,C136,fCustoDiaria!$E$2:$E$51),2) | K136: =ROUND(I136*J136,0) | L136: =ROUND(I136/ROUND(SUMIF(fCensoDiario!$B$2:$B$301,C136,fCensoDiario!$E$2:$E$301)/SUMIF(fCensoDiario!$B$2:$B$301,C136,fCensoDiario!$K$2:$K$301),1),2) | M136: =ROUND(I136/ROUND(SUMIF(fCensoDiario!$B$2:$B$301,C136,fCensoDiario!$E$2:$E$301)/SUMIF(fCensoDiario!$B$2:$B$301,C136,fCensoDiario!$K$2:$K$301),1)*INDEX(dUnidade!$H:$H,MATCH(C136,dUnidade!$A:$A,0)),0)
A137: DES-0049 | B137: CM-A20 | C137: CM | D137: P27442 | E137: MD04 | F137: 46309.716 | G137: 46312.074 | H137: Resolvido | I137: 2.4 | J137: =ROUND(SUMIF(fCustoDiaria!$A$2:$A$51,C137,fCustoDiaria!$E$2:$E$51),2) | K137: =ROUND(I137*J137,0) | L137: =ROUND(I137/ROUND(SUMIF(fCensoDiario!$B$2:$B$301,C137,fCensoDiario!$E$2:$E$301)/SUMIF(fCensoDiario!$B$2:$B$301,C137,fCensoDiario!$K$2:$K$301),1),2) | M137: =ROUND(I137/ROUND(SUMIF(fCensoDiario!$B$2:$B$301,C137,fCensoDiario!$E$2:$E$301)/SUMIF(fCensoDiario!$B$2:$B$301,C137,fCensoDiario!$K$2:$K$301),1)*INDEX(dUnidade!$H:$H,MATCH(C137,dUnidade!$A:$A,0)),0)
A138: DES-0018 | B138: INF-B06 | C138: INF | D138: P10185 | E138: MD08 | F138: 46309.865 | H138: Em aberto | I138: 4.4 | J138: =ROUND(SUMIF(fCustoDiaria!$A$2:$A$51,C138,fCustoDiaria!$E$2:$E$51),2) | K138: =ROUND(I138*J138,0) | L138: =ROUND(I138/ROUND(SUMIF(fCensoDiario!$B$2:$B$301,C138,fCensoDiario!$E$2:$E$301)/SUMIF(fCensoDiario!$B$2:$B$301,C138,fCensoDiario!$K$2:$K$301),1),2) | M138: =ROUND(I138/ROUND(SUMIF(fCensoDiario!$B$2:$B$301,C138,fCensoDiario!$E$2:$E$301)/SUMIF(fCensoDiario!$B$2:$B$301,C138,fCensoDiario!$K$2:$K$301),1)*INDEX(dUnidade!$H:$H,MATCH(C138,dUnidade!$A:$A,0)),0)
A139: DES-0077 | B139: CM-B55 | C139: CM | D139: P28377 | E139: MD01 | F139: 46310.123 | G139: 46313.96 | H139: Resolvido | I139: 3.8 | J139: =ROUND(SUMIF(fCustoDiaria!$A$2:$A$51,C139,fCustoDiaria!$E$2:$E$51),2) | K139: =ROUND(I139*J139,0) | L139: =ROUND(I139/ROUND(SUMIF(fCensoDiario!$B$2:$B$301,C139,fCensoDiario!$E$2:$E$301)/SUMIF(fCensoDiario!$B$2:$B$301,C139,fCensoDiario!$K$2:$K$301),1),2) | M139: =ROUND(I139/ROUND(SUMIF(fCensoDiario!$B$2:$B$301,C139,fCensoDiario!$E$2:$E$301)/SUMIF(fCensoDiario!$B$2:$B$301,C139,fCensoDiario!$K$2:$K$301),1)*INDEX(dUnidade!$H:$H,MATCH(C139,dUnidade!$A:$A,0)),0)
A140: DES-0006 | B140: CM-B46 | C140: CM | D140: P10040 | E140: MD06 | F140: 46310.214 | H140: Em aberto | I140: 4.1 | J140: =ROUND(SUMIF(fCustoDiaria!$A$2:$A$51,C140,fCustoDiaria!$E$2:$E$51),2) | K140: =ROUND(I140*J140,0) | L140: =ROUND(I140/ROUND(SUMIF(fCensoDiario!$B$2:$B$301,C140,fCensoDiario!$E$2:$E$301)/SUMIF(fCensoDiario!$B$2:$B$301,C140,fCensoDiario!$K$2:$K$301),1),2) | M140: =ROUND(I140/ROUND(SUMIF(fCensoDiario!$B$2:$B$301,C140,fCensoDiario!$E$2:$E$301)/SUMIF(fCensoDiario!$B$2:$B$301,C140,fCensoDiario!$K$2:$K$301),1)*INDEX(dUnidade!$H:$H,MATCH(C140,dUnidade!$A:$A,0)),0)
A141: DES-0011 | B141: ORT-A10 | C141: ORT | D141: P10093 | E141: MD04 | F141: 46310.292 | H141: Em aberto | I141: 4 | J141: =ROUND(SUMIF(fCustoDiaria!$A$2:$A$51,C141,fCustoDiaria!$E$2:$E$51),2) | K141: =ROUND(I141*J141,0) | L141: =ROUND(I141/ROUND(SUMIF(fCensoDiario!$B$2:$B$301,C141,fCensoDiario!$E$2:$E$301)/SUMIF(fCensoDiario!$B$2:$B$301,C141,fCensoDiario!$K$2:$K$301),1),2) | M141: =ROUND(I141/ROUND(SUMIF(fCensoDiario!$B$2:$B$301,C141,fCensoDiario!$E$2:$E$301)/SUMIF(fCensoDiario!$B$2:$B$301,C141,fCensoDiario!$K$2:$K$301),1)*INDEX(dUnidade!$H:$H,MATCH(C141,dUnidade!$A:$A,0)),0)
A142: DES-0170 | B142: PED-B17 | C142: PED | D142: P25617 | E142: MD02 | F142: 46310.422 | G142: 46310.935 | H142: Resolvido | I142: 0.5 | J142: =ROUND(SUMIF(fCustoDiaria!$A$2:$A$51,C142,fCustoDiaria!$E$2:$E$51),2) | K142: =ROUND(I142*J142,0) | L142: =ROUND(I142/ROUND(SUMIF(fCensoDiario!$B$2:$B$301,C142,fCensoDiario!$E$2:$E$301)/SUMIF(fCensoDiario!$B$2:$B$301,C142,fCensoDiario!$K$2:$K$301),1),2) | M142: =ROUND(I142/ROUND(SUMIF(fCensoDiario!$B$2:$B$301,C142,fCensoDiario!$E$2:$E$301)/SUMIF(fCensoDiario!$B$2:$B$301,C142,fCensoDiario!$K$2:$K$301),1)*INDEX(dUnidade!$H:$H,MATCH(C142,dUnidade!$A:$A,0)),0)
A143: DES-0061 | B143: CM-B50 | C143: CM | D143: P29482 | E143: MD05 | F143: 46310.473 | G143: 46314.153 | H143: Resolvido | I143: 3.7 | J143: =ROUND(SUMIF(fCustoDiaria!$A$2:$A$51,C143,fCustoDiaria!$E$2:$E$51),2) | K143: =ROUND(I143*J143,0) | L143: =ROUND(I143/ROUND(SUMIF(fCensoDiario!$B$2:$B$301,C143,fCensoDiario!$E$2:$E$301)/SUMIF(fCensoDiario!$B$2:$B$301,C143,fCensoDiario!$K$2:$K$301),1),2) | M143: =ROUND(I143/ROUND(SUMIF(fCensoDiario!$B$2:$B$301,C143,fCensoDiario!$E$2:$E$301)/SUMIF(fCensoDiario!$B$2:$B$301,C143,fCensoDiario!$K$2:$K$301),1)*INDEX(dUnidade!$H:$H,MATCH(C143,dUnidade!$A:$A,0)),0)
A144: DES-0139 | B144: ONC-A03 | C144: ONC | D144: P24253 | E144: MD07 | F144: 46310.913 | G144: 46314.068 | H144: Resolvido | I144: 3.2 | J144: =ROUND(SUMIF(fCustoDiaria!$A$2:$A$51,C144,fCustoDiaria!$E$2:$E$51),2) | K144: =ROUND(I144*J144,0) | L144: =ROUND(I144/ROUND(SUMIF(fCensoDiario!$B$2:$B$301,C144,fCensoDiario!$E$2:$E$301)/SUMIF(fCensoDiario!$B$2:$B$301,C144,fCensoDiario!$K$2:$K$301),1),2) | M144: =ROUND(I144/ROUND(SUMIF(fCensoDiario!$B$2:$B$301,C144,fCensoDiario!$E$2:$E$301)/SUMIF(fCensoDiario!$B$2:$B$301,C144,fCensoDiario!$K$2:$K$301),1)*INDEX(dUnidade!$H:$H,MATCH(C144,dUnidade!$A:$A,0)),0)
A145: DES-0068 | B145: CM-B56 | C145: CM | D145: P25366 | E145: MD08 | F145: 46311.131 | G145: 46312.222 | H145: Resolvido | I145: 1.1 | J145: =ROUND(SUMIF(fCustoDiaria!$A$2:$A$51,C145,fCustoDiaria!$E$2:$E$51),2) | K145: =ROUND(I145*J145,0) | L145: =ROUND(I145/ROUND(SUMIF(fCensoDiario!$B$2:$B$301,C145,fCensoDiario!$E$2:$E$301)/SUMIF(fCensoDiario!$B$2:$B$301,C145,fCensoDiario!$K$2:$K$301),1),2) | M145: =ROUND(I145/ROUND(SUMIF(fCensoDiario!$B$2:$B$301,C145,fCensoDiario!$E$2:$E$301)/SUMIF(fCensoDiario!$B$2:$B$301,C145,fCensoDiario!$K$2:$K$301),1)*INDEX(dUnidade!$H:$H,MATCH(C145,dUnidade!$A:$A,0)),0)
A146: DES-0079 | B146: CM-A02 | C146: CM | D146: P25374 | E146: MD02 | F146: 46311.208 | G146: 46312.388 | H146: Resolvido | I146: 1.2 | J146: =ROUND(SUMIF(fCustoDiaria!$A$2:$A$51,C146,fCustoDiaria!$E$2:$E$51),2) | K146: =ROUND(I146*J146,0) | L146: =ROUND(I146/ROUND(SUMIF(fCensoDiario!$B$2:$B$301,C146,fCensoDiario!$E$2:$E$301)/SUMIF(fCensoDiario!$B$2:$B$301,C146,fCensoDiario!$K$2:$K$301),1),2) | M146: =ROUND(I146/ROUND(SUMIF(fCensoDiario!$B$2:$B$301,C146,fCensoDiario!$E$2:$E$301)/SUMIF(fCensoDiario!$B$2:$B$301,C146,fCensoDiario!$K$2:$K$301),1)*INDEX(dUnidade!$H:$H,MATCH(C146,dUnidade!$A:$A,0)),0)
A147: DES-0084 | B147: CM-A25 | C147: CM | D147: P28221 | E147: MD02 | F147: 46311.213 | G147: 46313.966 | H147: Resolvido | I147: 2.8 | J147: =ROUND(SUMIF(fCustoDiaria!$A$2:$A$51,C147,fCustoDiaria!$E$2:$E$51),2) | K147: =ROUND(I147*J147,0) | L147: =ROUND(I147/ROUND(SUMIF(fCensoDiario!$B$2:$B$301,C147,fCensoDiario!$E$2:$E$301)/SUMIF(fCensoDiario!$B$2:$B$301,C147,fCensoDiario!$K$2:$K$301),1),2) | M147: =ROUND(I147/ROUND(SUMIF(fCensoDiario!$B$2:$B$301,C147,fCensoDiario!$E$2:$E$301)/SUMIF(fCensoDiario!$B$2:$B$301,C147,fCensoDiario!$K$2:$K$301),1)*INDEX(dUnidade!$H:$H,MATCH(C147,dUnidade!$A:$A,0)),0)
A148: DES-0014 | B148: CC-A14 | C148: CC | D148: P10063 | E148: MD04 | F148: 46311.216 | H148: Em aberto | I148: 3.1 | J148: =ROUND(SUMIF(fCustoDiaria!$A$2:$A$51,C148,fCustoDiaria!$E$2:$E$51),2) | K148: =ROUND(I148*J148,0) | L148: =ROUND(I148/ROUND(SUMIF(fCensoDiario!$B$2:$B$301,C148,fCensoDiario!$E$2:$E$301)/SUMIF(fCensoDiario!$B$2:$B$301,C148,fCensoDiario!$K$2:$K$301),1),2) | M148: =ROUND(I148/ROUND(SUMIF(fCensoDiario!$B$2:$B$301,C148,fCensoDiario!$E$2:$E$301)/SUMIF(fCensoDiario!$B$2:$B$301,C148,fCensoDiario!$K$2:$K$301),1)*INDEX(dUnidade!$H:$H,MATCH(C148,dUnidade!$A:$A,0)),0)
A149: DES-0005 | B149: CM-A06 | C149: CM | D149: P10005 | E149: MD04 | F149: 46311.292 | H149: Em aberto | I149: 3 | J149: =ROUND(SUMIF(fCustoDiaria!$A$2:$A$51,C149,fCustoDiaria!$E$2:$E$51),2) | K149: =ROUND(I149*J149,0) | L149: =ROUND(I149/ROUND(SUMIF(fCensoDiario!$B$2:$B$301,C149,fCensoDiario!$E$2:$E$301)/SUMIF(fCensoDiario!$B$2:$B$301,C149,fCensoDiario!$K$2:$K$301),1),2) | M149: =ROUND(I149/ROUND(SUMIF(fCensoDiario!$B$2:$B$301,C149,fCensoDiario!$E$2:$E$301)/SUMIF(fCensoDiario!$B$2:$B$301,C149,fCensoDiario!$K$2:$K$301),1)*INDEX(dUnidade!$H:$H,MATCH(C149,dUnidade!$A:$A,0)),0)
A150: DES-0009 | B150: CM-A11 | C150: CM | D150: P10010 | E150: MD05 | F150: 46311.292 | H150: Em aberto | I150: 3 | J150: =ROUND(SUMIF(fCustoDiaria!$A$2:$A$51,C150,fCustoDiaria!$E$2:$E$51),2) | K150: =ROUND(I150*J150,0) | L150: =ROUND(I150/ROUND(SUMIF(fCensoDiario!$B$2:$B$301,C150,fCensoDiario!$E$2:$E$301)/SUMIF(fCensoDiario!$B$2:$B$301,C150,fCensoDiario!$K$2:$K$301),1),2) | M150: =ROUND(I150/ROUND(SUMIF(fCensoDiario!$B$2:$B$301,C150,fCensoDiario!$E$2:$E$301)/SUMIF(fCensoDiario!$B$2:$B$301,C150,fCensoDiario!$K$2:$K$301),1)*INDEX(dUnidade!$H:$H,MATCH(C150,dUnidade!$A:$A,0)),0)
A151: DES-0038 | B151: CM-B52 | C151: CM | D151: P24832 | E151: MD08 | F151: 46311.294 | G151: 46311.944 | H151: Resolvido | I151: 0.6 | J151: =ROUND(SUMIF(fCustoDiaria!$A$2:$A$51,C151,fCustoDiaria!$E$2:$E$51),2) | K151: =ROUND(I151*J151,0) | L151: =ROUND(I151/ROUND(SUMIF(fCensoDiario!$B$2:$B$301,C151,fCensoDiario!$E$2:$E$301)/SUMIF(fCensoDiario!$B$2:$B$301,C151,fCensoDiario!$K$2:$K$301),1),2) | M151: =ROUND(I151/ROUND(SUMIF(fCensoDiario!$B$2:$B$301,C151,fCensoDiario!$E$2:$E$301)/SUMIF(fCensoDiario!$B$2:$B$301,C151,fCensoDiario!$K$2:$K$301),1)*INDEX(dUnidade!$H:$H,MATCH(C151,dUnidade!$A:$A,0)),0)
A152: DES-0024 | B152: CM-A09 | C152: CM | D152: P23518 | E152: MD06 | F152: 46311.311 | G152: 46312.129 | H152: Resolvido | I152: 0.8 | J152: =ROUND(SUMIF(fCustoDiaria!$A$2:$A$51,C152,fCustoDiaria!$E$2:$E$51),2) | K152: =ROUND(I152*J152,0) | L152: =ROUND(I152/ROUND(SUMIF(fCensoDiario!$B$2:$B$301,C152,fCensoDiario!$E$2:$E$301)/SUMIF(fCensoDiario!$B$2:$B$301,C152,fCensoDiario!$K$2:$K$301),1),2) | M152: =ROUND(I152/ROUND(SUMIF(fCensoDiario!$B$2:$B$301,C152,fCensoDiario!$E$2:$E$301)/SUMIF(fCensoDiario!$B$2:$B$301,C152,fCensoDiario!$K$2:$K$301),1)*INDEX(dUnidade!$H:$H,MATCH(C152,dUnidade!$A:$A,0)),0)
A153: DES-0086 | B153: CM-B39 | C153: CM | D153: P25925 | E153: MD05 | F153: 46311.39 | G153: 46314.155 | H153: Resolvido | I153: 2.8 | J153: =ROUND(SUMIF(fCustoDiaria!$A$2:$A$51,C153,fCustoDiaria!$E$2:$E$51),2) | K153: =ROUND(I153*J153,0) | L153: =ROUND(I153/ROUND(SUMIF(fCensoDiario!$B$2:$B$301,C153,fCensoDiario!$E$2:$E$301)/SUMIF(fCensoDiario!$B$2:$B$301,C153,fCensoDiario!$K$2:$K$301),1),2) | M153: =ROUND(I153/ROUND(SUMIF(fCensoDiario!$B$2:$B$301,C153,fCensoDiario!$E$2:$E$301)/SUMIF(fCensoDiario!$B$2:$B$301,C153,fCensoDiario!$K$2:$K$301),1)*INDEX(dUnidade!$H:$H,MATCH(C153,dUnidade!$A:$A,0)),0)
A154: DES-0053 | B154: CM-B39 | C154: CM | D154: P27151 | E154: MD04 | F154: 46311.44 | G154: 46314.224 | H154: Resolvido | I154: 2.8 | J154: =ROUND(SUMIF(fCustoDiaria!$A$2:$A$51,C154,fCustoDiaria!$E$2:$E$51),2) | K154: =ROUND(I154*J154,0) | L154: =ROUND(I154/ROUND(SUMIF(fCensoDiario!$B$2:$B$301,C154,fCensoDiario!$E$2:$E$301)/SUMIF(fCensoDiario!$B$2:$B$301,C154,fCensoDiario!$K$2:$K$301),1),2) | M154: =ROUND(I154/ROUND(SUMIF(fCensoDiario!$B$2:$B$301,C154,fCensoDiario!$E$2:$E$301)/SUMIF(fCensoDiario!$B$2:$B$301,C154,fCensoDiario!$K$2:$K$301),1)*INDEX(dUnidade!$H:$H,MATCH(C154,dUnidade!$A:$A,0)),0)
A155: DES-0160 | B155: UCI-B07 | C155: UCI | D155: P29154 | E155: MD04 | F155: 46311.618 | G155: 46314.208 | H155: Resolvido | I155: 2.6 | J155: =ROUND(SUMIF(fCustoDiaria!$A$2:$A$51,C155,fCustoDiaria!$E$2:$E$51),2) | K155: =ROUND(I155*J155,0) | L155: =ROUND(I155/ROUND(SUMIF(fCensoDiario!$B$2:$B$301,C155,fCensoDiario!$E$2:$E$301)/SUMIF(fCensoDiario!$B$2:$B$301,C155,fCensoDiario!$K$2:$K$301),1),2) | M155: =ROUND(I155/ROUND(SUMIF(fCensoDiario!$B$2:$B$301,C155,fCensoDiario!$E$2:$E$301)/SUMIF(fCensoDiario!$B$2:$B$301,C155,fCensoDiario!$K$2:$K$301),1)*INDEX(dUnidade!$H:$H,MATCH(C155,dUnidade!$A:$A,0)),0)
A156: DES-0028 | B156: CM-B57 | C156: CM | D156: P23774 | E156: MD05 | F156: 46311.701 | G156: 46312.616 | H156: Resolvido | I156: 0.9 | J156: =ROUND(SUMIF(fCustoDiaria!$A$2:$A$51,C156,fCustoDiaria!$E$2:$E$51),2) | K156: =ROUND(I156*J156,0) | L156: =ROUND(I156/ROUND(SUMIF(fCensoDiario!$B$2:$B$301,C156,fCensoDiario!$E$2:$E$301)/SUMIF(fCensoDiario!$B$2:$B$301,C156,fCensoDiario!$K$2:$K$301),1),2) | M156: =ROUND(I156/ROUND(SUMIF(fCensoDiario!$B$2:$B$301,C156,fCensoDiario!$E$2:$E$301)/SUMIF(fCensoDiario!$B$2:$B$301,C156,fCensoDiario!$K$2:$K$301),1)*INDEX(dUnidade!$H:$H,MATCH(C156,dUnidade!$A:$A,0)),0)
A157: DES-0178 | B157: UTI-B14 | C157: UTI | D157: P27188 | E157: MD08 | F157: 46311.733 | G157: 46314.181 | H157: Resolvido | I157: 2.4 | J157: =ROUND(SUMIF(fCustoDiaria!$A$2:$A$51,C157,fCustoDiaria!$E$2:$E$51),2) | K157: =ROUND(I157*J157,0) | L157: =ROUND(I157/ROUND(SUMIF(fCensoDiario!$B$2:$B$301,C157,fCensoDiario!$E$2:$E$301)/SUMIF(fCensoDiario!$B$2:$B$301,C157,fCensoDiario!$K$2:$K$301),1),2) | M157: =ROUND(I157/ROUND(SUMIF(fCensoDiario!$B$2:$B$301,C157,fCensoDiario!$E$2:$E$301)/SUMIF(fCensoDiario!$B$2:$B$301,C157,fCensoDiario!$K$2:$K$301),1)*INDEX(dUnidade!$H:$H,MATCH(C157,dUnidade!$A:$A,0)),0)
A158: DES-0064 | B158: CM-A14 | C158: CM | D158: P26965 | E158: MD04 | F158: 46311.751 | G158: 46313.949 | H158: Resolvido | I158: 2.2 | J158: =ROUND(SUMIF(fCustoDiaria!$A$2:$A$51,C158,fCustoDiaria!$E$2:$E$51),2) | K158: =ROUND(I158*J158,0) | L158: =ROUND(I158/ROUND(SUMIF(fCensoDiario!$B$2:$B$301,C158,fCensoDiario!$E$2:$E$301)/SUMIF(fCensoDiario!$B$2:$B$301,C158,fCensoDiario!$K$2:$K$301),1),2) | M158: =ROUND(I158/ROUND(SUMIF(fCensoDiario!$B$2:$B$301,C158,fCensoDiario!$E$2:$E$301)/SUMIF(fCensoDiario!$B$2:$B$301,C158,fCensoDiario!$K$2:$K$301),1)*INDEX(dUnidade!$H:$H,MATCH(C158,dUnidade!$A:$A,0)),0)
A159: DES-0091 | B159: CC-A20 | C159: CC | D159: P23713 | E159: MD04 | F159: 46311.787 | G159: 46313.831 | H159: Resolvido | I159: 2 | J159: =ROUND(SUMIF(fCustoDiaria!$A$2:$A$51,C159,fCustoDiaria!$E$2:$E$51),2) | K159: =ROUND(I159*J159,0) | L159: =ROUND(I159/ROUND(SUMIF(fCensoDiario!$B$2:$B$301,C159,fCensoDiario!$E$2:$E$301)/SUMIF(fCensoDiario!$B$2:$B$301,C159,fCensoDiario!$K$2:$K$301),1),2) | M159: =ROUND(I159/ROUND(SUMIF(fCensoDiario!$B$2:$B$301,C159,fCensoDiario!$E$2:$E$301)/SUMIF(fCensoDiario!$B$2:$B$301,C159,fCensoDiario!$K$2:$K$301),1)*INDEX(dUnidade!$H:$H,MATCH(C159,dUnidade!$A:$A,0)),0)
A160: DES-0019 | B160: INF-B08 | C160: INF | D160: P10186 | E160: MD06 | F160: 46311.893 | H160: Em aberto | I160: 2.4 | J160: =ROUND(SUMIF(fCustoDiaria!$A$2:$A$51,C160,fCustoDiaria!$E$2:$E$51),2) | K160: =ROUND(I160*J160,0) | L160: =ROUND(I160/ROUND(SUMIF(fCensoDiario!$B$2:$B$301,C160,fCensoDiario!$E$2:$E$301)/SUMIF(fCensoDiario!$B$2:$B$301,C160,fCensoDiario!$K$2:$K$301),1),2) | M160: =ROUND(I160/ROUND(SUMIF(fCensoDiario!$B$2:$B$301,C160,fCensoDiario!$E$2:$E$301)/SUMIF(fCensoDiario!$B$2:$B$301,C160,fCensoDiario!$K$2:$K$301),1)*INDEX(dUnidade!$H:$H,MATCH(C160,dUnidade!$A:$A,0)),0)
A161: DES-0102 | B161: CC-A01 | C161: CC | D161: P27475 | E161: MD06 | F161: 46311.955 | G161: 46312.929 | H161: Resolvido | I161: 1 | J161: =ROUND(SUMIF(fCustoDiaria!$A$2:$A$51,C161,fCustoDiaria!$E$2:$E$51),2) | K161: =ROUND(I161*J161,0) | L161: =ROUND(I161/ROUND(SUMIF(fCensoDiario!$B$2:$B$301,C161,fCensoDiario!$E$2:$E$301)/SUMIF(fCensoDiario!$B$2:$B$301,C161,fCensoDiario!$K$2:$K$301),1),2) | M161: =ROUND(I161/ROUND(SUMIF(fCensoDiario!$B$2:$B$301,C161,fCensoDiario!$E$2:$E$301)/SUMIF(fCensoDiario!$B$2:$B$301,C161,fCensoDiario!$K$2:$K$301),1)*INDEX(dUnidade!$H:$H,MATCH(C161,dUnidade!$A:$A,0)),0)
A162: DES-0080 | B162: CM-A14 | C162: CM | D162: P24718 | E162: MD02 | F162: 46311.992 | G162: 46312.435 | H162: Resolvido | I162: 0.4 | J162: =ROUND(SUMIF(fCustoDiaria!$A$2:$A$51,C162,fCustoDiaria!$E$2:$E$51),2) | K162: =ROUND(I162*J162,0) | L162: =ROUND(I162/ROUND(SUMIF(fCensoDiario!$B$2:$B$301,C162,fCensoDiario!$E$2:$E$301)/SUMIF(fCensoDiario!$B$2:$B$301,C162,fCensoDiario!$K$2:$K$301),1),2) | M162: =ROUND(I162/ROUND(SUMIF(fCensoDiario!$B$2:$B$301,C162,fCensoDiario!$E$2:$E$301)/SUMIF(fCensoDiario!$B$2:$B$301,C162,fCensoDiario!$K$2:$K$301),1)*INDEX(dUnidade!$H:$H,MATCH(C162,dUnidade!$A:$A,0)),0)
A163: DES-0127 | B163: ORT-B16 | C163: ORT | D163: P25340 | E163: MD02 | F163: 46312.001 | G163: 46314.064 | H163: Resolvido | I163: 2.1 | J163: =ROUND(SUMIF(fCustoDiaria!$A$2:$A$51,C163,fCustoDiaria!$E$2:$E$51),2) | K163: =ROUND(I163*J163,0) | L163: =ROUND(I163/ROUND(SUMIF(fCensoDiario!$B$2:$B$301,C163,fCensoDiario!$E$2:$E$301)/SUMIF(fCensoDiario!$B$2:$B$301,C163,fCensoDiario!$K$2:$K$301),1),2) | M163: =ROUND(I163/ROUND(SUMIF(fCensoDiario!$B$2:$B$301,C163,fCensoDiario!$E$2:$E$301)/SUMIF(fCensoDiario!$B$2:$B$301,C163,fCensoDiario!$K$2:$K$301),1)*INDEX(dUnidade!$H:$H,MATCH(C163,dUnidade!$A:$A,0)),0)
A164: DES-0020 | B164: UCI-A02 | C164: UCI | D164: P10124 | E164: MD03 | F164: 46312.05 | H164: Em aberto | I164: 2.2 | J164: =ROUND(SUMIF(fCustoDiaria!$A$2:$A$51,C164,fCustoDiaria!$E$2:$E$51),2) | K164: =ROUND(I164*J164,0) | L164: =ROUND(I164/ROUND(SUMIF(fCensoDiario!$B$2:$B$301,C164,fCensoDiario!$E$2:$E$301)/SUMIF(fCensoDiario!$B$2:$B$301,C164,fCensoDiario!$K$2:$K$301),1),2) | M164: =ROUND(I164/ROUND(SUMIF(fCensoDiario!$B$2:$B$301,C164,fCensoDiario!$E$2:$E$301)/SUMIF(fCensoDiario!$B$2:$B$301,C164,fCensoDiario!$K$2:$K$301),1)*INDEX(dUnidade!$H:$H,MATCH(C164,dUnidade!$A:$A,0)),0)
A165: DES-0128 | B165: ORT-B16 | C165: ORT | D165: P21757 | E165: MD02 | F165: 46312.183 | G165: 46312.639 | H165: Resolvido | I165: 0.5 | J165: =ROUND(SUMIF(fCustoDiaria!$A$2:$A$51,C165,fCustoDiaria!$E$2:$E$51),2) | K165: =ROUND(I165*J165,0) | L165: =ROUND(I165/ROUND(SUMIF(fCensoDiario!$B$2:$B$301,C165,fCensoDiario!$E$2:$E$301)/SUMIF(fCensoDiario!$B$2:$B$301,C165,fCensoDiario!$K$2:$K$301),1),2) | M165: =ROUND(I165/ROUND(SUMIF(fCensoDiario!$B$2:$B$301,C165,fCensoDiario!$E$2:$E$301)/SUMIF(fCensoDiario!$B$2:$B$301,C165,fCensoDiario!$K$2:$K$301),1)*INDEX(dUnidade!$H:$H,MATCH(C165,dUnidade!$A:$A,0)),0)
A166: DES-0007 | B166: CM-A17 | C166: CM | D166: P10016 | E166: MD04 | F166: 46312.292 | H166: Em aberto | I166: 2 | J166: =ROUND(SUMIF(fCustoDiaria!$A$2:$A$51,C166,fCustoDiaria!$E$2:$E$51),2) | K166: =ROUND(I166*J166,0) | L166: =ROUND(I166/ROUND(SUMIF(fCensoDiario!$B$2:$B$301,C166,fCensoDiario!$E$2:$E$301)/SUMIF(fCensoDiario!$B$2:$B$301,C166,fCensoDiario!$K$2:$K$301),1),2) | M166: =ROUND(I166/ROUND(SUMIF(fCensoDiario!$B$2:$B$301,C166,fCensoDiario!$E$2:$E$301)/SUMIF(fCensoDiario!$B$2:$B$301,C166,fCensoDiario!$K$2:$K$301),1)*INDEX(dUnidade!$H:$H,MATCH(C166,dUnidade!$A:$A,0)),0)
A167: DES-0004 | B167: CM-A01 | C167: CM | D167: P10001 | E167: MD08 | F167: 46312.292 | H167: Em aberto | I167: 2 | J167: =ROUND(SUMIF(fCustoDiaria!$A$2:$A$51,C167,fCustoDiaria!$E$2:$E$51),2) | K167: =ROUND(I167*J167,0) | L167: =ROUND(I167/ROUND(SUMIF(fCensoDiario!$B$2:$B$301,C167,fCensoDiario!$E$2:$E$301)/SUMIF(fCensoDiario!$B$2:$B$301,C167,fCensoDiario!$K$2:$K$301),1),2) | M167: =ROUND(I167/ROUND(SUMIF(fCensoDiario!$B$2:$B$301,C167,fCensoDiario!$E$2:$E$301)/SUMIF(fCensoDiario!$B$2:$B$301,C167,fCensoDiario!$K$2:$K$301),1)*INDEX(dUnidade!$H:$H,MATCH(C167,dUnidade!$A:$A,0)),0)
A168: DES-0021 | B168: PED-A03 | C168: PED | D168: P10133 | E168: MD08 | F168: 46312.449 | H168: Em aberto | I168: 1.8 | J168: =ROUND(SUMIF(fCustoDiaria!$A$2:$A$51,C168,fCustoDiaria!$E$2:$E$51),2) | K168: =ROUND(I168*J168,0) | L168: =ROUND(I168/ROUND(SUMIF(fCensoDiario!$B$2:$B$301,C168,fCensoDiario!$E$2:$E$301)/SUMIF(fCensoDiario!$B$2:$B$301,C168,fCensoDiario!$K$2:$K$301),1),2) | M168: =ROUND(I168/ROUND(SUMIF(fCensoDiario!$B$2:$B$301,C168,fCensoDiario!$E$2:$E$301)/SUMIF(fCensoDiario!$B$2:$B$301,C168,fCensoDiario!$K$2:$K$301),1)*INDEX(dUnidade!$H:$H,MATCH(C168,dUnidade!$A:$A,0)),0)
A169: DES-0022 | B169: UTI-A07 | C169: UTI | D169: P10110 | E169: MD08 | F169: 46312.721 | H169: Em aberto | I169: 1.6 | J169: =ROUND(SUMIF(fCustoDiaria!$A$2:$A$51,C169,fCustoDiaria!$E$2:$E$51),2) | K169: =ROUND(I169*J169,0) | L169: =ROUND(I169/ROUND(SUMIF(fCensoDiario!$B$2:$B$301,C169,fCensoDiario!$E$2:$E$301)/SUMIF(fCensoDiario!$B$2:$B$301,C169,fCensoDiario!$K$2:$K$301),1),2) | M169: =ROUND(I169/ROUND(SUMIF(fCensoDiario!$B$2:$B$301,C169,fCensoDiario!$E$2:$E$301)/SUMIF(fCensoDiario!$B$2:$B$301,C169,fCensoDiario!$K$2:$K$301),1)*INDEX(dUnidade!$H:$H,MATCH(C169,dUnidade!$A:$A,0)),0)
A170: DES-0114 | B170: ORT-B16 | C170: ORT | D170: P26143 | E170: MD03 | F170: 46312.74 | G170: 46314.071 | H170: Resolvido | I170: 1.3 | J170: =ROUND(SUMIF(fCustoDiaria!$A$2:$A$51,C170,fCustoDiaria!$E$2:$E$51),2) | K170: =ROUND(I170*J170,0) | L170: =ROUND(I170/ROUND(SUMIF(fCensoDiario!$B$2:$B$301,C170,fCensoDiario!$E$2:$E$301)/SUMIF(fCensoDiario!$B$2:$B$301,C170,fCensoDiario!$K$2:$K$301),1),2) | M170: =ROUND(I170/ROUND(SUMIF(fCensoDiario!$B$2:$B$301,C170,fCensoDiario!$E$2:$E$301)/SUMIF(fCensoDiario!$B$2:$B$301,C170,fCensoDiario!$K$2:$K$301),1)*INDEX(dUnidade!$H:$H,MATCH(C170,dUnidade!$A:$A,0)),0)
A171: DES-0062 | B171: CM-B38 | C171: CM | D171: P29809 | E171: MD02 | F171: 46312.746 | G171: 46313.477 | H171: Resolvido | I171: 0.7 | J171: =ROUND(SUMIF(fCustoDiaria!$A$2:$A$51,C171,fCustoDiaria!$E$2:$E$51),2) | K171: =ROUND(I171*J171,0) | L171: =ROUND(I171/ROUND(SUMIF(fCensoDiario!$B$2:$B$301,C171,fCensoDiario!$E$2:$E$301)/SUMIF(fCensoDiario!$B$2:$B$301,C171,fCensoDiario!$K$2:$K$301),1),2) | M171: =ROUND(I171/ROUND(SUMIF(fCensoDiario!$B$2:$B$301,C171,fCensoDiario!$E$2:$E$301)/SUMIF(fCensoDiario!$B$2:$B$301,C171,fCensoDiario!$K$2:$K$301),1)*INDEX(dUnidade!$H:$H,MATCH(C171,dUnidade!$A:$A,0)),0)
A172: DES-0052 | B172: CM-B40 | C172: CM | D172: P20462 | E172: MD02 | F172: 46312.781 | G172: 46313.182 | H172: Resolvido | I172: 0.4 | J172: =ROUND(SUMIF(fCustoDiaria!$A$2:$A$51,C172,fCustoDiaria!$E$2:$E$51),2) | K172: =ROUND(I172*J172,0) | L172: =ROUND(I172/ROUND(SUMIF(fCensoDiario!$B$2:$B$301,C172,fCensoDiario!$E$2:$E$301)/SUMIF(fCensoDiario!$B$2:$B$301,C172,fCensoDiario!$K$2:$K$301),1),2) | M172: =ROUND(I172/ROUND(SUMIF(fCensoDiario!$B$2:$B$301,C172,fCensoDiario!$E$2:$E$301)/SUMIF(fCensoDiario!$B$2:$B$301,C172,fCensoDiario!$K$2:$K$301),1)*INDEX(dUnidade!$H:$H,MATCH(C172,dUnidade!$A:$A,0)),0)
A173: DES-0088 | B173: CM-A13 | C173: CM | D173: P22793 | E173: MD03 | F173: 46312.804 | G173: 46314.213 | H173: Resolvido | I173: 1.4 | J173: =ROUND(SUMIF(fCustoDiaria!$A$2:$A$51,C173,fCustoDiaria!$E$2:$E$51),2) | K173: =ROUND(I173*J173,0) | L173: =ROUND(I173/ROUND(SUMIF(fCensoDiario!$B$2:$B$301,C173,fCensoDiario!$E$2:$E$301)/SUMIF(fCensoDiario!$B$2:$B$301,C173,fCensoDiario!$K$2:$K$301),1),2) | M173: =ROUND(I173/ROUND(SUMIF(fCensoDiario!$B$2:$B$301,C173,fCensoDiario!$E$2:$E$301)/SUMIF(fCensoDiario!$B$2:$B$301,C173,fCensoDiario!$K$2:$K$301),1)*INDEX(dUnidade!$H:$H,MATCH(C173,dUnidade!$A:$A,0)),0)
A174: DES-0013 | B174: CC-A03 | C174: CC | D174: P10055 | E174: MD03 | F174: 46312.833 | H174: Em aberto | I174: 1.5 | J174: =ROUND(SUMIF(fCustoDiaria!$A$2:$A$51,C174,fCustoDiaria!$E$2:$E$51),2) | K174: =ROUND(I174*J174,0) | L174: =ROUND(I174/ROUND(SUMIF(fCensoDiario!$B$2:$B$301,C174,fCensoDiario!$E$2:$E$301)/SUMIF(fCensoDiario!$B$2:$B$301,C174,fCensoDiario!$K$2:$K$301),1),2) | M174: =ROUND(I174/ROUND(SUMIF(fCensoDiario!$B$2:$B$301,C174,fCensoDiario!$E$2:$E$301)/SUMIF(fCensoDiario!$B$2:$B$301,C174,fCensoDiario!$K$2:$K$301),1)*INDEX(dUnidade!$H:$H,MATCH(C174,dUnidade!$A:$A,0)),0)
A175: DES-0003 | B175: CM-B48 | C175: CM | D175: P10042 | E175: MD02 | F175: 46312.884 | H175: Em aberto | I175: 1.4 | J175: =ROUND(SUMIF(fCustoDiaria!$A$2:$A$51,C175,fCustoDiaria!$E$2:$E$51),2) | K175: =ROUND(I175*J175,0) | L175: =ROUND(I175/ROUND(SUMIF(fCensoDiario!$B$2:$B$301,C175,fCensoDiario!$E$2:$E$301)/SUMIF(fCensoDiario!$B$2:$B$301,C175,fCensoDiario!$K$2:$K$301),1),2) | M175: =ROUND(I175/ROUND(SUMIF(fCensoDiario!$B$2:$B$301,C175,fCensoDiario!$E$2:$E$301)/SUMIF(fCensoDiario!$B$2:$B$301,C175,fCensoDiario!$K$2:$K$301),1)*INDEX(dUnidade!$H:$H,MATCH(C175,dUnidade!$A:$A,0)),0)
A176: DES-0092 | B176: CC-A13 | C176: CC | D176: P20140 | E176: MD04 | F176: 46312.949 | G176: 46313.858 | H176: Resolvido | I176: 0.9 | J176: =ROUND(SUMIF(fCustoDiaria!$A$2:$A$51,C176,fCustoDiaria!$E$2:$E$51),2) | K176: =ROUND(I176*J176,0) | L176: =ROUND(I176/ROUND(SUMIF(fCensoDiario!$B$2:$B$301,C176,fCensoDiario!$E$2:$E$301)/SUMIF(fCensoDiario!$B$2:$B$301,C176,fCensoDiario!$K$2:$K$301),1),2) | M176: =ROUND(I176/ROUND(SUMIF(fCensoDiario!$B$2:$B$301,C176,fCensoDiario!$E$2:$E$301)/SUMIF(fCensoDiario!$B$2:$B$301,C176,fCensoDiario!$K$2:$K$301),1)*INDEX(dUnidade!$H:$H,MATCH(C176,dUnidade!$A:$A,0)),0)
A177: DES-0016 | B177: ONC-A06 | C177: ONC | D177: P10176 | E177: MD03 | F177: 46312.986 | H177: Em aberto | I177: 1.3 | J177: =ROUND(SUMIF(fCustoDiaria!$A$2:$A$51,C177,fCustoDiaria!$E$2:$E$51),2) | K177: =ROUND(I177*J177,0) | L177: =ROUND(I177/ROUND(SUMIF(fCensoDiario!$B$2:$B$301,C177,fCensoDiario!$E$2:$E$301)/SUMIF(fCensoDiario!$B$2:$B$301,C177,fCensoDiario!$K$2:$K$301),1),2) | M177: =ROUND(I177/ROUND(SUMIF(fCensoDiario!$B$2:$B$301,C177,fCensoDiario!$E$2:$E$301)/SUMIF(fCensoDiario!$B$2:$B$301,C177,fCensoDiario!$K$2:$K$301),1)*INDEX(dUnidade!$H:$H,MATCH(C177,dUnidade!$A:$A,0)),0)
A178: DES-0098 | B178: CC-A14 | C178: CC | D178: P24601 | E178: MD03 | F178: 46313.063 | G178: 46313.713 | H178: Resolvido | I178: 0.6 | J178: =ROUND(SUMIF(fCustoDiaria!$A$2:$A$51,C178,fCustoDiaria!$E$2:$E$51),2) | K178: =ROUND(I178*J178,0) | L178: =ROUND(I178/ROUND(SUMIF(fCensoDiario!$B$2:$B$301,C178,fCensoDiario!$E$2:$E$301)/SUMIF(fCensoDiario!$B$2:$B$301,C178,fCensoDiario!$K$2:$K$301),1),2) | M178: =ROUND(I178/ROUND(SUMIF(fCensoDiario!$B$2:$B$301,C178,fCensoDiario!$E$2:$E$301)/SUMIF(fCensoDiario!$B$2:$B$301,C178,fCensoDiario!$K$2:$K$301),1)*INDEX(dUnidade!$H:$H,MATCH(C178,dUnidade!$A:$A,0)),0)
A179: DES-0017 | B179: ONC-A02 | C179: ONC | D179: P10172 | E179: MD06 | F179: 46313.249 | H179: Em aberto | I179: 1 | J179: =ROUND(SUMIF(fCustoDiaria!$A$2:$A$51,C179,fCustoDiaria!$E$2:$E$51),2) | K179: =ROUND(I179*J179,0) | L179: =ROUND(I179/ROUND(SUMIF(fCensoDiario!$B$2:$B$301,C179,fCensoDiario!$E$2:$E$301)/SUMIF(fCensoDiario!$B$2:$B$301,C179,fCensoDiario!$K$2:$K$301),1),2) | M179: =ROUND(I179/ROUND(SUMIF(fCensoDiario!$B$2:$B$301,C179,fCensoDiario!$E$2:$E$301)/SUMIF(fCensoDiario!$B$2:$B$301,C179,fCensoDiario!$K$2:$K$301),1)*INDEX(dUnidade!$H:$H,MATCH(C179,dUnidade!$A:$A,0)),0)
A180: DES-0008 | B180: CM-A02 | C180: CM | D180: P10002 | E180: MD03 | F180: 46313.326 | H180: Em aberto | I180: 1 | J180: =ROUND(SUMIF(fCustoDiaria!$A$2:$A$51,C180,fCustoDiaria!$E$2:$E$51),2) | K180: =ROUND(I180*J180,0) | L180: =ROUND(I180/ROUND(SUMIF(fCensoDiario!$B$2:$B$301,C180,fCensoDiario!$E$2:$E$301)/SUMIF(fCensoDiario!$B$2:$B$301,C180,fCensoDiario!$K$2:$K$301),1),2) | M180: =ROUND(I180/ROUND(SUMIF(fCensoDiario!$B$2:$B$301,C180,fCensoDiario!$E$2:$E$301)/SUMIF(fCensoDiario!$B$2:$B$301,C180,fCensoDiario!$K$2:$K$301),1)*INDEX(dUnidade!$H:$H,MATCH(C180,dUnidade!$A:$A,0)),0)
A181: DES-0033 | B181: CM-A23 | C181: CM | D181: P29074 | E181: MD08 | F181: 46313.344 | G181: 46313.908 | H181: Resolvido | I181: 0.6 | J181: =ROUND(SUMIF(fCustoDiaria!$A$2:$A$51,C181,fCustoDiaria!$E$2:$E$51),2) | K181: =ROUND(I181*J181,0) | L181: =ROUND(I181/ROUND(SUMIF(fCensoDiario!$B$2:$B$301,C181,fCensoDiario!$E$2:$E$301)/SUMIF(fCensoDiario!$B$2:$B$301,C181,fCensoDiario!$K$2:$K$301),1),2) | M181: =ROUND(I181/ROUND(SUMIF(fCensoDiario!$B$2:$B$301,C181,fCensoDiario!$E$2:$E$301)/SUMIF(fCensoDiario!$B$2:$B$301,C181,fCensoDiario!$K$2:$K$301),1)*INDEX(dUnidade!$H:$H,MATCH(C181,dUnidade!$A:$A,0)),0)
A182: DES-0002 | B182: CM-A27 | C182: CM | D182: P10025 | E182: MD06 | F182: 46313.401 | H182: Em aberto | I182: 0.9 | J182: =ROUND(SUMIF(fCustoDiaria!$A$2:$A$51,C182,fCustoDiaria!$E$2:$E$51),2) | K182: =ROUND(I182*J182,0) | L182: =ROUND(I182/ROUND(SUMIF(fCensoDiario!$B$2:$B$301,C182,fCensoDiario!$E$2:$E$301)/SUMIF(fCensoDiario!$B$2:$B$301,C182,fCensoDiario!$K$2:$K$301),1),2) | M182: =ROUND(I182/ROUND(SUMIF(fCensoDiario!$B$2:$B$301,C182,fCensoDiario!$E$2:$E$301)/SUMIF(fCensoDiario!$B$2:$B$301,C182,fCensoDiario!$K$2:$K$301),1)*INDEX(dUnidade!$H:$H,MATCH(C182,dUnidade!$A:$A,0)),0)

Sheet dMetas
A1: indicador | B1: meta | C1: unidade_medida | D1: sentido | E1: regra
A2: Taxa de ocupação (30 dias) | B2: 0.85 | C2: % | D2: Faixa | E2: Atenção a partir de 85%; crítico a partir de 90%
A3: Ocupação instantânea | B3: 0.85 | C3: % | D3: Faixa | E3: Crítico a partir de 90% ou com três unidades nesse patamar
A4: Média de permanência | B4: 5.8 | C4: dias | D4: Menor é melhor | E4: Meta do hospital ponderada pelos pacientes-dia das metas das unidades
A5: Pacientes em vermelho (Kanban) | B5: 0.15 | C5: % dos internados | D5: Menor é melhor | E5: Atenção a partir de 15%; crítico a partir de 25%
A6: Saídas até 10 h | B6: 0.3 | C6: % das saídas | D6: Maior é melhor | E6: Crítico abaixo de 15%; atenção abaixo de 30%
A7: Alta médica até a saída | B7: 120 | C7: minutos (mediana) | D7: Menor é melhor | E7: Acima de 120 min indica alta tardia
A8: Saída até início da higienização | B8: 30 | C8: minutos (mediana) | D8: Menor é melhor | E8: Acima de 30 min indica demora em acionar a limpeza
A9: Higienização concorrente | B9: 60 | C9: minutos | D9: Menor é melhor | E9: Acima do alvo atrasa a liberação do leito
A10: Higienização terminal | B10: 120 | C10: minutos | D10: Menor é melhor | E10: Acima do alvo atrasa a liberação do leito
A11: Espera por leito | B11: 6 | C11: horas | D11: Menor é melhor | E11: Crítico com espera pendente acima de 24 h ou menos de 40% atendidos em até 6 h
A12: Leitos-dia perdidos com desocupação | B12: 0.04 | C12: % dos leitos-dia | D12: Menor é melhor | E12: Atenção a partir de 4%; crítico a partir de 8%
A13: Saldo de leitos do dia | B13: 2 | C13: leitos | D13: Maior é melhor | E13: Crítico com saldo negativo; atenção com saldo até 2

Sheet Conferencia
A1: Conferência dos indicadores: base × painel
A3: Indicador | B3: Como é calculado na base | C3: Calculado na base | D3: Valor no painel | E3: Diferença | F3: Tolerância
A4: Taxa de ocupação (30 dias) | B4: Σ pacientes-dia ÷ Σ leitos operacionais | C4: =SUM(fCensoDiario!$E$2:$E$301)/SUM(fCensoDiario!$C$2:$C$301) | D4: 0.844 | E4: =C4-D4 | F4: 0.0005
A5: Ocupação instantânea (censo) | B5: Ocupados ÷ (leitos − bloqueados) | C5: =COUNTIF(fLeitosCenso!$C$2:$C$231,"Ocupado")/(COUNTA(fLeitosCenso!$A$2:$A$231)-COUNTIF(fLeitosCenso!$C$2:$C$231,"Bloqueado")) | D5: 0.849 | E5: =C5-D5 | F5: 0.0005
A6: Média de permanência (dias) | B6: Σ pacientes-dia ÷ Σ saídas | C6: =SUM(fCensoDiario!$E$2:$E$301)/SUM(fCensoDiario!$K$2:$K$301) | D6: 5.6 | E6: =C6-D6 | F6: 0.05
A7: Índice de giro (saídas por leito) | B7: Σ saídas ÷ leitos operacionais médios | C7: =SUM(fCensoDiario!$K$2:$K$301)/(SUM(fCensoDiario!$C$2:$C$301)/30) | D7: 4.5 | E7: =C7-D7 | F7: 0.05
A8: Mortalidade institucional | B8: (óbitos − óbitos até 24 h) ÷ saídas | C8: =(SUM(fCensoDiario!$H$2:$H$301)-SUM(fCensoDiario!$I$2:$I$301))/SUM(fCensoDiario!$K$2:$K$301) | D8: 0.023 | E8: =C8-D8 | F8: 0.0005
A9: Leitos vagos (censo) | B9: Contagem de leitos vagos | C9: =COUNTIF(fLeitosCenso!$C$2:$C$231,"Vago") | D9: 14 | E9: =C9-D9 | F9: 0
A10: Pacientes em vermelho (Kanban) | B10: Contagem de classificação Vermelho | C10: =COUNTIF(fLeitosCenso!$N$2:$N$231,"Vermelho") | D10: 29 | E10: =C10-D10 | F10: 0
A11: Pacientes de alta aguardando desocupação | B11: Contagem da etapa Aguardando desocupação | C11: =COUNTIF(fLeitosCenso!$D$2:$D$231,"Aguardando desocupação") | D11: 22 | E11: =C11-D11 | F11: 0
A12: Solicitações pendentes no NIR | B12: Contagem de pedidos pendentes | C12: =COUNTIF(fSolicitacoes!$G$2:$G$832,"Pendente") | D12: 10 | E12: =C12-D12 | F12: 0
A13: Leitos-dia perdidos com desocupação | B13: Σ dias de atraso | C13: =SUM(fAtrasosDesocupacao!$I$2:$I$182) | D13: 578.9 | E13: =C13-D13 | F13: 0.05
A14: Custo da espera nos 30 dias (R$) | B14: Σ custo dos episódios | C14: =SUM(fAtrasosDesocupacao!$K$2:$K$182) | D14: 665016 | E14: =C14-D14 | F14: 0.5
A16: Resultado | B16: =IF(SUMPRODUCT((ABS(E4:E14)>F4:F14)*1)=0,"Base confere com o painel","Revisar: há diferença acima da tolerância")
A17: Nota | B17: O painel exibe valores arredondados; a tolerância de cada linha corresponde à precisão exibida.

Sheet Dicionario
A1: tabela | B1: coluna | C1: tipo | D1: descricao | E1: relacionamento
A2: dUnidade | B2: id_unidade | C2: texto | D2: Sigla da unidade de internação (chave)
A3: dUnidade | B3: unidade | C3: texto | D3: Nome da unidade
A4: dUnidade | B4: tipo_leito | C4: texto | D4: Perfil assistencial do leito
A5: dUnidade | B5: leitos_instalados | C5: inteiro | D5: Leitos instalados no censo de referência
A6: dUnidade | B6: meta_taxa_ocupacao | C6: percentual | D6: Meta de taxa de ocupação da unidade
A7: dUnidade | B7: meta_media_permanencia | C7: decimal | D7: Meta de média de permanência, em dias
A8: dUnidade | B8: custo_diaria | C8: moeda | D8: Custo padrão da diária (soma dos componentes de fCustoDiaria)
A9: dUnidade | B9: receita_media_aih | C9: moeda | D9: Receita média por internação (AIH) usada para estimar a receita não realizada
A10: dLeito | B10: id_leito | C10: texto | D10: Código do leito (unidade-ala+número)
A11: dLeito | B11: id_unidade | C11: texto | D11: Unidade do leito | E11: dUnidade[id_unidade]
A12: dLeito | B12: ala | C12: texto | D12: Ala da unidade (A ou B)
A13: dLeito | B13: numero | C13: inteiro | D13: Número do leito na ala
A14: dCalendario | B14: data | C14: data | D14: Dia do período de análise (chave)
A15: dCalendario | B15: dia | C15: inteiro | D15: Dia do mês
A16: dCalendario | B16: mes | C16: inteiro | D16: Mês (1 a 12)
A17: dCalendario | B17: nome_mes | C17: texto | D17: Nome do mês
A18: dCalendario | B18: ano | C18: inteiro | D18: Ano
A19: dCalendario | B19: dia_semana | C19: inteiro | D19: Dia da semana (1 = segunda, 7 = domingo)
A20: dCalendario | B20: nome_dia | C20: texto | D20: Nome do dia da semana
A21: dCalendario | B21: fim_de_semana | C21: texto | D21: Sim para sábado e domingo
A22: dProcedimento | B22: id_procedimento | C22: texto | D22: Código do procedimento (chave)
A23: dProcedimento | B23: procedimento | C23: texto | D23: Procedimento principal da internação
A24: dProcedimento | B24: id_unidade | C24: texto | D24: Unidade em que o procedimento é realizado | E24: dUnidade[id_unidade]
A25: dProcedimento | B25: permanencia_ref_dias | C25: inteiro | D25: Tempo de referência de permanência (padrão SIGTAP simplificado), base do Kanban
A26: dMotivoDesocupacao | B26: id_motivo | C26: texto | D26: Código do motivo de atraso na desocupação (chave)
A27: dMotivoDesocupacao | B27: motivo | C27: texto | D27: Motivo não clínico que impede a saída após a alta médica
A28: dMotivoDesocupacao | B28: area_responsavel | C28: texto | D28: Área responsável por destravar o caso
A29: dMotivoDesocupacao | B29: acao_recomendada | C29: texto | D29: Prática recomendada de planejamento de alta
A30: dComponenteCusto | B30: id_componente | C30: texto | D30: Código do componente de custo (chave)
A31: dComponenteCusto | B31: componente | C31: texto | D31: Componente da diária hospitalar
A32: dComponenteCusto | B32: fator_dia_de_espera | C32: percentual | D32: Parte do componente que continua sendo gasta enquanto o paciente de alta espera no leito
A33: fCensoDiario | B33: data | C33: data | D33: Dia do censo | E33: dCalendario[data]
A34: fCensoDiario | B34: id_unidade | C34: texto | D34: Unidade | E34: dUnidade[id_unidade]
A35: fCensoDiario | B35: leitos_operacionais | C35: inteiro | D35: Leitos instalados menos bloqueados no dia
A36: fCensoDiario | B36: leitos_bloqueados | C36: inteiro | D36: Leitos fora de operação no dia
A37: fCensoDiario | B37: pacientes_dia | C37: inteiro | D37: Pacientes internados no censo do dia (pacientes-dia)
A38: fCensoDiario | B38: admissoes | C38: inteiro | D38: Entradas na unidade no dia
A39: fCensoDiario | B39: altas | C39: inteiro | D39: Altas no dia
A40: fCensoDiario | B40: obitos | C40: inteiro | D40: Óbitos no dia
A41: fCensoDiario | B41: obitos_ate_24h | C41: inteiro | D41: Óbitos com menos de 24 h de internação (fora da mortalidade institucional)
A42: fCensoDiario | B42: transferencias_externas | C42: inteiro | D42: Transferências para outros serviços no dia
A43: fCensoDiario | B43: saidas | C43: inteiro (fórmula) | D43: Saídas = altas + óbitos + transferências externas
A44: fCensoDiario | B44: taxa_ocupacao | C44: percentual (fórmula) | D44: Taxa de ocupação do dia = pacientes-dia ÷ leitos operacionais
A45: fLeitosCenso | B45: id_leito | C45: texto | D45: Leito | E45: dLeito[id_leito]
A46: fLeitosCenso | B46: id_unidade | C46: texto | D46: Unidade | E46: dUnidade[id_unidade]
A47: fLeitosCenso | B47: status | C47: texto | D47: Situação no censo: Ocupado, Vago, Em higienização, Reservado ou Bloqueado
A48: fLeitosCenso | B48: etapa_fluxo | C48: texto | D48: Etapa do fluxo do leito (coluna do Kanban)
A49: fLeitosCenso | B49: prontuario | C49: texto | D49: Prontuário fictício do paciente
A50: fLeitosCenso | B50: iniciais | C50: texto | D50: Iniciais fictícias do paciente
A51: fLeitosCenso | B51: idade | C51: inteiro | D51: Idade em anos
A52: fLeitosCenso | B52: sexo | C52: texto | D52: Sexo (F ou M)
A53: fLeitosCenso | B53: id_procedimento | C53: texto | D53: Procedimento da internação | E53: dProcedimento[id_procedimento]
A54: fLeitosCenso | B54: data_internacao | C54: data e hora | D54: Data e hora da internação
A55: fLeitosCenso | B55: dias_internacao | C55: inteiro (fórmula) | D55: Dias completos de internação até a data de referência
A56: fLeitosCenso | B56: permanencia_ref_dias | C56: inteiro (fórmula) | D56: Tempo de referência do procedimento
A57: fLeitosCenso | B57: razao_permanencia | C57: decimal (fórmula) | D57: Dias de internação ÷ tempo de referência
A58: fLeitosCenso | B58: classificacao_kanban | C58: texto (fórmula) | D58: Verde até metade do tempo de referência; Amarelo até o tempo; Vermelho acima
A59: fLeitosCenso | B59: previsao_alta | C59: data | D59: Data prevista para a alta
A60: fLeitosCenso | B60: origem | C60: texto | D60: Porta de entrada do paciente
A61: fLeitosCenso | B61: pendencia | C61: texto | D61: Pendência que atrasa a alta ou a desocupação
A62: fLeitosCenso | B62: motivo_bloqueio | C62: texto | D62: Motivo do bloqueio do leito
A63: fLeitosCenso | B63: bloqueado_desde | C63: data e hora | D63: Início do bloqueio
A64: fLeitosCenso | B64: tipo_higienizacao | C64: texto | D64: Concorrente ou terminal
A65: fLeitosCenso | B65: inicio_higienizacao | C65: data e hora | D65: Início da higienização em andamento
... A69: fSaidas | B69: id_saida | C69: texto | D69: Código da saída (chave)
A70: fSaidas | B70: data | C70: data | D70: Dia da saída | E70: dCalendario[data]
A71: fSaidas | B71: id_unidade | C71: texto | D71: Unidade | E71: dUnidade[id_unidade]
A72: fSaidas | B72: tipo_saida | C72: texto | D72: Alta, Óbito ou Transferência externa
A73: fSaidas | B73: alta_medica | C73: data e hora | D73: Registro da alta médica
A74: fSaidas | B74: saida_paciente | C74: data e hora | D74: Saída física do paciente do leito
A75: fSaidas | B75: inicio_higienizacao | C75: data e hora | D75: Início da limpeza do leito
A76: fSaidas | B76: fim_higienizacao | C76: data e hora | D76: Fim da limpeza do leito
A77: fSaidas | B77: tipo_higienizacao | C77: texto | D77: Concorrente ou terminal
A78: fSaidas | B78: nova_ocupacao | C78: data e hora | D78: Entrada do próximo paciente no leito
A79: fSaidas | B79: min_alta_ate_saida | C79: inteiro | D79: Minutos entre a alta médica e a saída
A80: fSaidas | B80: min_saida_ate_inicio_hig | C80: inteiro | D80: Minutos entre a saída e o início da limpeza
A81: fSaidas | B81: min_higienizacao | C81: inteiro | D81: Duração da higienização em minutos
A82: fSaidas | B82: min_liberacao_ate_ocupacao | C82: inteiro | D82: Minutos entre o leito liberado e a nova ocupação
A83: fSaidas | B83: min_giro_total | C83: inteiro | D83: Minutos da saída até a nova ocupação
... A87: fSolicitacoes | B87: origem | C87: texto | D87: Origem do pedido
A88: fSolicitacoes | B88: id_unidade_destino | C88: texto | D88: Unidade solicitada | E88: dUnidade[id_unidade]
A89: fSolicitacoes | B89: prioridade | C89: texto | D89: Emergência, Urgência ou Eletiva
A90: fSolicitacoes | B90: data_alocacao | C90: data e hora | D90: Alocação do leito (vazio se pendente ou cancelado)
A91: fSolicitacoes | B91: status | C91: texto | D91: Atendida, Cancelada ou Pendente
A92: fSolicitacoes | B92: tempo_espera_h | C92: decimal | D92: Horas entre o pedido e a alocação (pendentes: até o censo)
A93: fSolicitacoes | B93: atendida_ate_6h | C93: texto (fórmula) | D93: Sim quando atendida em até 6 h
A94: fCustoDiaria | B94: id_unidade | C94: texto | D94: Unidade | E94: dUnidade[id_unidade]
A95: fCustoDiaria | B95: id_componente | C95: texto | D95: Componente da diária | E95: dComponenteCusto[id_componente]
A96: fCustoDiaria | B96: valor_diaria | C96: moeda | D96: Valor do componente na diária padrão
A97: fCustoDiaria | B97: fator_dia_de_espera | C97: percentual (fórmula) | D97: Fator do componente que continua no dia de espera
A98: fCustoDiaria | B98: valor_dia_espera | C98: moeda (fórmula) | D98: Valor do componente por dia de espera
A99: fAtrasosDesocupacao | B99: id_atraso | C99: texto | D99: Código do episódio (chave)
A100: fAtrasosDesocupacao | B100: id_leito | C100: texto | D100: Leito ocupado durante a espera | E100: dLeito[id_leito]
A101: fAtrasosDesocupacao | B101: id_unidade | C101: texto | D101: Unidade | E101: dUnidade[id_unidade]
A102: fAtrasosDesocupacao | B102: prontuario | C102: texto | D102: Prontuário fictício
A103: fAtrasosDesocupacao | B103: id_motivo | C103: texto | D103: Motivo do atraso | E103: dMotivoDesocupacao[id_motivo]
A104: fAtrasosDesocupacao | B104: data_alta_medica | C104: data e hora | D104: Alta médica (início da espera)
A105: fAtrasosDesocupacao | B105: data_desocupacao | C105: data e hora | D105: Saída do leito (vazio se em aberto)
A106: fAtrasosDesocupacao | B106: situacao | C106: texto | D106: Resolvido ou Em aberto
...
